Workbook
Name Categories: OFFSET('[1]Admin & Settings'!$C$10,1,,COUNTA('[1]Admin & Settings'!$C$10:$C$33)-1,1)
Name Categories: OFFSET('[1]Admin & Settings'!$C$10,1,,COUNTA('[1]Admin & Settings'!$C$10:$C$33)-1,1)
Name Categories: OFFSET('[1]Admin & Settings'!$C$10,1,,COUNTA('[1]Admin & Settings'!$C$10:$C$33)-1,1)
Name Categories: OFFSET('[1]Admin & Settings'!$C$10,1,,COUNTA('[1]Admin & Settings'!$C$10:$C$33)-1,1)
Name Categories: OFFSET('[2]Admin & Settings'!$C$10,1,,COUNTA('[2]Admin & Settings'!$C$10:$C$33)-1,1)
Name Months: [3]Expenses!#REF!
Name Status: [4]TE!$AB$4:$AB$6
Name Status: [4]TE!$AB$4:$AB$6
Name Status: [4]TE!$AB$4:$AB$6
Name Status: [4]TE!$AB$4:$AB$6
Name Status: [5]TE!$AB$4:$AB$6
Name Status: [5]TE!$AB$4:$AB$6
Name Status: [6]TE!$AB$4:$AB$6
Name Status: [5]TE!$AB$4:$AB$6
Name Status: [6]TE!$AB$4:$AB$6
Name Status: TE!#REF!
Name valHighlight: IFERROR(IF(AM!#REF!="Yes", TRUE, FALSE),FALSE)
Name valHighlight: IFERROR(IF(AN!#REF!="Yes", TRUE, FALSE),FALSE)
Name valHighlight: IFERROR(IF(BT!#REF!="Yes", TRUE, FALSE),FALSE)
Name valHighlight: IFERROR(IF(CP!#REF!="Yes", TRUE, FALSE),FALSE)
Name valHighlight: IFERROR(IF(DH!#REF!="Yes", TRUE, FALSE),FALSE)
Name valHighlight: IFERROR(IF(EM!#REF!="Yes", TRUE, FALSE),FALSE)
Name valHighlight: IFERROR(IF(ET!#REF!="Yes", TRUE, FALSE),FALSE)
Name valHighlight: IFERROR(IF(FR!#REF!="Yes", TRUE, FALSE),FALSE)
Name valHighlight: IFERROR(IF(GE!#REF!="Yes", TRUE, FALSE),FALSE)
Name valHighlight: IFERROR(IF(GS!#REF!="Yes", TRUE, FALSE),FALSE)
Name valHighlight: IFERROR(IF(JM!#REF!="Yes", TRUE, FALSE),FALSE)
Name valHighlight: IFERROR(IF(ML!#REF!="Yes", TRUE, FALSE),FALSE)
Name valHighlight: IFERROR(IF(RF!#REF!="Yes", TRUE, FALSE),FALSE)
Name valHighlight: IFERROR(IF(TE!#REF!="Yes", TRUE, FALSE),FALSE)
Name valHighlight: IFERROR(IF(#REF!="Yes", TRUE, FALSE),FALSE)

Sheet -vPayment
A1: 825 | B1: v0128 | E1: DH | F1: =F4-(SUM(Table7[[#All],[PAYMENT DH]])) -> -11037.28 | G1: EM | H1: =H4-(SUM(Table7[[#All],[PAYMENT EM]])) -> 325420 | I1: FR | J1: =J4-SUM(I5:I29) -> -9284.5 | K1: TE | L1: =L4-SUM(K5:K29) -> 160533.5 | M1: GE | N1: =N4-SUM(M5:M29) -> 72256.5 | O1: GS | P1: =P4-SUM(O5:O29) -> 5115 | Q1: BT | R1: =R4-SUM(Q5:Q29) -> 17400 | S1: JM | T1: =T4-SUM(Table7[PAYMENT JM]) -> 22000 | U1: ML | V1: =V4-SUM(Table7[PAYMENT ML]) -> 192482 | W1: ET | X1: =X4-SUM(Table7[PAYMENT ET]) -> 119315 | Y1: AM | Z1: =Z4-SUM(Y4:Y29) -> 114240 | AA1: RF | AB1: =AB4-SUM(AA4:AA29) -> 77185 | AC1: CP | AD1: =AD4-SUM(AC4:AC29) -> 30000 | AE1: AN | AF1: =AF4-SUM(AE4:AE29) -> 12000
A2: USD MXN RATE | B2: TOTAL AQ MXN | C2: VENDOR PAYMENT TRACKING | E2: DELFINO HERNANDEZ | G2: EMMANUEL DE LOS SANTOS | I2: FOUNTAIN ROCK | K2: TELLEZ GALERY | M2: GERARDO DE GANTE | O2: GIFT SHOP | Q2: BERNARDO TELLEZ | S2: JOSE MEZA | U2: MARIA LUISA AND JAIR | W2: LALO TELLEZ | Y2: ALEJANDRO AND FANY MEZA | AA2: ALEJANDRO AND FANY MEZA | AC2: CANTERA PUEBLA | AE2: ANGEL CABRERA
A3: 18 | B3: =RF!K2+AM!K2+JM!K2+AN!K2+CP!K2+ML!K2+EM!K2+DH!K2+FR!K2+TE!K2+GE!K2+GS!K2+BT!K2+ET!K2 -> 3052411.3 | E3: PAYMENT DH | F3: BALANCE DH | G3: PAYMENT EM | H3: BALANCE EM | I3: PAYMEN FR | J3: BALANCE FR | K3: PAYMENT TE | L3: BALANCE TE | M3: PAYMENT GE | N3: BALANCE GE | O3: PAYMENT LH2 | P3: BALANCE GS3 | Q3: PAYMENTBT | R3: BALANCEBT | S3: PAYMENT JM | T3: BALANCE JM | U3: PAYMENT ML | V3: BALANCE ML | W3: PAYMENT ET | X3: BALANCE MT | Y3: PAYMENT AM | Z3: BALANCE AM | AA3: PAYMENT AM | AB3: BALANCE AM | AC3: PAYMENT CP | AD3: BALANCE CP | AE3: PAYMENT CP | AF3: BALANCE CP
A4: SHIPPING RECORD | C4: TYPE | D4: FROM VENDOR SHEET | E4: FROM DH | F4: =DH!K2 -> 348472.8 | G4: FROM EM | H4: =EM!K2 -> 779315.5 | J4: =[5]FR!K2 -> 135715.5 | K4: FROM TE | L4: =[5]TE!S1 -> 452094 | M4: FROM GE | N4: =[5]GE!K2 -> 150221.5 | O4: FROM GS | P4: =[5]GS!S2 -> 61290 | Q4: FROM BT | R4: =[5]BT!K2 -> 104500 | S4: FROM JM | T4: =JM!K2 -> 476680 | V4: =ML!K2 -> 192482 | X4: =ET!K2 -> 119315 | Z4: =AM!K2 -> 114240 | AB4: =RF!K2 -> 77185 | AD4: =CP!K2 -> 30000 | AF4: =AN!K2 -> 12000
A5: TRK1 | B5: 666790 | C5: DIRECT WIRE | D5: 07/30/2025 | F5: =F4-Table7[[#This Row],[PAYMENT DH]] -> 348472.8 | H5: =H4-Table7[[#This Row],[PAYMENT EM]] -> 779315.5 | J5: =J4-Table7[[#This Row],[PAYMEN FR]] -> 135715.5 | K5: 237760.5 | L5: =L4-Table7[[#This Row],[PAYMENT TE]] -> 214333.5 | N5: =N4-Table7[[#This Row],[PAYMENT GE]] -> 150221.5 | P5: =P4-Table7[[#This Row],[PAYMENT LH2]] -> 61290 | R5: =R4-Table7[[#This Row],[PAYMENTBT]] -> 104500 | T5: =T4-S5 -> 476680 | V5: =V4-Table7[[#This Row],[PAYMENT ML]] -> 192482 | X5: =X4-W5 -> 119315 | Z5: =Z4-Y5 -> 114240 | AB5: =AB4-AA5 -> 77185 | AD5: =AD4-AC5 -> 30000 | AF5: =AF4-AE5 -> 12000
A6: TRK2 | B6: 493962.54 | C6: CASH | D6: 07/31/2025 | F6: =F5-Table7[[#This Row],[PAYMENT DH]] -> 348472.8 | H6: =H5-Table7[[#This Row],[PAYMENT EM]] -> 779315.5 | J6: =J5-Table7[[#This Row],[PAYMEN FR]] -> 135715.5 | L6: =L5-Table7[[#This Row],[PAYMENT TE]] -> 214333.5 | N6: =N5-Table7[[#This Row],[PAYMENT GE]] -> 150221.5 | O6: 18000 | P6: =P5-Table7[[#This Row],[PAYMENT LH2]] -> 43290 | R6: =R5-Table7[[#This Row],[PAYMENTBT]] -> 104500 | T6: =T5-S6 -> 476680 | V6: =V5-Table7[[#This Row],[PAYMENT ML]] -> 192482 | X6: =X5-W6 -> 119315 | Z6: =Z5-Y6 -> 114240 | AB6: =AB5-AA6 -> 77185 | AD6: =AD5-AC6 -> 30000 | AF6: =AF5-AE6 -> 12000
A7: TRK3 | B7: 253320.36 | C7: CASH | D7: 07/31/2025 | F7: =F6-Table7[[#This Row],[PAYMENT DH]] -> 348472.8 | H7: =H6-Table7[[#This Row],[PAYMENT EM]] -> 779315.5 | J7: =J6-Table7[[#This Row],[PAYMEN FR]] -> 135715.5 | L7: =L6-Table7[[#This Row],[PAYMENT TE]] -> 214333.5 | N7: =N6-Table7[[#This Row],[PAYMENT GE]] -> 150221.5 | O7: 27000 | P7: =P6-Table7[[#This Row],[PAYMENT LH2]] -> 16290 | R7: =R6-Table7[[#This Row],[PAYMENTBT]] -> 104500 | T7: =T6-S7 -> 476680 | V7: =V6-Table7[[#This Row],[PAYMENT ML]] -> 192482 | X7: =X6-W7 -> 119315 | Z7: =Z6-Y7 -> 114240 | AB7: =AB6-AA7 -> 77185 | AD7: =AD6-AC7 -> 30000 | AF7: =AF6-AE7 -> 12000
A8: ='-TRK4'!A2 -> TRK4 | B8: =RF!K2+AM!K2+EM!K1+JM!K1+ML!K1+TE!K1+GE!K1+BT!K1+ET!K2 -> 1424429.5 | C8: CASH W | D8: 6/7/25 | E8: 100000 | F8: =F7-Table7[[#This Row],[PAYMENT DH]] -> 248472.8 | H8: =H7-Table7[[#This Row],[PAYMENT EM]] -> 779315.5 | J8: =J7-Table7[[#This Row],[PAYMEN FR]] -> 135715.5 | L8: =L7-Table7[[#This Row],[PAYMENT TE]] -> 214333.5 | N8: =N7-Table7[[#This Row],[PAYMENT GE]] -> 150221.5 | P8: =P7-Table7[[#This Row],[PAYMENT LH2]] -> 16290 | R8: =R7-Table7[[#This Row],[PAYMENTBT]] -> 104500 | T8: =T7-S8 -> 476680 | V8: =V7-Table7[[#This Row],[PAYMENT ML]] -> 192482 | X8: =X7-W8 -> 119315 | Z8: =Z7-Y8 -> 114240 | AB8: =AB7-AA8 -> 77185 | AD8: =AD7-AC8 -> 30000 | AF8: =AF7-AE8 -> 12000
A9: T SHIPPED | B9: =SUM(B5:B8) -> 2838502.4 | C9: IVA 10641.6 | D9: 8/13/25 | E9: 66510.08 | F9: =F8-Table7[[#This Row],[PAYMENT DH]] -> 181962.72 | H9: =H8-Table7[[#This Row],[PAYMENT EM]] -> 779315.5 | J9: =J8-Table7[[#This Row],[PAYMEN FR]] -> 135715.5 | L9: =L8-Table7[[#This Row],[PAYMENT TE]] -> 214333.5 | N9: =N8-Table7[[#This Row],[PAYMENT GE]] -> 150221.5 | P9: =P8-Table7[[#This Row],[PAYMENT LH2]] -> 16290 | R9: =R8-Table7[[#This Row],[PAYMENTBT]] -> 104500 | T9: =T8-S9 -> 476680 | V9: =V8-Table7[[#This Row],[PAYMENT ML]] -> 192482 | X9: =X8-W9 -> 119315 | Z9: =Z8-Y9 -> 114240 | AB9: =AB8-AA9 -> 77185 | AD9: =AD8-AC9 -> 30000 | AF9: =AF8-AE9 -> 12000
A10: IN WAREHOUSE | B10: =B3-B9 -> 213908.9 | C10: CASH | D10: 5/30/25 | F10: =F9-Table7[[#This Row],[PAYMENT DH]] -> 181962.72 | H10: =H9-Table7[[#This Row],[PAYMENT EM]] -> 779315.5 | J10: =J9-Table7[[#This Row],[PAYMEN FR]] -> 135715.5 | L10: =L9-Table7[[#This Row],[PAYMENT TE]] -> 214333.5 | N10: =N9-Table7[[#This Row],[PAYMENT GE]] -> 150221.5 | P10: =P9-Table7[[#This Row],[PAYMENT LH2]] -> 16290 | Q10: 60100 | R10: =R9-Table7[[#This Row],[PAYMENTBT]] -> 44400 | T10: =T9-S10 -> 476680 | V10: =V9-Table7[[#This Row],[PAYMENT ML]] -> 192482 | X10: =X9-W10 -> 119315 | Z10: =Z9-Y10 -> 114240 | AB10: =AB9-AA10 -> 77185 | AD10: =AD9-AC10 -> 30000 | AF10: =AF9-AE10 -> 12000
C11: CASH | D11: 6/18/25 | F11: =F10-Table7[[#This Row],[PAYMENT DH]] -> 181962.72 | H11: =H10-Table7[[#This Row],[PAYMENT EM]] -> 779315.5 | I11: 120000 | J11: =J10-Table7[[#This Row],[PAYMEN FR]] -> 15715.5 | L11: =L10-Table7[[#This Row],[PAYMENT TE]] -> 214333.5 | N11: =N10-Table7[[#This Row],[PAYMENT GE]] -> 150221.5 | P11: =P10-Table7[[#This Row],[PAYMENT LH2]] -> 16290 | R11: =R10-Table7[[#This Row],[PAYMENTBT]] -> 44400 | T11: =T10-S11 -> 476680 | V11: =V10-Table7[[#This Row],[PAYMENT ML]] -> 192482 | X11: =X10-W11 -> 119315 | Z11: =Z10-Y11 -> 114240 | AB11: =AB10-AA11 -> 77185 | AD11: =AD10-AC11 -> 30000 | AF11: =AF10-AE11 -> 12000
C12: CASH | D12: 8/12/25 | F12: =F11-Table7[[#This Row],[PAYMENT DH]] -> 181962.72 | H12: =H11-Table7[[#This Row],[PAYMENT EM]] -> 779315.5 | I12: 25000 | J12: =J11-Table7[[#This Row],[PAYMEN FR]] -> -9284.5 | L12: =L11-Table7[[#This Row],[PAYMENT TE]] -> 214333.5 | N12: =N11-Table7[[#This Row],[PAYMENT GE]] -> 150221.5 | P12: =P11-Table7[[#This Row],[PAYMENT LH2]] -> 16290 | R12: =R11-Table7[[#This Row],[PAYMENTBT]] -> 44400 | T12: =T11-S12 -> 476680 | V12: =V11-Table7[[#This Row],[PAYMENT ML]] -> 192482 | X12: =X11-W12 -> 119315 | Z12: =Z11-Y12 -> 114240 | AB12: =AB11-AA12 -> 77185 | AD12: =AD11-AC12 -> 30000 | AF12: =AF11-AE12 -> 12000
C13: CASH CHAD | D13: 06/07/2025 | F13: =F12-Table7[[#This Row],[PAYMENT DH]] -> 181962.72 | H13: =H12-Table7[[#This Row],[PAYMENT EM]] -> 779315.5 | J13: =J12-Table7[[#This Row],[PAYMEN FR]] -> -9284.5 | L13: =L12-Table7[[#This Row],[PAYMENT TE]] -> 214333.5 | M13: 30000 | N13: =N12-Table7[[#This Row],[PAYMENT GE]] -> 120221.5 | P13: =P12-Table7[[#This Row],[PAYMENT LH2]] -> 16290 | R13: =R12-Table7[[#This Row],[PAYMENTBT]] -> 44400 | T13: =T12-S13 -> 476680 | V13: =V12-Table7[[#This Row],[PAYMENT ML]] -> 192482 | X13: =X12-W13 -> 119315 | Z13: =Z12-Y13 -> 114240 | AB13: =AB12-AA13 -> 77185 | AD13: =AD12-AC13 -> 30000 | AF13: =AF12-AE13 -> 12000
C14: IVA 7674.40 | D14: 8/23/2025 | F14: =F13-Table7[[#This Row],[PAYMENT DH]] -> 181962.72 | H14: =H13-Table7[[#This Row],[PAYMENT EM]] -> 779315.5 | J14: =J13-Table7[[#This Row],[PAYMEN FR]] -> -9284.5 | L14: =L13-Table7[[#This Row],[PAYMENT TE]] -> 214333.5 | M14: 47965 | N14: =N13-Table7[[#This Row],[PAYMENT GE]] -> 72256.5 | P14: =P13-Table7[[#This Row],[PAYMENT LH2]] -> 16290 | R14: =R13-Table7[[#This Row],[PAYMENTBT]] -> 44400 | T14: =T13-S14 -> 476680 | V14: =V13-Table7[[#This Row],[PAYMENT ML]] -> 192482 | X14: =X13-W14 -> 119315 | Z14: =Z13-Y14 -> 114240 | AB14: =AB13-AA14 -> 77185 | AD14: =AD13-AC14 -> 30000 | AF14: =AF13-AE14 -> 12000
C15: CASH | D15: 8/31/2025 | F15: =F14-Table7[[#This Row],[PAYMENT DH]] -> 181962.72 | H15: =H14-Table7[[#This Row],[PAYMENT EM]] -> 779315.5 | J15: =J14-Table7[[#This Row],[PAYMEN FR]] -> -9284.5 | L15: =L14-Table7[[#This Row],[PAYMENT TE]] -> 214333.5 | N15: =N14-Table7[[#This Row],[PAYMENT GE]] -> 72256.5 | O15: 11175 | P15: =P14-Table7[[#This Row],[PAYMENT LH2]] -> 5115 | R15: =R14-Table7[[#This Row],[PAYMENTBT]] -> 44400 | T15: =T14-S15 -> 476680 | V15: =V14-Table7[[#This Row],[PAYMENT ML]] -> 192482 | X15: =X14-W15 -> 119315 | Z15: =Z14-Y15 -> 114240 | AB15: =AB14-AA15 -> 77185 | AD15: =AD14-AC15 -> 30000 | AF15: =AF14-AE15 -> 12000
C16: IVA 51814 | D16: 8/25/2025 | F16: =F15-Table7[[#This Row],[PAYMENT DH]] -> 181962.72 | G16: 323838.5 | H16: =H15-Table7[[#This Row],[PAYMENT EM]] -> 455477 | J16: =J15-Table7[[#This Row],[PAYMEN FR]] -> -9284.5 | L16: =L15-Table7[[#This Row],[PAYMENT TE]] -> 214333.5 | N16: =N15-Table7[[#This Row],[PAYMENT GE]] -> 72256.5 | P16: =P15-Table7[[#This Row],[PAYMENT LH2]] -> 5115 | R16: =R15-Table7[[#This Row],[PAYMENTBT]] -> 44400 | T16: =T15-S16 -> 476680 | V16: =V15-Table7[[#This Row],[PAYMENT ML]] -> 192482 | X16: =X15-W16 -> 119315 | Z16: =Z15-Y16 -> 114240 | AB16: =AB15-AA16 -> 77185 | AD16: =AD15-AC16 -> 30000 | AF16: =AF15-AE16 -> 12000
C17: CASH | D17: 9/1/2025 | F17: =F16-Table7[[#This Row],[PAYMENT DH]] -> 181962.72 | H17: =H16-Table7[[#This Row],[PAYMENT EM]] -> 455477 | J17: =J16-Table7[[#This Row],[PAYMEN FR]] -> -9284.5 | L17: =L16-Table7[[#This Row],[PAYMENT TE]] -> 214333.5 | N17: =N16-Table7[[#This Row],[PAYMENT GE]] -> 72256.5 | P17: =P16-Table7[[#This Row],[PAYMENT LH2]] -> 5115 | Q17: 27000 | R17: =R16-Table7[[#This Row],[PAYMENTBT]] -> 17400 | T17: =T16-S17 -> 476680 | V17: =V16-Table7[[#This Row],[PAYMENT ML]] -> 192482 | X17: =X16-W17 -> 119315 | Z17: =Z16-Y17 -> 114240 | AB17: =AB16-AA17 -> 77185 | AD17: =AD16-AC17 -> 30000 | AF17: =AF16-AE17 -> 12000
C18: cash | D18: 9/5/25 | F18: =F17-Table7[[#This Row],[PAYMENT DH]] -> 181962.72 | H18: =H17-Table7[[#This Row],[PAYMENT EM]] -> 455477 | J18: =J17-Table7[[#This Row],[PAYMEN FR]] -> -9284.5 | K18: 23000 | L18: =L17-Table7[[#This Row],[PAYMENT TE]] -> 191333.5 | N18: =N17-Table7[[#This Row],[PAYMENT GE]] -> 72256.5 | P18: =P17-Table7[[#This Row],[PAYMENT LH2]] -> 5115 | R18: =R17-Table7[[#This Row],[PAYMENTBT]] -> 17400 | T18: =T17-S18 -> 476680 | V18: =V17-Table7[[#This Row],[PAYMENT ML]] -> 192482 | X18: =X17-W18 -> 119315 | Z18: =Z17-Y18 -> 114240 | AB18: =AB17-AA18 -> 77185 | AD18: =AD17-AC18 -> 30000 | AF18: =AF17-AE18 -> 12000
C19: IVA20809.12 | D19: 11/9/25 | F19: =F18-Table7[[#This Row],[PAYMENT DH]] -> 181962.72 | G19: 130057 | H19: =H18-Table7[[#This Row],[PAYMENT EM]] -> 325420 | J19: =J18-Table7[[#This Row],[PAYMEN FR]] -> -9284.5 | L19: =L18-Table7[[#This Row],[PAYMENT TE]] -> 191333.5 | N19: =N18-Table7[[#This Row],[PAYMENT GE]] -> 72256.5 | P19: =P18-Table7[[#This Row],[PAYMENT LH2]] -> 5115 | R19: =R18-Table7[[#This Row],[PAYMENTBT]] -> 17400 | T19: =T18-S19 -> 476680 | V19: =V18-Table7[[#This Row],[PAYMENT ML]] -> 192482 | X19: =X18-W19 -> 119315 | Z19: =Z18-Y19 -> 114240 | AB19: =AB18-AA19 -> 77185 | AD19: =AD18-AC19 -> 30000 | AF19: =AF18-AE19 -> 12000
C20: CASH | D20: 10/30/25 | F20: =F19-Table7[[#This Row],[PAYMENT DH]] -> 181962.72 | H20: =H19-Table7[[#This Row],[PAYMENT EM]] -> 325420 | J20: =J19-Table7[[#This Row],[PAYMEN FR]] -> -9284.5 | K20: 30800 | L20: =L19-Table7[[#This Row],[PAYMENT TE]] -> 160533.5 | N20: =N19-Table7[[#This Row],[PAYMENT GE]] -> 72256.5 | P20: =P19-Table7[[#This Row],[PAYMENT LH2]] -> 5115 | R20: =R19-Table7[[#This Row],[PAYMENTBT]] -> 17400 | T20: =T19-S20 -> 476680 | V20: =V19-Table7[[#This Row],[PAYMENT ML]] -> 192482 | X20: =X19-W20 -> 119315 | Z20: =Z19-Y20 -> 114240 | AB20: =AB19-AA20 -> 77185 | AD20: =AD19-AC20 -> 30000 | AF20: =AF19-AE20 -> 12000
C21: IVA 14880 | D21: 9/18/25 | E21: 93000 | F21: =F20-Table7[[#This Row],[PAYMENT DH]] -> 88962.72 | H21: =H20-Table7[[#This Row],[PAYMENT EM]] -> 325420 | J21: =J20-Table7[[#This Row],[PAYMEN FR]] -> -9284.5 | L21: =L20-Table7[[#This Row],[PAYMENT TE]] -> 160533.5 | N21: =N20-Table7[[#This Row],[PAYMENT GE]] -> 72256.5 | P21: =P20-Table7[[#This Row],[PAYMENT LH2]] -> 5115 | R21: =R20-Table7[[#This Row],[PAYMENTBT]] -> 17400 | T21: =T20-S21 -> 476680 | V21: =V20-Table7[[#This Row],[PAYMENT ML]] -> 192482 | X21: =X20-W21 -> 119315 | Z21: =Z20-Y21 -> 114240 | AB21: =AB20-AA21 -> 77185 | AD21: =AD20-AC21 -> 30000 | AF21: =AF20-AE21 -> 12000
C22: CASH | D22: 12/10/25 | E22: 75000 | F22: =F21-Table7[[#This Row],[PAYMENT DH]] -> 13962.72 | H22: =H21-Table7[[#This Row],[PAYMENT EM]] -> 325420 | J22: =J21-Table7[[#This Row],[PAYMEN FR]] -> -9284.5 | L22: =L21-Table7[[#This Row],[PAYMENT TE]] -> 160533.5 | N22: =N21-Table7[[#This Row],[PAYMENT GE]] -> 72256.5 | P22: =P21-Table7[[#This Row],[PAYMENT LH2]] -> 5115 | R22: =R21-Table7[[#This Row],[PAYMENTBT]] -> 17400 | T22: =T21-S22 -> 476680 | V22: =V21-Table7[[#This Row],[PAYMENT ML]] -> 192482 | X22: =X21-W22 -> 119315 | Z22: =Z21-Y22 -> 114240 | AB22: =AB21-AA22 -> 77185 | AD22: =AD21-AC22 -> 30000 | AF22: =AF21-AE22 -> 12000
C23: CASH | E23: 25000 | F23: =F22-Table7[[#This Row],[PAYMENT DH]] -> -11037.28 | H23: =H22-Table7[[#This Row],[PAYMENT EM]] -> 325420 | J23: =J22-Table7[[#This Row],[PAYMEN FR]] -> -9284.5 | L23: =L22-Table7[[#This Row],[PAYMENT TE]] -> 160533.5 | N23: =N22-Table7[[#This Row],[PAYMENT GE]] -> 72256.5 | P23: =P22-Table7[[#This Row],[PAYMENT LH2]] -> 5115 | R23: =R22-Table7[[#This Row],[PAYMENTBT]] -> 17400 | T23: =T22-S23 -> 476680 | V23: =V22-Table7[[#This Row],[PAYMENT ML]] -> 192482 | X23: =X22-W23 -> 119315 | Z23: =Z22-Y23 -> 114240 | AB23: =AB22-AA23 -> 77185 | AD23: =AD22-AC23 -> 30000 | AF23: =AF22-AE23 -> 12000
C24: DIRECT WIRE | D24: 10/28/2025 | F24: =F23-Table7[[#This Row],[PAYMENT DH]] -> -11037.28 | H24: =H23-Table7[[#This Row],[PAYMENT EM]] -> 325420 | J24: =J23-Table7[[#This Row],[PAYMEN FR]] -> -9284.5 | L24: =L23-Table7[[#This Row],[PAYMENT TE]] -> 160533.5 | N24: =N23-Table7[[#This Row],[PAYMENT GE]] -> 72256.5 | P24: =P23-Table7[[#This Row],[PAYMENT LH2]] -> 5115 | R24: =R23-Table7[[#This Row],[PAYMENTBT]] -> 17400 | S24: 79100 | T24: =T23-S24 -> 397580 | V24: =V23-Table7[[#This Row],[PAYMENT ML]] -> 192482 | X24: =X23-W24 -> 119315 | Z24: =Z23-Y24 -> 114240 | AB24: =AB23-AA24 -> 77185 | AD24: =AD23-AC24 -> 30000 | AF24: =AF23-AE24 -> 12000
C25: direct wire | D25: 1/22/2026 | F25: =F24-Table7[[#This Row],[PAYMENT DH]] -> -11037.28 | H25: =H24-Table7[[#This Row],[PAYMENT EM]] -> 325420 | J25: =J24-Table7[[#This Row],[PAYMEN FR]] -> -9284.5 | L25: =L24-Table7[[#This Row],[PAYMENT TE]] -> 160533.5 | N25: =N24-Table7[[#This Row],[PAYMENT GE]] -> 72256.5 | P25: =P24-Table7[[#This Row],[PAYMENT LH2]] -> 5115 | R25: =R24-Table7[[#This Row],[PAYMENTBT]] -> 17400 | S25: 375580 | T25: =T24-S25 -> 22000 | V25: =V24-Table7[[#This Row],[PAYMENT ML]] -> 192482 | X25: =X24-W25 -> 119315 | Z25: =Z24-Y25 -> 114240 | AB25: =AB24-AA25 -> 77185 | AD25: =AD24-AC25 -> 30000 | AF25: =AF24-AE25 -> 12000
F26: =F25-Table7[[#This Row],[PAYMENT DH]] -> -11037.28 | H26: =H25-Table7[[#This Row],[PAYMENT EM]] -> 325420 | J26: =J25-Table7[[#This Row],[PAYMEN FR]] -> -9284.5 | L26: =L25-Table7[[#This Row],[PAYMENT TE]] -> 160533.5 | N26: =N25-Table7[[#This Row],[PAYMENT GE]] -> 72256.5 | P26: =P25-Table7[[#This Row],[PAYMENT LH2]] -> 5115 | R26: =R25-Table7[[#This Row],[PAYMENTBT]] -> 17400 | T26: =T25-S26 -> 22000 | V26: =V25-Table7[[#This Row],[PAYMENT ML]] -> 192482 | X26: =X25-W26 -> 119315 | Z26: =Z25-Y26 -> 114240 | AB26: =AB25-AA26 -> 77185 | AD26: =AD25-AC26 -> 30000 | AF26: =AF25-AE26 -> 12000
F27: =F26-Table7[[#This Row],[PAYMENT DH]] -> -11037.28 | H27: =H26-Table7[[#This Row],[PAYMENT EM]] -> 325420 | J27: =J26-Table7[[#This Row],[PAYMEN FR]] -> -9284.5 | L27: =L26-Table7[[#This Row],[PAYMENT TE]] -> 160533.5 | N27: =N26-Table7[[#This Row],[PAYMENT GE]] -> 72256.5 | P27: =P26-Table7[[#This Row],[PAYMENT LH2]] -> 5115 | R27: =R26-Table7[[#This Row],[PAYMENTBT]] -> 17400 | T27: =T26-S27 -> 22000 | V27: =V26-Table7[[#This Row],[PAYMENT ML]] -> 192482 | X27: =X26-W27 -> 119315 | Z27: =Z26-Y27 -> 114240 | AB27: =AB26-AA27 -> 77185 | AD27: =AD26-AC27 -> 30000 | AF27: =AF26-AE27 -> 12000
F28: =F27-Table7[[#This Row],[PAYMENT DH]] -> -11037.28 | H28: =H27-Table7[[#This Row],[PAYMENT EM]] -> 325420 | J28: =J27-Table7[[#This Row],[PAYMEN FR]] -> -9284.5 | L28: =L27-Table7[[#This Row],[PAYMENT TE]] -> 160533.5 | N28: =N27-Table7[[#This Row],[PAYMENT GE]] -> 72256.5 | P28: =P27-Table7[[#This Row],[PAYMENT LH2]] -> 5115 | R28: =R27-Table7[[#This Row],[PAYMENTBT]] -> 17400 | T28: =T27-S28 -> 22000 | V28: =V27-Table7[[#This Row],[PAYMENT ML]] -> 192482 | X28: =X27-W28 -> 119315 | Z28: =Z27-Y28 -> 114240 | AB28: =AB27-AA28 -> 77185 | AD28: =AD27-AC28 -> 30000 | AF28: =AF27-AE28 -> 12000
F29: =F28-Table7[[#This Row],[PAYMENT DH]] -> -11037.28 | H29: =H28-Table7[[#This Row],[PAYMENT EM]] -> 325420 | J29: =J28-Table7[[#This Row],[PAYMEN FR]] -> -9284.5 | L29: =L28-Table7[[#This Row],[PAYMENT TE]] -> 160533.5 | N29: =N28-Table7[[#This Row],[PAYMENT GE]] -> 72256.5 | P29: =P28-Table7[[#This Row],[PAYMENT LH2]] -> 5115 | R29: =R28-Table7[[#This Row],[PAYMENTBT]] -> 17400 | T29: =T28-S29 -> 22000 | V29: =V28-Table7[[#This Row],[PAYMENT ML]] -> 192482 | X29: =X28-W29 -> 119315 | Z29: =Z28-Y29 -> 114240 | AB29: =AB28-AA29 -> 77185 | AD29: =AD28-AC29 -> 30000 | AF29: =AF28-AE29 -> 12000

Sheet -vSupplies
A1: SUPPLIES | B1: 825
A2: BALANCE | B2: =B3-B4 -> -15416
A3: TOTAL IN | B3: =SUM(Table115[[#All],[$MSN IN]]) -> 294294
A4: TOTAL OUT | B4: =SUM(Table115[TOTAL $]) -> 309710 | G4: \
A5: Date | B5: VENDOR | C5: ITEM | D5: DESCTIPTION | E5: Q | F5: $MSN IN | G5: $MXN OUT | H5: TOTAL $ | I5: $USD | J5: TOTAL USD
A6: 45945 | C6: atm | D6: withdrawal | E6: 1 | F6: 11000 | H6: =Table115[[#This Row],[Q]]*Table115[[#This Row],[$MXN OUT]] -> 0 | K6: =Table115[[#This Row],[$MSN IN]]-Table115[[#This Row],[$MXN OUT]] -> 11000
C7: atm | D7: withdrawal | E7: 1 | F7: 11000 | H7: =Table115[[#This Row],[Q]]*Table115[[#This Row],[$MXN OUT]] -> 0 | K7: =+K6+Table115[[#This Row],[$MSN IN]]-Table115[[#This Row],[$MXN OUT]] -> 22000
C8: atm | D8: withdrawal | E8: 1 | F8: 12000 | H8: =Table115[[#This Row],[Q]]*Table115[[#This Row],[$MXN OUT]] -> 0 | K8: =+K7+Table115[[#This Row],[$MSN IN]]-Table115[[#This Row],[$MXN OUT]] -> 34000
C9: atm | D9: withdrawal | E9: 1 | F9: 12000 | H9: =Table115[[#This Row],[Q]]*Table115[[#This Row],[$MXN OUT]] -> 0 | K9: =+K8+Table115[[#This Row],[$MSN IN]]-Table115[[#This Row],[$MXN OUT]] -> 46000
B10: warehouse | C10: rent | D10: september | E10: 1 | G10: 12000 | H10: =Table115[[#This Row],[Q]]*Table115[[#This Row],[$MXN OUT]] -> 12000 | K10: =+K9+Table115[[#This Row],[$MSN IN]]-Table115[[#This Row],[$MXN OUT]] -> 34000
B11: warehouse | C11: rent | D11: october | E11: 1 | G11: 12000 | H11: =Table115[[#This Row],[Q]]*Table115[[#This Row],[$MXN OUT]] -> 12000 | K11: =+K10+Table115[[#This Row],[$MSN IN]]-Table115[[#This Row],[$MXN OUT]] -> 22000
B12: personal | C12: advance | E12: 1 | G12: 15000 | H12: =Table115[[#This Row],[Q]]*Table115[[#This Row],[$MXN OUT]] -> 15000 | K12: =+K11+Table115[[#This Row],[$MSN IN]]-Table115[[#This Row],[$MXN OUT]] -> 7000
B13: house | C13: rent | D13: october | E13: 1 | G13: 7000 | H13: =Table115[[#This Row],[Q]]*Table115[[#This Row],[$MXN OUT]] -> 7000 | K13: =+K12+Table115[[#This Row],[$MSN IN]]-Table115[[#This Row],[$MXN OUT]] -> 0
A14: 45963 | C14: atm | D14: withdrawal | E14: 1 | F14: 11900 | H14: =Table115[[#This Row],[Q]]*Table115[[#This Row],[$MXN OUT]] -> 0 | K14: =+K13+Table115[[#This Row],[$MSN IN]]-Table115[[#This Row],[$MXN OUT]] -> 11900
C15: atm | D15: withdrawal | E15: 1 | F15: 11500 | H15: =Table115[[#This Row],[Q]]*Table115[[#This Row],[$MXN OUT]] -> 0 | K15: =+K14+Table115[[#This Row],[$MSN IN]]-Table115[[#This Row],[$MXN OUT]] -> 23400
C16: atm | D16: withdrawal | E16: 1 | F16: 11500 | H16: =Table115[[#This Row],[Q]]*Table115[[#This Row],[$MXN OUT]] -> 0 | K16: =+K15+Table115[[#This Row],[$MSN IN]]-Table115[[#This Row],[$MXN OUT]] -> 34900
C17: atm | D17: withdrawal | E17: 1 | F17: 11500 | H17: =Table115[[#This Row],[Q]]*Table115[[#This Row],[$MXN OUT]] -> 0 | K17: =+K16+Table115[[#This Row],[$MSN IN]]-Table115[[#This Row],[$MXN OUT]] -> 46400
C18: atm | D18: withdrawal | E18: 1 | F18: 10000 | H18: =Table115[[#This Row],[Q]]*Table115[[#This Row],[$MXN OUT]] -> 0 | K18: =+K17+Table115[[#This Row],[$MSN IN]]-Table115[[#This Row],[$MXN OUT]] -> 56400
B19: delfino | C19: fountain rock | D19: cash | E19: 1 | G19: 50000 | H19: =Table115[[#This Row],[Q]]*Table115[[#This Row],[$MXN OUT]] -> 50000 | K19: =+K18+Table115[[#This Row],[$MSN IN]]-Table115[[#This Row],[$MXN OUT]] -> 6400
B20: simona | C20: palets | D20: fountain | E20: 6 | G20: 1300 | H20: =Table115[[#This Row],[Q]]*Table115[[#This Row],[$MXN OUT]] -> 7800 | K20: =+K19+Table115[[#This Row],[$MSN IN]]-Table115[[#This Row],[$MXN OUT]] -> 5100
B21: simona | C21: palets | D21: fountain | E21: 6 | G21: 1500 | H21: =Table115[[#This Row],[Q]]*Table115[[#This Row],[$MXN OUT]] -> 9000 | K21: =+K20+Table115[[#This Row],[$MSN IN]]-Table115[[#This Row],[$MXN OUT]] -> 3600
B22: simona | C22: palets | D22: fountain | E22: 2 | G22: 850 | H22: =Table115[[#This Row],[Q]]*Table115[[#This Row],[$MXN OUT]] -> 1700 | K22: =+K21+Table115[[#This Row],[$MSN IN]]-Table115[[#This Row],[$MXN OUT]] -> 2750
B23: simona | C23: crates | D23: emmanuel | E23: 1 | G23: 3900 | H23: =Table115[[#This Row],[Q]]*Table115[[#This Row],[$MXN OUT]] -> 3900 | K23: =+K22+Table115[[#This Row],[$MSN IN]]-Table115[[#This Row],[$MXN OUT]] -> -1150
B24: simona | C24: crates | D24: emmanuel | E24: 1 | G24: 2000 | H24: =Table115[[#This Row],[Q]]*Table115[[#This Row],[$MXN OUT]] -> 2000 | K24: =+K23+Table115[[#This Row],[$MSN IN]]-Table115[[#This Row],[$MXN OUT]] -> -3150
B25: simona | C25: crates | D25: emmanuel | E25: 3 | G25: 3000 | H25: =Table115[[#This Row],[Q]]*Table115[[#This Row],[$MXN OUT]] -> 9000 | K25: =+K24+Table115[[#This Row],[$MSN IN]]-Table115[[#This Row],[$MXN OUT]] -> -6150
B26: simona | C26: crates | D26: emmanuel | E26: 1 | G26: 1600 | H26: =Table115[[#This Row],[Q]]*Table115[[#This Row],[$MXN OUT]] -> 1600 | K26: =+K25+Table115[[#This Row],[$MSN IN]]-Table115[[#This Row],[$MXN OUT]] -> -7750 | L26: =SUM(H20:H26) -> 35000
B27: angel | C27: cactus set | D27: advance 50% | E27: 1 | G27: 6000 | H27: =Table115[[#This Row],[Q]]*Table115[[#This Row],[$MXN OUT]] -> 6000 | K27: =+K26+Table115[[#This Row],[$MSN IN]]-Table115[[#This Row],[$MXN OUT]] -> -13750
B28: forklift | C28: service | E28: 1 | G28: 2600 | H28: =Table115[[#This Row],[Q]]*Table115[[#This Row],[$MXN OUT]] -> 2600 | K28: =+K27+Table115[[#This Row],[$MSN IN]]-Table115[[#This Row],[$MXN OUT]] -> -16350
B29: filling truck | C29: paymenths + food | D29: 45958 | E29: 1 | G29: 2500 | H29: =Table115[[#This Row],[Q]]*Table115[[#This Row],[$MXN OUT]] -> 2500 | K29: =+K28+Table115[[#This Row],[$MSN IN]]-Table115[[#This Row],[$MXN OUT]] -> -18850
B30: house | C30: rent | D30: advance | E30: 1 | G30: 7000 | H30: =Table115[[#This Row],[Q]]*Table115[[#This Row],[$MXN OUT]] -> 7000 | K30: =+K29+Table115[[#This Row],[$MSN IN]]-Table115[[#This Row],[$MXN OUT]] -> -25850
B31: warehose | C31: rent | D31: november | E31: 1 | G31: 12000 | H31: =Table115[[#This Row],[Q]]*Table115[[#This Row],[$MXN OUT]] -> 12000 | K31: =+K30+Table115[[#This Row],[$MSN IN]]-Table115[[#This Row],[$MXN OUT]] -> -37850
B32: personal | D32: advance | E32: 1 | G32: 10000 | H32: =Table115[[#This Row],[Q]]*Table115[[#This Row],[$MXN OUT]] -> 10000 | K32: =+K31+Table115[[#This Row],[$MSN IN]]-Table115[[#This Row],[$MXN OUT]] -> -47850
A33: 45974 | C33: ATM | D33: withdrawal | E33: 1 | F33: 11900 | H33: =Table115[[#This Row],[Q]]*Table115[[#This Row],[$MXN OUT]] -> 0
A34: 45973 | C34: atm | D34: withdrawal | E34: 1 | F34: 11500 | H34: =Table115[[#This Row],[Q]]*Table115[[#This Row],[$MXN OUT]] -> 0
A35: 45976 | C35: atm | D35: withdrawal | E35: 1 | F35: 11500 | H35: =Table115[[#This Row],[Q]]*Table115[[#This Row],[$MXN OUT]] -> 0
A36: 45978 | C36: atm | D36: withdrawal | E36: 1 | F36: 11500 | H36: =Table115[[#This Row],[Q]]*Table115[[#This Row],[$MXN OUT]] -> 0
A37: 45979 | C37: atm | D37: withdrawal | E37: 1 | F37: 11900 | H37: =Table115[[#This Row],[Q]]*Table115[[#This Row],[$MXN OUT]] -> 0
A38: 46004 | C38: atm | D38: withdrawal | E38: 1 | F38: 2200 | H38: =Table115[[#This Row],[Q]]*Table115[[#This Row],[$MXN OUT]] -> 0
A39: 46004 | C39: atm | D39: withdrawal | E39: 1 | F39: 8000 | H39: =Table115[[#This Row],[Q]]*Table115[[#This Row],[$MXN OUT]] -> 0
A40: 46001 | B40: simona | C40: crates | D40: la cantera | E40: 2 | G40: 1750 | H40: =Table115[[#This Row],[Q]]*Table115[[#This Row],[$MXN OUT]] -> 3500
B41: simona | C41: crates | D41: emmanuel | E41: 2 | G41: 2000 | H41: =Table115[[#This Row],[Q]]*Table115[[#This Row],[$MXN OUT]] -> 4000 | I41: =IF(E41>0.1,G41/18," ") -> 111.11111 | J41: =IF(E41>0.1,I41*E41," ") -> 222.22222
B42: simona | C42: crates | D42: emmanuel | E42: 2 | G42: 3000 | H42: =Table115[[#This Row],[Q]]*Table115[[#This Row],[$MXN OUT]] -> 6000 | I42: =IF(E42>0.1,G42/18," ") -> 166.66667 | J42: =IF(E42>0.1,I42*E42," ") -> 333.33333
B43: simonaa | C43: palets | D43: angel | E43: 1 | G43: 900 | H43: =Table115[[#This Row],[Q]]*Table115[[#This Row],[$MXN OUT]] -> 900 | I43: =IF(E43>0.1,G43/18," ") -> 50 | J43: =IF(E43>0.1,I43*E43," ") -> 50
B44: simona | C44: palets | D44: fountain | E44: 6 | G44: 1300 | H44: =Table115[[#This Row],[Q]]*Table115[[#This Row],[$MXN OUT]] -> 7800 | I44: =IF(E44>0.1,G44/18," ") -> 72.222222 | J44: =IF(E44>0.1,I44*E44," ") -> 433.33333
B45: simona | C45: palets | D45: fountain | E45: 8 | G45: 900 | H45: =Table115[[#This Row],[Q]]*Table115[[#This Row],[$MXN OUT]] -> 7200 | I45: =IF(E45>0.1,G45/18," ") -> 50 | J45: =IF(E45>0.1,I45*E45," ") -> 400
B46: warehouse | C46: rent | D46: december | E46: 1 | G46: 12000 | H46: =Table115[[#This Row],[Q]]*Table115[[#This Row],[$MXN OUT]] -> 12000 | I46: =IF(E46>0.1,G46/18," ") -> 666.66667 | J46: =IF(E46>0.1,I46*E46," ") -> 666.66667
B47: house | C47: rent | D47: december | E47: 1 | G47: 7000 | H47: =Table115[[#This Row],[Q]]*Table115[[#This Row],[$MXN OUT]] -> 7000 | I47: =IF(E47>0.1,G47/18," ") -> 388.88889 | J47: =IF(E47>0.1,I47*E47," ") -> 388.88889
B48: electricity | C48: warehouse | E48: 1 | G48: 768 | H48: =Table115[[#This Row],[Q]]*Table115[[#This Row],[$MXN OUT]] -> 768 | I48: =IF(E48>0.1,G48/18," ") -> 42.666667 | J48: =IF(E48>0.1,I48*E48," ") -> 42.666667
B49: bank | C49: account fee | D49: oct- nov | E49: 2 | G49: 1624 | H49: =Table115[[#This Row],[Q]]*Table115[[#This Row],[$MXN OUT]] -> 3248 | I49: =IF(E49>0.1,G49/18," ") -> 90.222222 | J49: =IF(E49>0.1,I49*E49," ") -> 180.44444
B50: gasoline | C50: 3 tiquets | E50: 1 | G50: 1000 | H50: =Table115[[#This Row],[Q]]*Table115[[#This Row],[$MXN OUT]] -> 1000 | I50: =IF(E50>0.1,G50/18," ") -> 55.555556 | J50: =IF(E50>0.1,I50*E50," ") -> 55.555556
B51: delivery | C51: fountain rock | E51: 4 | G51: 1000 | H51: =Table115[[#This Row],[Q]]*Table115[[#This Row],[$MXN OUT]] -> 4000 | I51: =IF(E51>0.1,G51/18," ") -> 55.555556 | J51: =IF(E51>0.1,I51*E51," ") -> 222.22222
B52: delivery | C52: packing | D52: cactus set | E52: 1 | G52: 1000 | H52: =Table115[[#This Row],[Q]]*Table115[[#This Row],[$MXN OUT]] -> 1000 | I52: =IF(E52>0.1,G52/18," ") -> 55.555556 | J52: =IF(E52>0.1,I52*E52," ") -> 55.555556
B53: internet | C53: warehouse | D53: oct- nov | E53: 2 | G53: 479 | H53: =Table115[[#This Row],[Q]]*Table115[[#This Row],[$MXN OUT]] -> 958 | I53: =IF(E53>0.1,G53/18," ") -> 26.611111 | J53: =IF(E53>0.1,I53*E53," ") -> 53.222222
B54: stickers | E54: 2 | G54: 720 | H54: =Table115[[#This Row],[Q]]*Table115[[#This Row],[$MXN OUT]] -> 1440 | I54: =IF(E54>0.1,G54/18," ") -> 40 | J54: =IF(E54>0.1,I54*E54," ") -> 80
A55: 46009 | B55: TRUCK | C55: food + workers | E55: 1 | G55: 2000 | H55: =Table115[[#This Row],[Q]]*Table115[[#This Row],[$MXN OUT]] -> 2000 | I55: =IF(E55>0.1,G55/18," ") -> 111.11111 | J55: =IF(E55>0.1,I55*E55," ") -> 111.11111
A56: 46008 | B56: gasoline | E56: 1 | G56: 300 | H56: =Table115[[#This Row],[Q]]*Table115[[#This Row],[$MXN OUT]] -> 300 | I56: =IF(E56>0.1,G56/18," ") -> 16.666667 | J56: =IF(E56>0.1,I56*E56," ") -> 16.666667
B57: gas | C57: forklift | E57: 1 | G57: 280 | H57: =Table115[[#This Row],[Q]]*Table115[[#This Row],[$MXN OUT]] -> 280 | I57: =IF(E57>0.1,G57/18," ") -> 15.555556 | J57: =IF(E57>0.1,I57*E57," ") -> 15.555556
A58: 46014 | B58: cash | C58: BBWA martha | D58: wire recibed | E58: 1 | F58: 63594 | H58: =Table115[[#This Row],[Q]]*Table115[[#This Row],[$MXN OUT]] -> 0 | I58: =IF(E58>0.1,G58/18," ") -> 0 | J58: =IF(E58>0.1,I58*E58," ") -> 0
A59: 46036 | B59: warehouse rent | C59: january | E59: 1 | G59: 12000 | H59: =Table115[[#This Row],[Q]]*Table115[[#This Row],[$MXN OUT]] -> 12000 | I59: =IF(E59>0.1,G59/18," ") -> 666.66667 | J59: =IF(E59>0.1,I59*E59," ") -> 666.66667
A60: 46036 | B60: delfino | C60: green talan rock | E60: 1 | G60: 30849 | H60: =Table115[[#This Row],[Q]]*Table115[[#This Row],[$MXN OUT]] -> 30849 | I60: =IF(E60>0.1,G60/18," ") -> 1713.8333 | J60: =IF(E60>0.1,I60*E60," ") -> 1713.8333
A61: 46036 | B61: delfino | C61: delivery | E61: 1 | G61: 600 | H61: =Table115[[#This Row],[Q]]*Table115[[#This Row],[$MXN OUT]] -> 600 | I61: =IF(E61>0.1,G61/18," ") -> 33.333333 | J61: =IF(E61>0.1,I61*E61," ") -> 33.333333
A62: 46036 | B62: internet | C62: warehouse | D62: nov-dec | E62: 2 | G62: 479 | H62: =Table115[[#This Row],[Q]]*Table115[[#This Row],[$MXN OUT]] -> 958 | I62: =IF(E62>0.1,G62/18," ") -> 26.611111 | J62: =IF(E62>0.1,I62*E62," ") -> 53.222222
B63: banck account | C63: fee | D63: dec | E63: 1 | G63: 1624 | H63: 1624 | I63: =IF(E63>0.1,G63/18," ") -> 90.222222 | J63: =IF(E63>0.1,I63*E63," ") -> 90.222222
B64: gasoline | E64: 1 | G64: 800 | H64: 800 | I64: =IF(E64>0.1,G64/18," ") -> 44.444444 | J64: =IF(E64>0.1,I64*E64," ") -> 44.444444
B65: exxpenses | C65: filling truck | E65: 1 | G65: 3000 | H65: =Table115[[#This Row],[Q]]*Table115[[#This Row],[$MXN OUT]] -> 3000 | I65: =IF(E65>0.1,G65/18," ") -> 166.66667 | J65: =IF(E65>0.1,I65*E65," ") -> 166.66667
B66: personal | C66: advance | E66: 1 | G66: 10000 | H66: =Table115[[#This Row],[Q]]*Table115[[#This Row],[$MXN OUT]] -> 10000 | I66: =IF(E66>0.1,G66/18," ") -> 555.55556 | J66: =IF(E66>0.1,I66*E66," ") -> 555.55556
A67: 46042 | B67: atm | C67: atm | D67: withdrawal | E67: 1 | F67: 11500 | H67: =Table115[[#This Row],[Q]]*Table115[[#This Row],[$MXN OUT]] -> 0 | I67: =IF(E67>0.1,G67/18," ") -> 0 | J67: =IF(E67>0.1,I67*E67," ") -> 0
A68: 46045 | B68: atm | C68: atm | D68: withdrawal | E68: 1 | F68: 11000 | H68: =Table115[[#This Row],[Q]]*Table115[[#This Row],[$MXN OUT]] -> 0 | I68: =IF(E68>0.1,G68/18," ") -> 0 | J68: =IF(E68>0.1,I68*E68," ") -> 0
A69: 46046 | B69: atm | C69: atm | D69: withdrawal | E69: 1 | F69: 8000 | H69: =Table115[[#This Row],[Q]]*Table115[[#This Row],[$MXN OUT]] -> 0 | I69: =IF(E69>0.1,G69/18," ") -> 0 | J69: =IF(E69>0.1,I69*E69," ") -> 0
A70: 46049 | B70: atm | C70: atm | D70: withdrawal | E70: 1 | F70: 10500 | H70: =Table115[[#This Row],[Q]]*Table115[[#This Row],[$MXN OUT]] -> 0 | I70: =IF(E70>0.1,G70/18," ") -> 0 | J70: =IF(E70>0.1,I70*E70," ") -> 0
A71: 46050 | B71: atm | C71: atm | D71: withdrawal | E71: 1 | F71: 10500 | H71: =Table115[[#This Row],[Q]]*Table115[[#This Row],[$MXN OUT]] -> 0 | I71: =IF(E71>0.1,G71/18," ") -> 0 | J71: =IF(E71>0.1,I71*E71," ") -> 0
A72: 265196 | B72: atm | C72: atm | D72: withdrawal | F72: 8300 | H72: =Table115[[#This Row],[Q]]*Table115[[#This Row],[$MXN OUT]] -> 0 | I72: =IF(E72>0.1,G72/18," ") | J72: =IF(E72>0.1,I72*E72," ")
A73: 46040 | B73: cardboard | C73: polifon, tape | D73: packing supplies | E73: 1 | G73: 2030 | H73: =Table115[[#This Row],[Q]]*Table115[[#This Row],[$MXN OUT]] -> 2030 | I73: =IF(E73>0.1,G73/18," ") -> 112.77778 | J73: =IF(E73>0.1,I73*E73," ") -> 112.77778
A74: 46042 | C74: straps truck | E74: 4 | G74: 300 | H74: =Table115[[#This Row],[Q]]*Table115[[#This Row],[$MXN OUT]] -> 1200 | I74: =IF(E74>0.1,G74/18," ") -> 16.666667 | J74: =IF(E74>0.1,I74*E74," ") -> 66.666667
A75: 46048 | B75: banck account | C75: fee | D75: jan | E75: 1 | G75: 1624 | H75: =Table115[[#This Row],[Q]]*Table115[[#This Row],[$MXN OUT]] -> 1624 | I75: =IF(E75>0.1,G75/18," ") -> 90.222222 | J75: =IF(E75>0.1,I75*E75," ") -> 90.222222
A76: 46048 | B76: trip to puebla | C76: send pakage | D76: fedex | E76: 2 | G76: 800 | H76: =Table115[[#This Row],[Q]]*Table115[[#This Row],[$MXN OUT]] -> 1600 | I76: =IF(E76>0.1,G76/18," ") -> 44.444444 | J76: =IF(E76>0.1,I76*E76," ") -> 88.888889
A77: 46041 | B77: gasoline | E77: 1 | G77: 500 | H77: =Table115[[#This Row],[Q]]*Table115[[#This Row],[$MXN OUT]] -> 500 | I77: =IF(E77>0.1,G77/18," ") -> 27.777778 | J77: =IF(E77>0.1,I77*E77," ") -> 27.777778
B78: warehouse | C78: internet | D78: jan | E78: 1 | G78: 479 | H78: =Table115[[#This Row],[Q]]*Table115[[#This Row],[$MXN OUT]] -> 479 | I78: =IF(E78>0.1,G78/18," ") -> 26.611111 | J78: =IF(E78>0.1,I78*E78," ") -> 26.611111
B79: warehouse | C79: electricity | D79: jan | E79: 1 | G79: 952 | H79: =Table115[[#This Row],[Q]]*Table115[[#This Row],[$MXN OUT]] -> 952 | I79: =IF(E79>0.1,G79/18," ") -> 52.888889 | J79: =IF(E79>0.1,I79*E79," ") -> 52.888889
B80: house rent | C80: advance | D80: feb | E80: 1 | G80: 7000 | H80: =Table115[[#This Row],[Q]]*Table115[[#This Row],[$MXN OUT]] -> 7000 | I80: =IF(E80>0.1,G80/18," ") -> 388.88889 | J80: =IF(E80>0.1,I80*E80," ") -> 388.88889
H81: =Table115[[#This Row],[Q]]*Table115[[#This Row],[$MXN OUT]] -> 0 | I81: =IF(E81>0.1,G81/#REF!," ") | J81: =IF(E81>0.1,I81*E81," ")
H82: =Table115[[#This Row],[Q]]*Table115[[#This Row],[$MXN OUT]] -> 0 | I82: =IF(E82>0.1,G82/#REF!," ") | J82: =IF(E82>0.1,I82*E82," ")
H83: =Table115[[#This Row],[Q]]*Table115[[#This Row],[$MXN OUT]] -> 0 | I83: =IF(E83>0.1,G83/#REF!," ") | J83: =IF(E83>0.1,I83*E83," ")
H84: =Table115[[#This Row],[Q]]*Table115[[#This Row],[$MXN OUT]] -> 0 | I84: =IF(E84>0.1,G84/#REF!," ") | J84: =IF(E84>0.1,I84*E84," ")
H85: =Table115[[#This Row],[Q]]*Table115[[#This Row],[$MXN OUT]] -> 0 | I85: =IF(E85>0.1,G85/#REF!," ") | J85: =IF(E85>0.1,I85*E85," ")
H86: =Table115[[#This Row],[Q]]*Table115[[#This Row],[$MXN OUT]] -> 0 | I86: =IF(E86>0.1,G86/#REF!," ") | J86: =IF(E86>0.1,I86*E86," ")
B87: bank account | C87: fee | D87: jan | G87: 1624

Sheet -vCrates
A1: PALLETS AND CRATES | C1: SIMONA | R1: =R3-R2 -> 3096.9444
A2: OWED | B2: =B3-B4 -> -55745 | R2: =B3/18 -> 0
A3: PAID | B3: =SUM(Table11524[[#All],[$MSN IN]]) -> 0 | R3: =SUM(R6:R14) -> 3096.9444
A4: TBP | B4: =SUM(Table11524[TOTAL $]) -> 55745 | K4: \
A5: Date | B5: VENDOR | C5: ITEM | D5: DESCTIPTION | E5: Q | F5: KG | G5: L CM | H5: W CM | I5: D CM | J5: $MSN IN | K5: $MXN OUT | L5: TOTAL $ | M5: POUNDS | N5: H " | O5: W" | P5: D" | Q5: $USD | R5: TOTAL USD
A6: 46042 | B6: simona | C6: crates | D6: GE. ET.RF, EM | E6: 6 | G6: 120 | H6: 150 | I6: 180 | K6: 3000 | L6: =Table11524[[#This Row],[Q]]*Table11524[[#This Row],[$MXN OUT]] -> 18000 | M6: =F6*2.20462 -> 0 | N6: =G6/2.54 -> 47.244094 | O6: =H6/2.54 -> 59.055118 | P6: =I6/2.54 -> 70.866142 | Q6: =IF(E6>0.1,K6/18," ") -> 166.66667 | R6: =IF(E6>0.1,Q6*E6," ") -> 1000
B7: simona | C7: crates w divisions | D7: EM | E7: 2 | G7: 120 | H7: 150 | I7: 180 | K7: 4200 | L7: =Table11524[[#This Row],[Q]]*Table11524[[#This Row],[$MXN OUT]] -> 8400 | M7: =F7*2.20462 -> 0 | N7: =G7/2.54 -> 47.244094 | O7: =H7/2.54 -> 59.055118 | P7: =I7/2.54 -> 70.866142 | Q7: =IF(E7>0.1,K7/18," ") -> 233.33333 | R7: =IF(E7>0.1,Q7*E7," ") -> 466.66667
B8: simona | C8: crates | D8: EM. GE | E8: 4 | G8: 120 | H8: 120 | I8: 120 | K8: 2150 | L8: =Table11524[[#This Row],[Q]]*Table11524[[#This Row],[$MXN OUT]] -> 8600 | M8: =F8*2.20462 -> 0 | N8: =G8/2.54 -> 47.244094 | O8: =H8/2.54 -> 47.244094 | P8: =I8/2.54 -> 47.244094 | Q8: =IF(E8>0.1,K8/18," ") -> 119.44444 | R8: =IF(E8>0.1,Q8*E8," ") -> 477.77778
B9: simona | C9: CRATES | D9: ML | E9: 2 | G9: 120 | H9: 150 | I9: 170 | K9: 2300 | L9: =Table11524[[#This Row],[Q]]*Table11524[[#This Row],[$MXN OUT]] -> 4600 | M9: =F9*2.20462 -> 0 | N9: =G9/2.54 -> 47.244094 | O9: =H9/2.54 -> 59.055118 | P9: =I9/2.54 -> 66.929134 | Q9: =IF(E9>0.1,K9/18," ") -> 127.77778 | R9: =IF(E9>0.1,Q9*E9," ") -> 255.55556
B10: simona | C10: PALETS | D10: DH | E10: 4 | G10: 180 | H10: 60 | K10: 1100 | L10: =Table11524[[#This Row],[Q]]*Table11524[[#This Row],[$MXN OUT]] -> 4400 | M10: =F10*2.20462 -> 0 | N10: =G10/2.54 -> 70.866142 | O10: =H10/2.54 -> 23.622047 | P10: =I10/2.54 -> 0 | Q10: =IF(E10>0.1,K10/18," ") -> 61.111111 | R10: =IF(E10>0.1,Q10*E10," ") -> 244.44444
B11: simona | C11: CRATES | D11: AM | E11: 1 | G11: 185 | H11: 45 | I11: 75 | K11: 1730 | L11: =Table11524[[#This Row],[Q]]*Table11524[[#This Row],[$MXN OUT]] -> 1730 | M11: =F11*2.20462 -> 0 | N11: =G11/2.54 -> 72.834646 | O11: =H11/2.54 -> 17.716535 | P11: =I11/2.54 -> 29.527559 | Q11: =IF(E11>0.1,K11/18," ") -> 96.111111 | R11: =IF(E11>0.1,Q11*E11," ") -> 96.111111
B12: simona | C12: CRATES | D12: AM | E12: 1 | G12: 200 | H12: 140 | I12: 75 | K12: 3765 | L12: =Table11524[[#This Row],[Q]]*Table11524[[#This Row],[$MXN OUT]] -> 3765 | M12: =F12*2.20462 -> 0 | N12: =G12/2.54 -> 78.740157 | O12: =H12/2.54 -> 55.11811 | P12: =I12/2.54 -> 29.527559 | Q12: =IF(E12>0.1,K12/18," ") -> 209.16667 | R12: =IF(E12>0.1,Q12*E12," ") -> 209.16667
B13: simona | C13: crates | D13: em | E13: 2 | G13: 120 | H13: 150 | I13: 180 | K13: 3000 | L13: =Table11524[[#This Row],[Q]]*Table11524[[#This Row],[$MXN OUT]] -> 6000 | M13: =F13*2.20462 -> 0 | N13: =G13/2.54 -> 47.244094 | O13: =H13/2.54 -> 59.055118 | P13: =I13/2.54 -> 70.866142 | Q13: =IF(E13>0.1,K13/18," ") -> 166.66667 | R13: =IF(E13>0.1,Q13*E13," ") -> 333.33333
B14: simona | C14: CRATE | D14: CH | E14: 1 | G14: 85 | H14: 40 | I14: 15 | K14: 250 | L14: =Table11524[[#This Row],[Q]]*Table11524[[#This Row],[$MXN OUT]] -> 250 | M14: =F14*2.20462 -> 0 | N14: =G14/2.54 -> 33.464567 | O14: =H14/2.54 -> 15.748031 | P14: =I14/2.54 -> 5.9055118 | Q14: =IF(E14>0.1,K14/18," ") -> 13.888889 | R14: =IF(E14>0.1,Q14*E14," ") -> 13.888889

Sheet -TRK1
A2: TRK1 | D2: 45887 | K2: TOTAL | N2: =SUM(N5:N128) -> 666790
B4: date | C4: Description | D4: Tag - ID with LC | E4: LC | F4: AQ CODE | G4: RETAIL | H4: Quantity | I4: Weight KG | J4: length in CM | K4: Width in CM | L4: Depth in | M4: Per piece Pesos | N4: Total in Pesos | O4: pounds | P4: Height in Inches | Q4: Width in inches | R4: Depth in Inches | S4: Per Piece US$ | T4: Total in US$ Dollars | U4: Column1
A5: EM | B5: } | C5: GREY RUSTIC ROCK FTN | D5: EM325055OHL | E5: OOM | F5: MEA | G5: 1768 | H5: 1 | I5: 228 | J5: 129 | K5: 42 | L5: 21 | M5: 2850 | N5: 2850 | O5: 502.65336 | P5: 50.787402 | Q5: 16.535433 | R5: 8.2677165 | S5: 158.33 | T5: 158.33
A6: EM | B6: 2 | C6: GREY RUSTIC ROCK FTN | D6: EM325056OFF | E6: OEM | F6: MFN | G6: 2008 | H6: 1 | I6: 257 | J6: 95 | K6: 45 | L6: 27 | M6: 3212.5 | N6: 3212.5 | O6: 566.58734 | P6: 37.401575 | Q6: 17.716535 | R6: 10.629921 | S6: 178.47 | T6: 178.47
A7: EM | B7: 3 | C7: GREY RUSTIC ROCK FTN | D7: EM325057OHO | E7: OMA | F7: MEL | G7: 1744 | H7: 1 | I7: 224 | J7: 95 | K7: 45 | L7: 23 | M7: 2800 | N7: 2800 | O7: 493.83488 | P7: 37.401575 | Q7: 17.716535 | R7: 9.0551181 | S7: 155.56 | T7: 155.56
A8: EM | B8: 4 | C8: GREY RUSTIC ROCK FTN | D8: EM325058MXL | E8: MOX | F8: AA | G8: 984 | H8: 1 | I8: 126 | J8: 100 | K8: 40 | L8: 23 | M8: 1575 | N8: 1575 | O8: 277.78212 | P8: 39.370079 | Q8: 15.748031 | R8: 9.0551181 | S8: 87.5 | T8: 87.5
A9: EM | B9: 5 | C9: GREY RUSTIC ROCK FTN | D9: EM325060OXH | E9: OMD | F9: MED | G9: 1680 | H9: 1 | I9: 216 | J9: 100 | K9: 45 | L9: 29 | M9: 2700 | N9: 2700 | O9: 476.19792 | P9: 39.370079 | Q9: 17.716535 | R9: 11.417323 | S9: 150 | T9: 150
A10: EM | B10: 6 | C10: GREY RUSTIC ROCK FTN | D10: EM325061NN | E10: ND | F10: LH | G10: 720 | H10: 1 | I10: 92 | J10: 68 | K10: 33 | L10: 23 | M10: 1150 | N10: 1150 | O10: 202.82504 | P10: 26.771654 | Q10: 12.992126 | R10: 9.0551181 | S10: 63.89 | T10: 63.89
A11: EM | B11: 7 | C11: SERPENTINE RUSTIC ROCK FTN | D11: EM325062OAD | E11: OEX | F11: MAM | G11: 2024 | H11: 1 | I11: 260 | J11: 93 | K11: 37 | L11: 40 | M11: 3250 | N11: 3250 | O11: 573.2012 | P11: 36.614173 | Q11: 14.566929 | R11: 15.748031 | S11: 180.56 | T11: 180.56
A12: EM | B12: 8 | C12: SERPENTINE RUSTIC ROCK FTN | D12: EM325063OXH | E12: OMD | F12: MED | G12: 1680 | H12: 1 | I12: 216 | J12: 91 | K12: 42 | L12: 32 | M12: 2700 | N12: 2700 | O12: 476.19792 | P12: 35.826772 | Q12: 16.535433 | R12: 12.598425 | S12: 150 | T12: 150
A13: EM | B13: 9 | C13: SERPENTINE RUSTIC ROCK FTN | D13: EM325064MLO | E13: MHF | F13: MDE | G13: 1176 | H13: 1 | I13: 151 | J13: 88 | K13: 49 | L13: 25 | M13: 1887.5 | N13: 1887.5 | O13: 332.89762 | P13: 34.645669 | Q13: 19.291339 | R13: 9.8425197 | S13: 104.86 | T13: 104.86
A14: EM | B14: 10 | C14: SERPENTINE RUSTIC ROCK FTN | D14: EM325065OHA | E14: OOH | F14: MLD | G14: 1792 | H14: 1 | I14: 230 | J14: 85 | K14: 40 | L14: 34 | M14: 2875 | N14: 2875 | O14: 507.0626 | P14: 33.464567 | Q14: 15.748031 | R14: 13.385827 | S14: 159.72 | T14: 159.72
A15: EM | B15: 11 | C15: PINK SERP RUSTIC ROCK FTN | D15: EM325066HHN | E15: HDL | F15: OND | G15: 3248 | H15: 1 | I15: 417 | J15: 68 | K15: 99 | L15: 42 | M15: 5212.5 | N15: 5212.5 | O15: 919.32654 | P15: 26.771654 | Q15: 38.976378 | R15: 16.535433 | S15: 289.58 | T15: 289.58
A16: EM | B16: 12 | C16: PINK SERP RUSTIC ROCK FTN | D16: EM325067AA | E16: AD | F16: EF | G16: 640 | H16: 1 | I16: 82 | J16: 80 | K16: 31 | L16: 18 | M16: 1025 | N16: 1025 | O16: 180.77884 | P16: 31.496063 | Q16: 12.204724 | R16: 7.0866142 | S16: 56.94 | T16: 56.94
A17: EM | B17: 13 | C17: PINK SERP RUSTIC ROCK FTN | D17: EM325068OFF | E17: OEM | F17: MFN | G17: 2008 | H17: 1 | I17: 257 | J17: 121 | K17: 60 | L17: 27 | M17: 3212.5 | N17: 3212.5 | O17: 566.58734 | P17: 47.637795 | Q17: 23.622047 | R17: 10.629921 | S17: 178.47 | T17: 178.47
... A21: EM | B21: 17 | C21: GREY RUSTIC ROCK FTN | D21: EM325074AA | E21: AD | F21: EF | G21: 640 | H21: 1 | I21: 82 | J21: 70 | K21: 34 | L21: 18 | M21: 1025 | N21: 1025 | O21: 180.77884 | P21: 27.559055 | Q21: 13.385827 | R21: 7.0866142 | S21: 56.94 | T21: 56.94
A22: EM | B22: 20 | C22: GRAY REC MIRROR | D22: EM82520XNL | E22: XNL | F22: OAX | G22: 3168 | H22: 1 | I22: 30 | J22: 150 | K22: 80 | M22: 5100 | N22: 5100 | O22: 66.1386 | P22: 59.055118 | Q22: 31.496063 | R22: 0 | S22: 283.33 | T22: 283.33
A23: EM | B23: 21 | C23: GRAY REC MIRROR | D23: EM82521XNL | E23: XNL | F23: OAX | G23: 3168 | H23: 1 | I23: 30 | J23: 150 | K23: 80 | M23: 5100 | N23: 5100 | O23: 66.1386 | P23: 59.055118 | Q23: 31.496063 | R23: 0 | S23: 283.33 | T23: 283.33
A24: EM | B24: 22 | C24: AMBER REC MIRROR | D24: EM82522XNL | E24: XNL | F24: OAX | G24: 3168 | H24: 1 | I24: 30 | J24: 150 | K24: 80 | M24: 5100 | N24: 5100 | O24: 66.1386 | P24: 59.055118 | Q24: 31.496063 | R24: 0 | S24: 283.33 | T24: 283.33
A25: EM | B25: 23 | C25: AMBER REC MIRROR | D25: EM82523XNL | E25: XNL | F25: OAX | G25: 3168 | H25: 1 | I25: 30 | J25: 150 | K25: 80 | M25: 5100 | N25: 5100 | O25: 66.1386 | P25: 59.055118 | Q25: 31.496063 | R25: 0 | S25: 283.33 | T25: 283.33
A26: EM | B26: 24 | C26: CRYSTALLINE REC MIRROR | D26: EM82524XNL | E26: XNL | F26: OAX | G26: 3168 | H26: 1 | I26: 30 | J26: 150 | K26: 80 | M26: 5100 | N26: 5100 | O26: 66.1386 | P26: 59.055118 | Q26: 31.496063 | R26: 0 | S26: 283.33 | T26: 283.33
A27: EM | B27: 25 | C27: CRYS REC MIRROR | D27: EM82525XNL | E27: XNL | F27: OAX | G27: 3168 | H27: 1 | I27: 30 | J27: 150 | K27: 80 | M27: 5100 | N27: 5100 | O27: 66.1386 | P27: 59.055118 | Q27: 31.496063 | R27: 0 | S27: 283.33 | T27: 283.33
A28: EM | B28: 26 | C28: CRYS REC MIRROR | D28: EM82526XNL | E28: XNL | F28: OAX | G28: 3168 | H28: 1 | I28: 30 | J28: 150 | K28: 80 | M28: 5100 | N28: 5100 | O28: 66.1386 | P28: 59.055118 | Q28: 31.496063 | R28: 0 | S28: 283.33 | T28: 283.33
A29: EM | B29: 27 | C29: CRYS REC MIRROR | D29: EM82527XNL | E29: XNL | F29: OAX | G29: 3168 | H29: 1 | I29: 30 | J29: 150 | K29: 80 | M29: 5100 | N29: 5100 | O29: 66.1386 | P29: 59.055118 | Q29: 31.496063 | R29: 0 | S29: 283.33 | T29: 283.33
A30: EM | B30: 28 | C30: CRYS REC MIRROR | D30: EM82528XNL | E30: XNL | F30: OAX | G30: 3168 | H30: 1 | I30: 30 | J30: 150 | K30: 80 | M30: 5100 | N30: 5100 | O30: 66.1386 | P30: 59.055118 | Q30: 31.496063 | R30: 0 | S30: 283.33 | T30: 283.33
A31: EM | B31: 29 | C31: CRYS REC MIRROR | D31: EM82529XNL | E31: XNL | F31: OAX | G31: 3168 | H31: 1 | I31: 30 | J31: 150 | K31: 80 | M31: 5100 | N31: 5100 | O31: 66.1386 | P31: 59.055118 | Q31: 31.496063 | R31: 0 | S31: 283.33 | T31: 283.33
A32: EM | B32: 30 | C32: CRYS REC MIRROR | D32: EM82530XNL | E32: XNL | F32: OAX | G32: 3168 | H32: 1 | I32: 30 | J32: 150 | K32: 80 | M32: 5100 | N32: 5100 | O32: 66.1386 | P32: 59.055118 | Q32: 31.496063 | R32: 0 | S32: 283.33 | T32: 283.33
A33: EM | B33: 31 | C33: CRYS REC MIRROR | D33: EM82531XNL | E33: XNL | F33: OAX | G33: 3168 | H33: 1 | I33: 30 | J33: 150 | K33: 80 | M33: 5100 | N33: 5100 | O33: 66.1386 | P33: 59.055118 | Q33: 31.496063 | R33: 0 | S33: 283.33 | T33: 283.33
... A74: EM | B74: 72 | C74: CRIS GREY REC MIRROR | D74: EM82572XNL | E74: XNL | F74: OAX | G74: 3168 | H74: 1 | I74: 30 | J74: 150 | K74: 80 | M74: 5100 | N74: 5100 | O74: 66.1386 | P74: 59.055118 | Q74: 31.496063 | R74: 0 | S74: 283.33 | T74: 283.33
A75: EM | B75: 73 | C75: CRIS GREY RD MIRROR | D75: EM82573XOL | E75: XOL | F75: OXX | G75: 2608 | H75: 6 | I75: 13 | J75: 80 | M75: 4200 | N75: 25200 | O75: 28.66006 | P75: 31.496063 | Q75: 0 | R75: 0 | S75: 233.33 | T75: 1400
A76: EM | B76: 74 | C76: CRIS GREY REC MIRROR | D76: EM82574OLE | E76: OLE | F76: MAN | G76: 2120 | H76: 5 | I76: 19 | J76: 110 | K76: 60 | M76: 3400 | N76: 17000 | O76: 41.88778 | P76: 43.307087 | Q76: 23.622047 | R76: 0 | S76: 188.89 | T76: 944.44
A77: EM | B77: 75 | C77: TEHUA/GREY DIAMOND TABLE | D77: EM82575LOX | E77: LOX | F77: HHE | G77: 4984 | H77: 1 | I77: 52 | J77: 86 | K77: 86 | L77: 50 | M77: 8000 | N77: 8000 | O77: 114.64024 | P77: 33.858268 | Q77: 33.858268 | R77: 19.685039 | S77: 444.44 | T77: 444.44
A78: TE | B78: 1 | C78: ZEBRA PANEL SET | D78: TE82501MFMO | E78: MFMO | F78: MOOX | G78: 13696 | H78: 1 | I78: 155 | J78: 210 | K78: 40 | L78: 10 | M78: 22015 | N78: 22015 | O78: 341.7161 | P78: 82.677165 | Q78: 15.748031 | R78: 3.9370079 | S78: 1223.06 | T78: 1223.06
A79: TE | B79: 2 | C79: BEIGE MARBLE AMORE SCULPTURE | D79: TE82502MNMM | E79: MNMM | F79: MXLE | G79: 15288 | H79: 1 | I79: 250 | J79: 170 | M79: 24565 | N79: 24565 | O79: 551.155 | P79: 66.929134 | Q79: 0 | R79: 0 | S79: 1364.72 | T79: 1364.72
A80: TE | B80: 3 | C80: GREEN TALAN PANEL SET | D80: TE82503MEED | E80: MEED | F80: MMDF | G80: 12400 | H80: 1 | I80: 120 | J80: 190 | K80: 60 | L80: 10 | M80: 19932.5 | N80: 19932.5 | O80: 264.5544 | P80: 74.80315 | Q80: 23.622047 | R80: 3.9370079 | S80: 1107.36 | T80: 1107.36
A81: TE | B81: 4 | C81: BLUE ONIX SOL | D81: TE82504MFXD | E81: MFXD | F81: MOXL | G81: 13840 | H81: 1 | I81: 50 | J81: 160 | K81: 30 | L81: 30 | M81: 22240 | N81: 22240 | O81: 110.231 | P81: 62.992126 | Q81: 11.811024 | R81: 11.811024 | S81: 1235.56 | T81: 1235.56
A82: TE | B82: 5 | C82: BLUE ONIX SOL | D82: TE82505MEFM | E82: MEFM | F82: MMOO | G82: 12568 | H82: 1 | I82: 45 | J82: 145 | K82: 30 | L82: 30 | M82: 20200 | N82: 20200 | O82: 99.2079 | P82: 57.086614 | Q82: 11.811024 | R82: 11.811024 | S82: 1122.22 | T82: 1122.22
A83: TE | B83: 6 | C83: BLUE ONIX SOL | D83: TE82506MHMA | E83: MHMA | F83: MDMX | G83: 11344 | H83: 1 | I83: 40 | J83: 130 | K83: 30 | L83: 30 | M83: 18224 | N83: 18224 | O83: 88.1848 | P83: 51.181102 | Q83: 11.811024 | R83: 11.811024 | S83: 1012.44 | T83: 1012.44
A84: TE | B84: 7 | C84: RED MARBLE AMORE SCULPTURE | D84: TE82507LFN | E84: LFN | F84: HAE | G84: 5432 | H84: 1 | I84: 52 | J84: 100 | M84: 8720 | N84: 8720 | O84: 114.64024 | P84: 39.370079 | Q84: 0 | R84: 0 | S84: 484.44 | T84: 484.44
A85: TE | B85: 8 | C85: PINK SER SOL | D85: TE82508MEE | E85: MEE | F85: MMM | G85: 1240 | H85: 3 | I85: 8 | J85: 60 | K85: 20 | L85: 20 | M85: 1992 | N85: 5976 | O85: 17.63696 | P85: 23.622047 | Q85: 7.8740157 | R85: 7.8740157 | S85: 110.67 | T85: 332
A86: TE | B86: 9 | C86: PINK SER SOL | D86: TE82509MDE | E86: MDE | F86: FE | G86: 840 | H86: 2 | I86: 7 | J86: 50 | K86: 20 | L86: 20 | M86: 1352 | N86: 2704 | O86: 15.43234 | P86: 19.685039 | Q86: 7.8740157 | R86: 7.8740157 | S86: 75.11 | T86: 150.22
A87: TE | B87: 10 | C87: PINK SER SOL | D87: TE82510LN | E87: LN | F87: HN | G87: 552 | H87: 1 | I87: 5 | J87: 30 | K87: 20 | L87: 20 | M87: 880 | N87: 880 | O87: 11.0231 | P87: 11.811024 | Q87: 7.8740157 | R87: 7.8740157 | S87: 48.89 | T87: 48.89
A88: TE | B88: 13 | C88: WALL PANEL TOTAL | D88: TE82513OAOA | E88: OAOA | F88: ODOD | G88: 22624 | H88: 1 | I88: 320 | M88: 36365 | N88: 36365 | O88: 705.4784 | S88: 2020.28 | T88: 2020.28
A89: GE | B89: 1 | C89: TEHUA GREEN/ORANGE SOL | D89: GE82501MNF | E89: MNF | F89: MMA | G89: 1576 | H89: 7 | I89: 30 | J89: 100 | K89: 25 | L89: 25 | M89: 2125 | N89: 14875 | O89: 66.14 | P89: 39.370079 | Q89: 9.8425197 | R89: 9.8425197 | S89: 118.06 | T89: 826.39
A90: GE | B90: 2 | C90: TEHUA GREEN/ORANGE SOL | D90: GE82502MFA | E90: MFA | F90: MDF | G90: 1424 | H90: 2 | I90: 28 | J90: 90 | K90: 25 | L90: 25 | M90: 1925 | N90: 3850 | O90: 61.73 | P90: 35.433071 | Q90: 9.8425197 | R90: 9.8425197 | S90: 106.94 | T90: 213.89
A91: GE | B91: 3 | C91: TEHUA GREEN/ORANGE SOL | D91: GE82503MLD | E91: MLD | F91: NL | G91: 1280 | H91: 2 | I91: 26 | J91: 80 | K91: 25 | L91: 25 | M91: 1725 | N91: 3450 | O91: 57.32 | P91: 31.496063 | Q91: 9.8425197 | R91: 9.8425197 | S91: 95.83 | T91: 191.67
A92: GE | B92: 4 | C92: TEHUA GREEN/ORANGE SOL | D92: GE82504MHO | E92: MHO | F92: AE | G92: 1136 | H92: 1 | I92: 24 | J92: 70 | K92: 25 | L92: 25 | M92: 1525 | N92: 1525 | O92: 52.91 | P92: 27.559055 | Q92: 9.8425197 | R92: 9.8425197 | S92: 84.72 | T92: 84.72
A93: GE | B93: 5 | C93: TEHUA GREEN/ORANGE SOL | D93: GE82505MMO | E93: MMO | F93: LF | G93: 896 | H93: 1 | I93: 18 | J93: 70 | K93: 20 | L93: 20 | M93: 1200 | N93: 1200 | O93: 39.68 | P93: 27.559055 | Q93: 7.8740157 | R93: 7.8740157 | S93: 66.67 | T93: 66.67
A94: GE | B94: 6 | C94: TEHUA GREEN/ORANGE CT SOL | D94: GE82506LD | E94: LD | F94: XL | G94: 480 | H94: 2 | I94: 8 | J94: 50 | K94: 15 | L94: 15 | M94: 645 | N94: 1290 | O94: 17.64 | P94: 19.685039 | Q94: 5.9055118 | R94: 5.9055118 | S94: 35.83 | T94: 71.67
A95: GE | B95: 7 | C95: TEHUA GREEN/ORANGE CT SOL | D95: GE82507HA | E95: HA | F95: ON | G95: 384 | H95: 3 | I95: 7 | J95: 40 | K95: 15 | L95: 15 | M95: 525 | N95: 1575 | O95: 15.43 | P95: 15.748031 | Q95: 5.9055118 | R95: 5.9055118 | S95: 29.17 | T95: 87.5
A96: GE | B96: 8 | C96: TEHUA GREEN/ORANGE CT SOL | D96: GE82508XA | E96: XA | F96: OX | G96: 304 | H96: 22 | I96: 5 | J96: 30 | K96: 15 | L96: 15 | M96: 405 | N96: 8910 | O96: 11.02 | P96: 11.811024 | Q96: 5.9055118 | R96: 5.9055118 | S96: 22.5 | T96: 495
A97: GE | B97: 9 | C97: TEHUA GREEN/ORANGE OT SOL | D97: GE82509EE | E97: EE | F97: XX | G97: 440 | H97: 10 | I97: 8 | J97: 50 | K97: 15 | L97: 15 | M97: 600 | N97: 6000 | O97: 17.64 | P97: 19.685039 | Q97: 5.9055118 | R97: 5.9055118 | S97: 33.33 | T97: 333.33
A98: GE | B98: 10 | C98: TEHUA GREEN/ORANGE OT SOL | D98: GE82510HE | E98: HE | F98: OF | G98: 360 | H98: 40 | I98: 6.5 | J98: 40 | K98: 15 | L98: 15 | M98: 480 | N98: 19200 | O98: 14.33 | P98: 15.748031 | Q98: 5.9055118 | R98: 5.9055118 | S98: 26.67 | T98: 1066.67
A99: GE | B99: 11 | C99: RED ONIX SOL | D99: GE82511XOA | E99: XOA | F99: MNF | G99: 2624 | H99: 2 | I99: 40 | J99: 140 | K99: 30 | L99: 30 | M99: 3540 | N99: 7080 | O99: 88.18 | P99: 55.11811 | Q99: 11.811024 | R99: 11.811024 | S99: 196.67 | T99: 393.33
A100: GE | B100: 12 | C100: TEHUA GREEN/ORANGE OT SOL | D100: GE82512XA | E100: XA | F100: OX | G100: 304 | H100: 4 | I100: 5.5 | J100: 35 | K100: 15 | L100: 15 | M100: 420 | N100: 1680 | O100: 12.13 | P100: 13.779528 | Q100: 5.9055118 | R100: 5.9055118 | S100: 23.33 | T100: 93.33
A101: GE | B101: 13 | C101: TEHUA GREEN/ORANGE OT SOL | D101: GE82513XX | E101: XX | F101: OD | G101: 264 | H101: 12 | I101: 5 | J101: 30 | K101: 15 | L101: 15 | M101: 360 | N101: 4320 | O101: 11.02 | P101: 11.811024 | Q101: 5.9055118 | R101: 5.9055118 | S101: 20 | T101: 240
A102: LH | B102: 1 | C102: SMALL MUSHROOM PINK | D102: LH35001L | E102: E | F102: X | G102: 40 | H102: 100 | I102: 0.5 | J102: 8 | M102: 58 | N102: 5800 | O102: 1.1 | P102: 3.1496063 | Q102: 0 | R102: 0 | S102: 3.22 | T102: 322.22
A103: LH | B103: 2 | C103: SMALL MUSHROOM ORANGE | D103: LH35002L | E103: E | F103: X | G103: 40 | H103: 50 | I103: 0.5 | J103: 8 | M103: 58 | N103: 2900 | O103: 1.1 | P103: 3.1496063 | Q103: 0 | R103: 0 | S103: 3.22 | T103: 161.11
A104: LH | B104: 3 | C104: SMALL MUSHROOM YELOW | D104: LH35003L | E104: E | F104: X | G104: 40 | H104: 50 | I104: 0.5 | J104: 8 | M104: 58 | N104: 2900 | O104: 1.1 | P104: 3.1496063 | Q104: 0 | R104: 0 | S104: 3.22 | T104: 161.11
A105: LH | B105: 4 | C105: DOUBLE MUSHROOM DIF COLR | D105: LH35004OO | E105: OE | F105: ME | G105: 200 | H105: 30 | I105: 2.5 | J105: 14 | K105: 16 | M105: 260 | N105: 7800 | O105: 5.51 | P105: 5.511811 | Q105: 6.2992126 | R105: 0 | S105: 14.44 | T105: 433.33
A106: LH | B106: 5 | C106: XLARGE MUSHROOM GREEN | D106: LH35005XH | E106: XE | F106: OM | G106: 280 | H106: 3 | I106: 5 | J106: 25 | M106: 380 | N106: 1140 | O106: 11.02 | P106: 9.8425197 | Q106: 0 | R106: 0 | S106: 21.11 | T106: 63.33
A107: LH | B107: 6 | C107: XLARGE MUSHROOM PURPLE | D107: LH35006XH | E107: XE | F107: OM | G107: 280 | H107: 3 | I107: 5 | J107: 25 | M107: 380 | N107: 1140 | O107: 11.02 | P107: 9.8425197 | Q107: 0 | R107: 0 | S107: 21.11 | T107: 63.33
A108: LH | B108: 7 | C108: XLARGE MUSHROOM BLUE | D108: LH35007XH | E108: XE | F108: OM | G108: 280 | H108: 3 | I108: 5 | J108: 25 | M108: 380 | N108: 1140 | O108: 11.02 | P108: 9.8425197 | Q108: 0 | R108: 0 | S108: 21.11 | T108: 63.33
A109: LH | B109: 8 | C109: XLARGE MUSHROOM PINK | D109: LH35008XH | E109: XE | F109: OM | G109: 280 | H109: 3 | I109: 5 | J109: 25 | M109: 380 | N109: 1140 | O109: 11.02 | P109: 9.8425197 | Q109: 0 | R109: 0 | S109: 21.11 | T109: 63.33
A110: LH | B110: 9 | C110: XLARGE MUSHROOM NATURAL | D110: LH35009XH | E110: XE | F110: OM | G110: 280 | H110: 8 | I110: 5 | J110: 25 | M110: 380 | N110: 3040 | O110: 11.02 | P110: 9.8425197 | Q110: 0 | R110: 0 | S110: 21.11 | T110: 168.89
A111: JV | B111: 1 | C111: PINK WHITE ENGLISH CHESS | D111: JV82501XX | E111: XX | F111: OD | G111: 264 | H111: 10 | I111: 5 | J111: 4 | K111: 4 | M111: 360 | N111: 3600 | O111: 11.02 | P111: 1.5748031 | Q111: 1.5748031 | R111: 0 | S111: 20 | T111: 200
A112: JV | B112: 2 | C112: PINK GREY ENGLISH CHESS | D112: JV82502MA | E112: MA | F112: MM | G112: 144 | H112: 10 | I112: 4 | J112: 2 | K112: 2 | M112: 190 | N112: 1900 | O112: 8.82 | P112: 0.78740157 | Q112: 0.78740157 | R112: 0 | S112: 10.56 | T112: 105.56
A113: JV | B113: 3 | C113: GREY BLACK ITALIAN CHESS | D113: JV82503HF | E113: HF | F113: OA | G113: 376 | H113: 10 | I113: 4 | J113: 3 | K113: 3 | M113: 500 | N113: 5000 | O113: 8.82 | P113: 1.1811024 | Q113: 1.1811024 | R113: 0 | S113: 27.78 | T113: 277.78
A114: JV | B114: 4 | C114: PINK BLACK ITALIAN HESS | D114: JV82504OX | E114: OX | F114: MH | G114: 184 | H114: 10 | I114: 4 | J114: 2 | K114: 2 | M114: 250 | N114: 2500 | O114: 8.82 | P114: 0.78740157 | Q114: 0.78740157 | R114: 0 | S114: 13.89 | T114: 138.89
A115: JV | B115: 5 | C115: PINK WHITE ITALIAN CHESS | D115: JV82505OX | E115: OX | F115: MH | G115: 184 | H115: 10 | I115: 4 | J115: 2 | K115: 2 | M115: 250 | N115: 2500 | O115: 8.82 | P115: 0.78740157 | Q115: 0.78740157 | R115: 0 | S115: 13.89 | T115: 138.89
A116: JV | B116: 6 | C116: PINK GREY ITALIAN CHESS | D116: JV82506OX | E116: OX | F116: MH | G116: 184 | H116: 10 | I116: 4 | J116: 2 | K116: 2 | M116: 250 | N116: 2500 | O116: 8.82 | P116: 0.78740157 | Q116: 0.78740157 | R116: 0 | S116: 13.89 | T116: 138.89
A117: GS | B117: 16 | C117: PINK MAR RD COASTER SET | D117: GS82516A | E117: A | F117: E | G117: 64 | H117: 15 | I117: 1 | J117: 8 | M117: 85 | N117: 1275 | O117: 2.2 | P117: 3.1496063 | Q117: 0 | R117: 0 | S117: 4.72 | T117: 70.83
A118: GS | B118: 17 | C118: WHITE MAR RC COASTE SET | D118: GS82517A | E118: A | F118: E | G118: 64 | H118: 20 | I118: 1 | J118: 8 | M118: 85 | N118: 1700 | O118: 2.2 | P118: 3.1496063 | Q118: 0 | R118: 0 | S118: 4.72 | T118: 94.44
A119: GS | B119: 18 | C119: MOKA MAR RD COSTER SET | D119: GS82518A | E119: A | F119: E | G119: 64 | H119: 10 | I119: 1 | J119: 8 | M119: 85 | N119: 850 | O119: 2.2 | P119: 3.1496063 | Q119: 0 | R119: 0 | S119: 4.72 | T119: 47.22
A120: GS | B120: 19 | C120: MOKA MAR SQ COSTER SET 8 | D120: GS82519MD | E120: MD | F120: L | G120: 80 | H120: 15 | I120: 2 | J120: 10 | M120: 110 | N120: 1650 | O120: 4.41 | P120: 3.9370079 | Q120: 0 | R120: 0 | S120: 6.11 | T120: 91.67
A121: GS | B121: 20 | C121: PINK MAR SQ COASTER SET | D121: GS82520MD | E121: MD | F121: L | G121: 80 | H121: 15 | I121: 1.5 | J121: 10 | M121: 100 | N121: 1500 | O121: 3.31 | P121: 3.9370079 | Q121: 0 | R121: 0 | S121: 5.56 | T121: 83.33
A122: MM | B122: 21 | C122: AMBER ONIX SCONCE | D122: MM82521OA | E122: OA | F122: MF | G122: 224 | H122: 4 | J122: 26 | K122: 14 | M122: 300 | N122: 1200 | O122: 0 | P122: 10.23622 | Q122: 5.511811 | R122: 0 | S122: 16.67 | T122: 66.67
A123: MM | B123: 22 | C123: ONIX HR SCONCE | D123: MM82522XX | E123: XX | F123: OD | G123: 264 | H123: 2 | J123: 30 | K123: 20 | M123: 350 | N123: 700 | O123: 0 | P123: 11.811024 | Q123: 7.8740157 | R123: 0 | S123: 19.44 | T123: 38.89
A124: MM | B124: 23 | C124: ONIX SQ SCONCE | D124: MM82523XF | E124: XF | F124: OO | G124: 296 | H124: 4 | J124: 40 | K124: 20 | M124: 400 | N124: 1600 | O124: 0 | P124: 15.748031 | Q124: 7.8740157 | R124: 0 | S124: 22.22 | T124: 88.89
A125: MM | B125: 24 | C125: ONIX SQ SCONCE | D125: MM82524XX | E125: XX | F125: OD | G125: 264 | H125: 2 | J125: 35 | K125: 20 | M125: 350 | N125: 700 | O125: 0 | P125: 13.779528 | Q125: 7.8740157 | R125: 0 | S125: 19.44 | T125: 38.89
A126: GS | B126: 32 | D126: GS82532D | E126: D | F126: D | G126: 0 | N126: 0 | O126: 0 | P126: 0 | Q126: 0 | R126: 0 | S126: 0 | T126: 0
A127: BT | B127: 3 | C127: SELENITE MIRROR | D127: BT82503NOF | E127: NOF | F127: EEL | G127: 7416 | H127: 3 | I127: 32 | J127: 96 | M127: 10000 | N127: 30000 | O127: 70.54784 | P127: 37.795276 | Q127: 0 | R127: 0 | S127: 555.56 | T127: 1666.67

Sheet -TRK2
A2: TRK2 | K2: TOTAL | N2: =SUM(N5:N128) -> 493962.54
B4: date | C4: Description | D4: Tag - ID with LC | E4: LC | F4: AQ CODE | G4: RETAIL | H4: Quantity | I4: Weight KG | J4: length in CM | K4: Width in CM | L4: Depth in | M4: Per piece Pesos | N4: Total in Pesos | O4: pounds | P4: Height in Inches | Q4: Width in inches | R4: Depth in Inches | S4: Per Piece US$ | T4: Total in US$ Dollars
C5: COL ONYX ICE | D5: ML82501XO | E5: XO | F5: OX | H5: 12 | J5: 40 | K5: 12 | L5: 12 | M5: 420 | N5: =M5*H5 -> 5040 | O5: =IF(I5>0.1,I5*2.20462," ") | P5: =J5/2.54 -> 15.748031 | Q5: =K5/2.54 -> 4.7244094 | R5: =L5/2.54 -> 4.7244094 | S5: =M5/18 -> 23.333333 | T5: =S5*H5 -> 280
C6: COL ONYX ICE | D6: ML82502HA | E6: HA | F6: XH | H6: 5 | J6: 40 | K6: 16 | L6: 16 | M6: 605 | N6: =M6*H6 -> 3025 | O6: =IF(I6>0.1,I6*2.20462," ") | P6: =J6/2.54 -> 15.748031 | Q6: =K6/2.54 -> 6.2992126 | R6: =L6/2.54 -> 6.2992126 | S6: =M6/18 -> 33.611111 | T6: =S6*H6 -> 168.05556
C7: COL ONYX ICE | D7: ML82503XO | E7: XO | F7: OX | H7: 10 | J7: 35 | K7: 12 | L7: 12 | M7: 410 | N7: =M7*H7 -> 4100 | O7: =IF(I7>0.1,I7*2.20462," ") | P7: =J7/2.54 -> 13.779528 | Q7: =K7/2.54 -> 4.7244094 | R7: =L7/2.54 -> 4.7244094 | S7: =M7/18 -> 22.777778 | T7: =S7*H7 -> 227.77778
C8: COL ONYX ICE | D8: ML82504OA | E8: OA | F8: OD | H8: 23 | J8: 30 | K8: 12 | L8: 12 | M8: 350 | N8: =M8*H8 -> 8050 | O8: =IF(I8>0.1,I8*2.20462," ") | P8: =J8/2.54 -> 11.811024 | Q8: =K8/2.54 -> 4.7244094 | R8: =L8/2.54 -> 4.7244094 | S8: =M8/18 -> 19.444444 | T8: =S8*H8 -> 447.22222
C9: COL ONYX ICE | D9: ML82505XL | E9: XL | F9: OL | H9: 7 | J9: 30 | K9: 16 | L9: 16 | M9: 460 | N9: =M9*H9 -> 3220 | O9: =IF(I9>0.1,I9*2.20462," ") | P9: =J9/2.54 -> 11.811024 | Q9: =K9/2.54 -> 6.2992126 | R9: =L9/2.54 -> 6.2992126 | S9: =M9/18 -> 25.555556 | T9: =S9*H9 -> 178.88889
C10: COL ONYX ICE | D10: ML82506MH | E10: MH | F10: MD | H10: 5 | J10: 25 | K10: 8 | L10: 8 | M10: 180 | N10: =M10*H10 -> 900 | O10: =IF(I10>0.1,I10*2.20462," ") | P10: =J10/2.54 -> 9.8425197 | Q10: =K10/2.54 -> 3.1496063 | R10: =L10/2.54 -> 3.1496063 | S10: =M10/18 -> 10 | T10: =S10*H10 -> 50
C11: AQUA SERP REC MIRROR | D11: EM82576XNL | E11: XNL | F11: OAX | H11: 2 | I11: 30 | J11: 150 | K11: 80 | L11: 10 | M11: 5100 | N11: =M11*H11 -> 10200 | O11: =IF(I11>0.1,I11*2.20462," ") -> 66.1386 | P11: =J11/2.54 -> 59.055118 | Q11: =K11/2.54 -> 31.496063 | R11: =L11/2.54 -> 3.9370079 | S11: =M11/18 -> 283.33333 | T11: =S11*H11 -> 566.66667
C12: TEHUA GREY REC MIRROR | D12: EM82577XNL | E12: XNL | F12: OAX | H12: 4 | I12: 30 | J12: 150 | K12: 80 | L12: 10 | M12: 5100 | N12: =M12*H12 -> 20400 | O12: =IF(I12>0.1,I12*2.20462," ") -> 66.1386 | P12: =J12/2.54 -> 59.055118 | Q12: =K12/2.54 -> 31.496063 | R12: =L12/2.54 -> 3.9370079 | S12: =M12/18 -> 283.33333 | T12: =S12*H12 -> 1133.3333
C13: CRISTALINO REC MIRROR | D13: EM82578ENM | E13: ENM | F13: HOO | H13: 1 | I13: 40 | J13: 183 | K13: 102 | L13: 10 | M13: 7600 | N13: =M13*H13 -> 7600 | O13: =IF(I13>0.1,I13*2.20462," ") -> 88.1848 | P13: =J13/2.54 -> 72.047244 | Q13: =K13/2.54 -> 40.15748 | R13: =L13/2.54 -> 3.9370079 | S13: =M13/18 -> 422.22222 | T13: =S13*H13 -> 422.22222
C14: CRIS GREY SQ MIRROR | D14: EM82579XOL | E14: XOL | F14: OXX | H14: 3 | I14: 27 | J14: 100 | K14: 100 | L14: 10 | M14: 4200 | N14: =M14*H14 -> 12600 | O14: =IF(I14>0.1,I14*2.20462," ") -> 59.52474 | P14: =J14/2.54 -> 39.370079 | Q14: =K14/2.54 -> 39.370079 | R14: =L14/2.54 -> 3.9370079 | S14: =M14/18 -> 233.33333 | T14: =S14*H14 -> 700
C15: TEHUA GREY REC MIRROR | D15: EM82580OLE | E15: OLE | F15: MAN | H15: 2 | I15: 19 | J15: 110 | K15: 60 | L15: 10 | M15: 3400 | N15: =M15*H15 -> 6800 | O15: =IF(I15>0.1,I15*2.20462," ") -> 41.88778 | P15: =J15/2.54 -> 43.307087 | Q15: =K15/2.54 -> 23.622047 | R15: =L15/2.54 -> 3.9370079 | S15: =M15/18 -> 188.88889 | T15: =S15*H15 -> 377.77778
C16: CRISTALINO CANOE | D16: EM82581OFO | E16: OFO | F16: MNH | H16: 1 | J16: 120 | K16: 22 | L16: 11 | M16: 3484 | N16: =M16*H16 -> 3484 | O16: =IF(I16>0.1,I16*2.20462," ") | P16: =J16/2.54 -> 47.244094 | Q16: =K16/2.54 -> 8.6614173 | R16: =L16/2.54 -> 4.3307087 | S16: =M16/18 -> 193.55556 | T16: =S16*H16 -> 193.55556
C17: CRISTALINO CANOE | D17: EM82582OLD | E17: OLD | F17: MAL | H17: 1 | J17: 115 | K17: 22 | L17: 11 | M17: 3339 | N17: =M17*H17 -> 3339 | O17: =IF(I17>0.1,I17*2.20462," ") | P17: =J17/2.54 -> 45.275591 | Q17: =K17/2.54 -> 8.6614173 | R17: =L17/2.54 -> 4.3307087 | S17: =M17/18 -> 185.5 | T17: =S17*H17 -> 185.5
C18: CRISTALINO AMBER CANOE | D18: EM82583OHN | E18: OHN | F18: MFA | H18: 3 | J18: 110 | K18: 22 | L18: 11 | M18: 3194 | N18: =M18*H18 -> 9582 | O18: =IF(I18>0.1,I18*2.20462," ") | P18: =J18/2.54 -> 43.307087 | Q18: =K18/2.54 -> 8.6614173 | R18: =L18/2.54 -> 4.3307087 | S18: =M18/18 -> 177.44444 | T18: =S18*H18 -> 532.33333
C19: CRISTALINO CANOE | D19: EM82584OOE | E19: OOE | F19: MLM | H19: 2 | J19: 110 | K19: 22 | L19: 11 | M19: 2904 | N19: =M19*H19 -> 5808 | O19: =IF(I19>0.1,I19*2.20462," ") | P19: =J19/2.54 -> 43.307087 | Q19: =K19/2.54 -> 8.6614173 | R19: =L19/2.54 -> 4.3307087 | S19: =M19/18 -> 161.33333 | T19: =S19*H19 -> 322.66667
C20: CRISTALINO GREEN CANOE | D20: EM82585MEA | E20: MEA | F20: MMX | H20: 2 | J20: 70 | K20: 22 | L20: 11 | M20: 2032 | N20: =M20*H20 -> 4064 | O20: =IF(I20>0.1,I20*2.20462," ") | P20: =J20/2.54 -> 27.559055 | Q20: =K20/2.54 -> 8.6614173 | R20: =L20/2.54 -> 4.3307087 | S20: =M20/18 -> 112.88889 | T20: =S20*H20 -> 225.77778
C21: CRISTALINO COL | D21: EM82586EN | E21: EN | F21: HO | H21: 18 | I21: 7 | J21: 45 | K21: 15 | L21: 15 | M21: 750 | N21: =M21*H21 -> 13500 | O21: =IF(I21>0.1,I21*2.20462," ") -> 15.43234 | P21: =J21/2.54 -> 17.716535 | Q21: =K21/2.54 -> 5.9055118 | R21: =L21/2.54 -> 5.9055118 | S21: =M21/18 -> 41.666667 | T21: =S21*H21 -> 750
C22: CRISTALINO POL | D22: EM82587XN | E22: XN | F22: OA | H22: 12 | I22: 4 | J22: 40 | K22: 12 | L22: 12 | M22: 500 | N22: =M22*H22 -> 6000 | O22: =IF(I22>0.1,I22*2.20462," ") -> 8.81848 | P22: =J22/2.54 -> 15.748031 | Q22: =K22/2.54 -> 4.7244094 | R22: =L22/2.54 -> 4.7244094 | S22: =M22/18 -> 27.777778 | T22: =S22*H22 -> 333.33333
C23: CRISTALINO POL | D23: EM82588ON | E23: ON | F23: OM | H23: 18 | I23: 3 | J23: 35 | K23: 10 | L23: 10 | M23: 380 | N23: =M23*H23 -> 6840 | O23: =IF(I23>0.1,I23*2.20462," ") -> 6.61386 | P23: =J23/2.54 -> 13.779528 | Q23: =K23/2.54 -> 3.9370079 | R23: =L23/2.54 -> 3.9370079 | S23: =M23/18 -> 21.111111 | T23: =S23*H23 -> 380
C24: GREY POL | D24: EM82589ON | E24: ON | F24: OM | H24: 13 | I24: 3 | J24: 35 | K24: 10 | L24: 10 | M24: 380 | N24: =M24*H24 -> 4940 | O24: =IF(I24>0.1,I24*2.20462," ") -> 6.61386 | P24: =J24/2.54 -> 13.779528 | Q24: =K24/2.54 -> 3.9370079 | R24: =L24/2.54 -> 3.9370079 | S24: =M24/18 -> 21.111111 | T24: =S24*H24 -> 274.44444
C25: CRIS AMBAR POL | D25: EM82590ON | E25: ON | F25: OM | H25: 23 | I25: 3 | J25: 35 | K25: 10 | L25: 10 | M25: 380 | N25: =M25*H25 -> 8740 | O25: =IF(I25>0.1,I25*2.20462," ") -> 6.61386 | P25: =J25/2.54 -> 13.779528 | Q25: =K25/2.54 -> 3.9370079 | R25: =L25/2.54 -> 3.9370079 | S25: =M25/18 -> 21.111111 | T25: =S25*H25 -> 485.55556
C26: CRISTALINO POL | D26: EM82591XE | E26: XE | F26: OE | H26: 14 | I26: 3 | J26: 35 | K26: 12 | L26: 12 | M26: 440 | N26: =M26*H26 -> 6160 | O26: =IF(I26>0.1,I26*2.20462," ") -> 6.61386 | P26: =J26/2.54 -> 13.779528 | Q26: =K26/2.54 -> 4.7244094 | R26: =L26/2.54 -> 4.7244094 | S26: =M26/18 -> 24.444444 | T26: =S26*H26 -> 342.22222
C27: CANOE | D27: JM8254491HDX | E27: HDX | F27: OAA | H27: 1 | J27: 130 | K27: 24 | L27: 10 | M27: 7400 | N27: =M27*H27 -> 7400 | O27: =IF(I27>0.1,I27*2.20462," ") | P27: =J27/2.54 -> 51.181102 | Q27: =K27/2.54 -> 9.4488189 | R27: =L27/2.54 -> 3.9370079 | S27: =M27/18 -> 411.11111 | T27: =S27*H27 -> 411.11111
C28: CANOE | D28: JM8254546EOO | E28: EOO | F28: XFX | H28: 1 | J28: 150 | K28: 24 | L28: 24 | M28: 9600 | N28: =M28*H28 -> 9600 | O28: =IF(I28>0.1,I28*2.20462," ") | P28: =J28/2.54 -> 59.055118 | Q28: =K28/2.54 -> 9.4488189 | R28: =L28/2.54 -> 9.4488189 | S28: =M28/18 -> 533.33333 | T28: =S28*H28 -> 533.33333
C29: CANOE | D29: JM8254574FF | E29: FF | F29: EE | H29: 1 | J29: 130 | K29: 24 | L29: 24 | M29: 1400 | N29: =M29*H29 -> 1400 | O29: =IF(I29>0.1,I29*2.20462," ") | P29: =J29/2.54 -> 51.181102 | Q29: =K29/2.54 -> 9.4488189 | R29: =L29/2.54 -> 9.4488189 | S29: =M29/18 -> 77.777778 | T29: =S29*H29 -> 77.777778
C30: CANOE | D30: JM8254418EOO | E30: EOO | F30: XFX | H30: 1 | J30: 150 | K30: 24 | L30: 24 | M30: 9600 | N30: =M30*H30 -> 9600 | O30: =IF(I30>0.1,I30*2.20462," ") | P30: =J30/2.54 -> 59.055118 | Q30: =K30/2.54 -> 9.4488189 | R30: =L30/2.54 -> 9.4488189 | S30: =M30/18 -> 533.33333 | T30: =S30*H30 -> 533.33333
C31: CANOE | D31: JM8254494HEA | E31: HEA | F31: XOF | H31: 1 | J31: 140 | K31: 24 | L31: 24 | M31: 8400 | N31: =M31*H31 -> 8400 | O31: =IF(I31>0.1,I31*2.20462," ") | P31: =J31/2.54 -> 55.11811 | Q31: =K31/2.54 -> 9.4488189 | R31: =L31/2.54 -> 9.4488189 | S31: =M31/18 -> 466.66667 | T31: =S31*H31 -> 466.66667
C32: CANOE | D32: JM8254542OFX | E32: OFX | F32: MNE | H32: 1 | J32: 95 | K32: 24 | L32: 24 | M32: 5000 | N32: =M32*H32 -> 5000 | O32: =IF(I32>0.1,I32*2.20462," ") | P32: =J32/2.54 -> 37.401575 | Q32: =K32/2.54 -> 9.4488189 | R32: =L32/2.54 -> 9.4488189 | S32: =M32/18 -> 277.77778 | T32: =S32*H32 -> 277.77778
C33: PLATE | D33: JM8253649EHE | E33: EHE | F33: XAN | H33: 1 | J33: 60 | K33: 60 | L33: 9 | M33: 10000 | N33: =M33*H33 -> 10000 | O33: =IF(I33>0.1,I33*2.20462," ") | P33: =J33/2.54 -> 23.622047 | Q33: =K33/2.54 -> 23.622047 | R33: =L33/2.54 -> 3.5433071 | S33: =M33/18 -> 555.55556 | T33: =S33*H33 -> 555.55556
C34: CANOE | D34: JM8254932HDX | E34: HDX | F34: OAA | H34: 1 | J34: 130 | K34: 23 | L34: 10 | M34: 7400 | N34: =M34*H34 -> 7400 | O34: =IF(I34>0.1,I34*2.20462," ") | P34: =J34/2.54 -> 51.181102 | Q34: =K34/2.54 -> 9.0551181 | R34: =L34/2.54 -> 3.9370079 | S34: =M34/18 -> 411.11111 | T34: =S34*H34 -> 411.11111
C35: CANOE | D35: JM8254933HEA | E35: HEA | F35: XOF | H35: 1 | J35: 140 | K35: 23 | L35: 10 | M35: 8400 | N35: =M35*H35 -> 8400 | O35: =IF(I35>0.1,I35*2.20462," ") | P35: =J35/2.54 -> 55.11811 | Q35: =K35/2.54 -> 9.0551181 | R35: =L35/2.54 -> 3.9370079 | S35: =M35/18 -> 466.66667 | T35: =S35*H35 -> 466.66667
C36: CANOE | D36: JM8254970HDX | E36: HDX | F36: OAA | H36: 1 | J36: 130 | K36: 23 | L36: 10 | M36: 7400 | N36: =M36*H36 -> 7400 | O36: =IF(I36>0.1,I36*2.20462," ") | P36: =J36/2.54 -> 51.181102 | Q36: =K36/2.54 -> 9.0551181 | R36: =L36/2.54 -> 3.9370079 | S36: =M36/18 -> 411.11111 | T36: =S36*H36 -> 411.11111
C37: CANOE | D37: JM8254972HDX | E37: HDX | F37: OAA | H37: 1 | J37: 130 | K37: 23 | L37: 10 | M37: 7400 | N37: =M37*H37 -> 7400 | O37: =IF(I37>0.1,I37*2.20462," ") | P37: =J37/2.54 -> 51.181102 | Q37: =K37/2.54 -> 9.0551181 | R37: =L37/2.54 -> 3.9370079 | S37: =M37/18 -> 411.11111 | T37: =S37*H37 -> 411.11111
C38: PLATE | D38: JM8255114MXLM | E38: MXLM | F38: NFO | H38: 1 | J38: 86 | K38: 23 | L38: 24 | M38: 25000 | N38: =M38*H38 -> 25000 | O38: =IF(I38>0.1,I38*2.20462," ") | P38: =J38/2.54 -> 33.858268 | Q38: =K38/2.54 -> 9.0551181 | R38: =L38/2.54 -> 9.4488189 | S38: =M38/18 -> 1388.8889 | T38: =S38*H38 -> 1388.8889
C39: ZEBRA RUSTIC FOUNTAIN | D39: DH82501HAF | E39: HAF | F39: XHA | H39: 1 | I39: 476 | J39: 147 | K39: 34 | L39: 40 | M39: 6254.64 | N39: =M39*H39 -> 6254.64 | O39: =IF(I39>0.1,I39*2.20462," ") -> 1049.3991 | P39: =J39/2.54 -> 57.874016 | Q39: =K39/2.54 -> 13.385827 | R39: =L39/2.54 -> 15.748031 | S39: =M39/18 -> 347.48 | T39: =S39*H39 -> 347.48
C40: ZEBRA RUSTIC FOUNTAIN | D40: DH82502MDHD | E40: MDHD | F40: FHX | H40: 1 | I40: 1017 | J40: 167 | K40: 65 | L40: 50 | M40: 13363.38 | N40: =M40*H40 -> 13363.38 | O40: =IF(I40>0.1,I40*2.20462," ") -> 2242.0985 | P40: =J40/2.54 -> 65.748031 | Q40: =K40/2.54 -> 25.590551 | R40: =L40/2.54 -> 19.685039 | S40: =M40/18 -> 742.41 | T40: =S40*H40 -> 742.41
C41: ZEBRA RUSTIC FOUNTAIN | D41: DH82503MDFD | E41: MDFD | F41: FLH | H41: 1 | I41: 1047 | J41: 155 | K41: 80 | L41: 56 | M41: 13757.58 | N41: =M41*H41 -> 13757.58 | O41: =IF(I41>0.1,I41*2.20462," ") -> 2308.2371 | P41: =J41/2.54 -> 61.023622 | Q41: =K41/2.54 -> 31.496063 | R41: =L41/2.54 -> 22.047244 | S41: =M41/18 -> 764.31 | T41: =S41*H41 -> 764.31
C42: ZEBRA RUSTIC FOUNTAIN | D42: DH82504EEF | E42: EEF | F42: XNA | H42: 1 | I42: 545 | J42: 171 | K42: 35 | L42: 38 | M42: 7161.3 | N42: =M42*H42 -> 7161.3 | O42: =IF(I42>0.1,I42*2.20462," ") -> 1201.5179 | P42: =J42/2.54 -> 67.322835 | Q42: =K42/2.54 -> 13.779528 | R42: =L42/2.54 -> 14.96063 | S42: =M42/18 -> 397.85 | T42: =S42*H42 -> 397.85
C43: WHITE SL. RUSTIC FOUNTAIN | D43: DH82505EMA | E43: EMA | F43: XFD | H43: 1 | I43: 507 | J43: 140 | K43: 52 | L43: 50 | M43: 6661.98 | N43: =M43*H43 -> 6661.98 | O43: =IF(I43>0.1,I43*2.20462," ") -> 1117.7423 | P43: =J43/2.54 -> 55.11811 | Q43: =K43/2.54 -> 20.472441 | R43: =L43/2.54 -> 19.685039 | S43: =M43/18 -> 370.11 | T43: =S43*H43 -> 370.11
C44: WHITE SL. RUSTIC FOUNTAIN | D44: DH82506AEH | E44: AEH | F44: LMD | H44: 1 | I44: 835 | J44: 213 | K44: 50 | L44: 31 | M44: 10971.9 | N44: =M44*H44 -> 10971.9 | O44: =IF(I44>0.1,I44*2.20462," ") -> 1840.8577 | P44: =J44/2.54 -> 83.858268 | Q44: =K44/2.54 -> 19.685039 | R44: =L44/2.54 -> 12.204724 | S44: =M44/18 -> 609.55 | T44: =S44*H44 -> 609.55
C45: WHITE SL. RUSTIC FOUNTAIN | D45: DH82507ENN | E45: ENN | F45: HOA | H45: 1 | I45: 586 | J45: 175 | K45: 56 | L45: 29 | M45: 7700.04 | N45: =M45*H45 -> 7700.04 | O45: =IF(I45>0.1,I45*2.20462," ") -> 1291.9073 | P45: =J45/2.54 -> 68.897638 | Q45: =K45/2.54 -> 22.047244 | R45: =L45/2.54 -> 11.417323 | S45: =M45/18 -> 427.78 | T45: =S45*H45 -> 427.78
C46: WHITE SL. RUSTIC FOUNTAIN | D46: DH82508LFM | E46: LFM | F46: HFN | H46: 1 | I46: 656 | J46: 190 | K46: 50 | L46: 34 | M46: 8619.84 | N46: =M46*H46 -> 8619.84 | O46: =IF(I46>0.1,I46*2.20462," ") -> 1446.2307 | P46: =J46/2.54 -> 74.80315 | Q46: =K46/2.54 -> 19.685039 | R46: =L46/2.54 -> 13.385827 | S46: =M46/18 -> 478.88 | T46: =S46*H46 -> 478.88
C47: WHITE SL. RUSTIC FOUNTAIN | D47: DH82509EFA | E47: EFA | F47: HMX | H47: 1 | I47: 566 | J47: 175 | K47: 40 | L47: 30 | M47: 7437.24 | N47: =M47*H47 -> 7437.24 | O47: =IF(I47>0.1,I47*2.20462," ") -> 1247.8149 | P47: =J47/2.54 -> 68.897638 | Q47: =K47/2.54 -> 15.748031 | R47: =L47/2.54 -> 11.811024 | S47: =M47/18 -> 413.18 | T47: =S47*H47 -> 413.18
C48: ORANGE FOUNTAIN ROCK | D48: DH82523HLL | E48: HLL | F48: XXX | H48: 1 | I48: 456 | J48: 183 | K48: 40 | L48: 20 | M48: 5991.84 | N48: =M48*H48 -> 5991.84 | O48: =IF(I48>0.1,I48*2.20462," ") -> 1005.3067 | P48: =J48/2.54 -> 72.047244 | Q48: =K48/2.54 -> 15.748031 | R48: =L48/2.54 -> 7.8740157 | S48: =M48/18 -> 332.88 | T48: =S48*H48 -> 332.88
C49: ORANGE FOUNTAIN ROCK | D49: DH82524HEO | E49: HEO | F49: XOX | H49: 1 | I49: 443 | J49: 175 | K49: 30 | L49: 26 | M49: 5821.02 | N49: =M49*H49 -> 5821.02 | O49: =IF(I49>0.1,I49*2.20462," ") -> 976.64666 | P49: =J49/2.54 -> 68.897638 | Q49: =K49/2.54 -> 11.811024 | R49: =L49/2.54 -> 10.23622 | S49: =M49/18 -> 323.39 | T49: =S49*H49 -> 323.39
C50: ORANGE FOUNTAIN ROCK | D50: DH82525HNL | E50: HNL | F50: XEH | H50: 1 | I50: 485 | J50: 180 | K50: 40 | L50: 38 | M50: 6372.9 | N50: =M50*H50 -> 6372.9 | O50: =IF(I50>0.1,I50*2.20462," ") -> 1069.2407 | P50: =J50/2.54 -> 70.866142 | Q50: =K50/2.54 -> 15.748031 | R50: =L50/2.54 -> 14.96063 | S50: =M50/18 -> 354.05 | T50: =S50*H50 -> 354.05
... C59: TEHUACAN FOUNTAIN ROCK | D59: FR82510MDOE | E59: MDOE | F59: FXO | H59: 1 | I59: 1098 | J59: 195.58 | K59: 40.64 | L59: 60.96 | M59: 13176 | N59: =M59*H59 -> 13176 | O59: =IF(I59>0.1,I59*2.20462," ") -> 2420.6728 | P59: =J59/2.54 -> 77 | Q59: =K59/2.54 -> 16 | R59: =L59/2.54 -> 24 | S59: =M59/18 -> 732 | T59: =S59*H59 -> 732
C60: EAGLE SCULPTURE | D60: TE825ODNX | E60: ODNX | F60: MHNE | H60: 2 | I60: 110 | J60: 105 | L60: 80 | M60: 26900 | N60: =M60*H60 -> 53800 | O60: =IF(I60>0.1,I60*2.20462," ") -> 242.5082 | P60: =J60/2.54 -> 41.338583 | Q60: =K60/2.54 -> 0 | R60: =L60/2.54 -> 31.496063 | S60: =M60/18 -> 1494.4444 | T60: =S60*H60 -> 2988.8889
C61: PINK MAR RD COASTER PIECES | D61: GS82525M | E61: M | F61: M | H61: 60 | J61: 8 | L61: 1 | M61: 10 | N61: =M61*H61 -> 600 | O61: =IF(I61>0.1,I61*2.20462," ") | P61: =J61/2.54 -> 3.1496063 | Q61: =K61/2.54 -> 0 | R61: =L61/2.54 -> 0.39370079 | S61: =M61/18 -> 0.55555556 | T61: =S61*H61 -> 33.333333
C62: WHITE MAR RD COASTE PIECES | D62: GS82526M | E62: M | F62: M | H62: 120 | J62: 8 | L62: 1 | M62: 10 | N62: =M62*H62 -> 1200 | O62: =IF(I62>0.1,I62*2.20462," ") | P62: =J62/2.54 -> 3.1496063 | Q62: =K62/2.54 -> 0 | R62: =L62/2.54 -> 0.39370079 | S62: =M62/18 -> 0.55555556 | T62: =S62*H62 -> 66.666667
C63: BLACK MAR RD COASTER SET | D63: GS82527F | E63: F | F63: E | H63: 13 | J63: 8 | L63: 1 | M63: 85 | N63: =M63*H63 -> 1105 | O63: =IF(I63>0.1,I63*2.20462," ") | P63: =J63/2.54 -> 3.1496063 | Q63: =K63/2.54 -> 0 | R63: =L63/2.54 -> 0.39370079 | S63: =M63/18 -> 4.7222222 | T63: =S63*H63 -> 61.388889
C64: RED TRAV RD COASTER SET | D64: GS82528F | E64: F | F64: E | H64: 13 | J64: 8 | L64: 1 | M64: 85 | N64: =M64*H64 -> 1105 | O64: =IF(I64>0.1,I64*2.20462," ") | P64: =J64/2.54 -> 3.1496063 | Q64: =K64/2.54 -> 0 | R64: =L64/2.54 -> 0.39370079 | S64: =M64/18 -> 4.7222222 | T64: =S64*H64 -> 61.388889
C65: GREY MAR RD COASTER SET | D65: GS82529F | E65: F | F65: E | H65: 13 | J65: 8 | L65: 1 | M65: 85 | N65: =M65*H65 -> 1105 | O65: =IF(I65>0.1,I65*2.20462," ") | P65: =J65/2.54 -> 3.1496063 | Q65: =K65/2.54 -> 0 | R65: =L65/2.54 -> 0.39370079 | S65: =M65/18 -> 4.7222222 | T65: =S65*H65 -> 61.388889

Sheet -TRK3
A2: TRK3 | E2: 28/10/26 | K2: TOTAL | N2: =SUM(N5:N127) -> 253320.36
B4: date | C4: Description | D4: Tag - ID with LC | E4: LC | F4: AQ CODE | G4: RETAIL | H4: Quantity | I4: Weight KG | J4: length in CM | K4: Width in CM | L4: Depth in | M4: Per piece Pesos | N4: Total in Pesos | O4: pounds | P4: Height in Inches | Q4: Width in inches | R4: Depth in Inches | S4: Per Piece US$ | T4: Total in US$ Dollars
C5: CACTUS SET (4) PCS | D5: AN82501NXH | E5: NXH | F5: LLF | H5: 1 | I5: 385 | J5: 60 | K5: 32 | M5: 12000 | N5: =M5*H5 -> 12000 | O5: =IF(I5>0.1,I5*2.20462," ") -> 848.7787 | P5: =J5/2.54 -> 23.622047 | Q5: =K5/2.54 -> 12.598425 | R5: =L5/2.54 -> 0 | S5: =M5/18 -> 666.66667 | T5: =S5*H5 -> 666.66667
C6: COL ONYX ICE | D6: ML82507HA | E6: HA | F6: XH | H6: 6 | I6: 8 | J6: 40 | K6: 16 | M6: 605 | N6: =M6*H6 -> 3630 | O6: =IF(I6>0.1,I6*2.20462," ") -> 17.63696 | P6: =J6/2.54 -> 15.748031 | Q6: =K6/2.54 -> 6.2992126 | R6: =L6/2.54 -> 0 | S6: =M6/18 -> 33.611111 | T6: =S6*H6 -> 201.66667
C7: SPHERE FOUNTAIN | D7: CP82501MMLL | E7: MMLL | F7: AXX | H7: 2 | I7: 480 | J7: 70 | M7: 15000 | N7: =M7*H7 -> 30000 | O7: =IF(I7>0.1,I7*2.20462," ") -> 1058.2176 | P7: =J7/2.54 -> 27.559055 | Q7: =K7/2.54 -> 0 | R7: =L7/2.54 -> 0 | S7: =M7/18 -> 833.33333 | T7: =S7*H7 -> 1666.6667
C8: RUSTIC TOWER SET (3) | D8: DH325036EAH | E8: EFE | F8: HMM | H8: 1 | I8: 563 | M8: 7397.82 | N8: =M8*H8 -> 7397.82 | O8: =IF(I8>0.1,I8*2.20462," ") -> 1241.2011 | P8: =J8/2.54 -> 0 | Q8: =K8/2.54 -> 0 | R8: =L8/2.54 -> 0 | S8: =M8/18 -> 410.99 | T8: =S8*H8 -> 410.99
C9: ORANGE FOUNTAIN ROCK | D9: DH82529LAF | E9: LAF | F9: HNM | H9: 1 | I9: 672 | M9: 8830.08 | N9: =M9*H9 -> 8830.08 | O9: =IF(I9>0.1,I9*2.20462," ") -> 1481.5046 | P9: =J9/2.54 -> 0 | Q9: =K9/2.54 -> 0 | R9: =L9/2.54 -> 0 | S9: =M9/18 -> 490.56 | T9: =S9*H9 -> 490.56
C10: ORANGE FOUNTAIN ROCK | D10: DH82530ELX | E10: ELX | F10: HDO | H10: 1 | I10: 551 | M10: 7240.14 | N10: =M10*H10 -> 7240.14 | O10: =IF(I10>0.1,I10*2.20462," ") -> 1214.7456 | P10: =J10/2.54 -> 0 | Q10: =K10/2.54 -> 0 | R10: =L10/2.54 -> 0 | S10: =M10/18 -> 402.23 | T10: =S10*H10 -> 402.23
C11: ORANGE FOUNTAIN ROCK | D11: DH82531FHM | E11: FHM | F11: EON | H11: 1 | I11: 725 | M11: 9526.5 | N11: =M11*H11 -> 9526.5 | O11: =IF(I11>0.1,I11*2.20462," ") -> 1598.3495 | P11: =J11/2.54 -> 0 | Q11: =K11/2.54 -> 0 | R11: =L11/2.54 -> 0 | S11: =M11/18 -> 529.25 | T11: =S11*H11 -> 529.25
C12: ORANGE FOUNTAIN ROCK | D12: DH82534AMM | E12: AMM | F12: EFN | H12: 1 | I12: 793 | M12: 10420.02 | N12: =M12*H12 -> 10420.02 | O12: =IF(I12>0.1,I12*2.20462," ") -> 1748.2637 | P12: =J12/2.54 -> 0 | Q12: =K12/2.54 -> 0 | R12: =L12/2.54 -> 0 | S12: =M12/18 -> 578.89 | T12: =S12*H12 -> 578.89
C13: ORANGE FOUNTAIN ROCK | D13: DH82535EON | E13: EON | F13: XFA | H13: 1 | I13: 518 | M13: 6806.52 | N13: =M13*H13 -> 6806.52 | O13: =IF(I13>0.1,I13*2.20462," ") -> 1141.9932 | P13: =J13/2.54 -> 0 | Q13: =K13/2.54 -> 0 | R13: =L13/2.54 -> 0 | S13: =M13/18 -> 378.14 | T13: =S13*H13 -> 378.14
C14: ORANGE FOUNTAIN ROCK | D14: DH82538FEF | E14: FEF | F14: EHM | H14: 1 | I14: 741 | M14: 9736.74 | N14: =M14*H14 -> 9736.74 | O14: =IF(I14>0.1,I14*2.20462," ") -> 1633.6234 | P14: =J14/2.54 -> 0 | Q14: =K14/2.54 -> 0 | R14: =L14/2.54 -> 0 | S14: =M14/18 -> 540.93 | T14: =S14*H14 -> 540.93
C15: ORANGE FOUNTAIN ROCK | D15: DH82539FDL | E15: FDL | F15: EDH | H15: 1 | I15: 690 | M15: 9066.6 | N15: =M15*H15 -> 9066.6 | O15: =IF(I15>0.1,I15*2.20462," ") -> 1521.1878 | P15: =J15/2.54 -> 0 | Q15: =K15/2.54 -> 0 | R15: =L15/2.54 -> 0 | S15: =M15/18 -> 503.7 | T15: =S15*H15 -> 503.7
C16: ORANGE FOUNTAIN ROCK | D16: DH82540AHD | E16: AHD | F16: LDD | H16: 1 | I16: 822 | M16: 10801.08 | N16: =M16*H16 -> 10801.08 | O16: =IF(I16>0.1,I16*2.20462," ") -> 1812.1976 | P16: =J16/2.54 -> 0 | Q16: =K16/2.54 -> 0 | R16: =L16/2.54 -> 0 | S16: =M16/18 -> 600.06 | T16: =S16*H16 -> 600.06
C17: ORANGE FOUNTAIN ROCK | D17: DH82541LML | E17: LML | F17: HHD | H17: 1 | I17: 603 | M17: 7923.42 | N17: =M17*H17 -> 7923.42 | O17: =IF(I17>0.1,I17*2.20462," ") -> 1329.3859 | P17: =J17/2.54 -> 0 | Q17: =K17/2.54 -> 0 | R17: =L17/2.54 -> 0 | S17: =M17/18 -> 440.19 | T17: =S17*H17 -> 440.19
C18: ZEBRA RUSTIC FOUNTAIN | D18: DH82542HFX | E18: HFX | F18: XXA | H18: 1 | I18: 463 | M18: 6083.82 | N18: =M18*H18 -> 6083.82 | O18: =IF(I18>0.1,I18*2.20462," ") -> 1020.7391 | P18: =J18/2.54 -> 0 | Q18: =K18/2.54 -> 0 | R18: =L18/2.54 -> 0 | S18: =M18/18 -> 337.99 | T18: =S18*H18 -> 337.99
C19: ZEBRA RUSTIC FOUNTAIN | D19: DH82543EHE | E19: EHE | F19: XAN | H19: 1 | I19: 533 | M19: 7003.62 | N19: =M19*H19 -> 7003.62 | O19: =IF(I19>0.1,I19*2.20462," ") -> 1175.0625 | P19: =J19/2.54 -> 0 | Q19: =K19/2.54 -> 0 | R19: =L19/2.54 -> 0 | S19: =M19/18 -> 389.09 | T19: =S19*H19 -> 389.09
... C26: GREEN TALAN RUSTIC ROCK | D26: TE82522HML | E26: HML | F26: ONF | H26: 1 | I26: 504 | M26: 5336 | N26: =M26*H26 -> 5336 | O26: =IF(I26>0.1,I26*2.20462," ") -> 1111.1285 | P26: =J26/2.54 -> 0 | Q26: =K26/2.54 -> 0 | R26: =L26/2.54 -> 0 | S26: =M26/18 -> 296.44444 | T26: =S26*H26 -> 296.44444
C27: PINK SER RUSTIC FTN | D27: BT82504HHM | E27: HHM | F27: XME | H27: 1 | I27: 473 | J27: 140 | K27: 55 | L27: 40 | M27: 5676 | N27: =M27*H27 -> 5676 | O27: =IF(I27>0.1,I27*2.20462," ") -> 1042.7853 | P27: =J27/2.54 -> 55.11811 | Q27: =K27/2.54 -> 21.653543 | R27: =L27/2.54 -> 15.748031 | S27: =M27/18 -> 315.33333 | T27: =S27*H27 -> 315.33333
C28: PINK SER RUSTIC FTN | D28: BT82505OAF | E28: OAF | F28: ODE | H28: 1 | I28: 308 | J28: 140 | K28: 48 | L28: 30 | M28: 3696 | N28: =M28*H28 -> 3696 | O28: =IF(I28>0.1,I28*2.20462," ") -> 679.02296 | P28: =J28/2.54 -> 55.11811 | Q28: =K28/2.54 -> 18.897638 | R28: =L28/2.54 -> 11.811024 | S28: =M28/18 -> 205.33333 | T28: =S28*H28 -> 205.33333
C29: BLACK ZEBRA FTN | D29: BT82506MFO | E29: MFO | F29: MOX | H29: 1 | I29: 185 | J29: 70 | K29: 42 | L29: 30 | M29: 2220 | N29: =M29*H29 -> 2220 | O29: =IF(I29>0.1,I29*2.20462," ") -> 407.8547 | P29: =J29/2.54 -> 27.559055 | Q29: =K29/2.54 -> 16.535433 | R29: =L29/2.54 -> 11.811024 | S29: =M29/18 -> 123.33333 | T29: =S29*H29 -> 123.33333
C30: BROWN ONIX FTN | D30: BT82507OLL | E30: OLL | F30: MND | H30: 1 | I30: 285 | J30: 60 | K30: 45 | L30: 38 | M30: 3420 | N30: =M30*H30 -> 3420 | O30: =IF(I30>0.1,I30*2.20462," ") -> 628.3167 | P30: =J30/2.54 -> 23.622047 | Q30: =K30/2.54 -> 17.716535 | R30: =L30/2.54 -> 14.96063 | S30: =M30/18 -> 190 | T30: =S30*H30 -> 190
C31: AQUA SER FTN | D31: BT82508MAE | E31: MAE | F31: MXO | H31: 1 | I31: 198 | J31: 80 | K31: 80 | L31: 29 | M31: 2376 | N31: =M31*H31 -> 2376 | O31: =IF(I31>0.1,I31*2.20462," ") -> 436.51476 | P31: =J31/2.54 -> 31.496063 | Q31: =K31/2.54 -> 31.496063 | R31: =L31/2.54 -> 11.417323 | S31: =M31/18 -> 132 | T31: =S31*H31 -> 132
C32: AQUA SER FTN | D32: BT82509OXM | E32: OXM | F32: MLE | H32: 1 | I32: 247 | J32: 66 | K32: 45 | L32: 36 | M32: 2964 | N32: =M32*H32 -> 2964 | O32: =IF(I32>0.1,I32*2.20462," ") -> 544.54114 | P32: =J32/2.54 -> 25.984252 | Q32: =K32/2.54 -> 17.716535 | R32: =L32/2.54 -> 14.173228 | S32: =M32/18 -> 164.66667 | T32: =S32*H32 -> 164.66667
C33: TEHUA FTN | D33: BT82510OXF | E33: OXF | F33: MLN | H33: 1 | I33: 254 | J33: 80 | K33: 50 | L33: 35 | M33: 3048 | N33: =M33*H33 -> 3048 | O33: =IF(I33>0.1,I33*2.20462," ") -> 559.97348 | P33: =J33/2.54 -> 31.496063 | Q33: =K33/2.54 -> 19.685039 | R33: =L33/2.54 -> 13.779528 | S33: =M33/18 -> 169.33333 | T33: =S33*H33 -> 169.33333
C34: AQUA SER FTN | D34: BT82511XDD | E34: XDD | F34: OMH | H34: 1 | I34: 350 | M34: 3850 | N34: =M34*H34 -> 3850 | O34: =IF(I34>0.1,I34*2.20462," ") -> 771.617 | P34: =J34/2.54 -> 0 | Q34: =K34/2.54 -> 0 | R34: =L34/2.54 -> 0 | S34: =M34/18 -> 213.88889 | T34: =S34*H34 -> 213.88889
C35: TEHUA FTN | D35: BT82512XDD | E35: XDD | F35: OMH | H35: 1 | I35: 350 | M35: 3850 | N35: =M35*H35 -> 3850 | O35: =IF(I35>0.1,I35*2.20462," ") -> 771.617 | P35: =J35/2.54 -> 0 | Q35: =K35/2.54 -> 0 | R35: =L35/2.54 -> 0 | S35: =M35/18 -> 213.88889 | T35: =S35*H35 -> 213.88889
C36: CALCITE WALL PANEL | D36: EM825102XED | E36: XED | F36: OED | H36: 1 | I36: 36 | J36: 90 | K36: 59 | M36: 4500 | N36: =M36*H36 -> 4500 | O36: =IF(I36>0.1,I36*2.20462," ") -> 79.36632 | P36: =J36/2.54 -> 35.433071 | Q36: =K36/2.54 -> 23.228346 | R36: =L36/2.54 -> 0 | S36: =M36/18 -> 250 | T36: =S36*H36 -> 250
C37: GREEN TALAN RUSTIC ROCK | D37: GE325001XDE | E37: XDE | F37: OFL | H37: 1 | I37: 295 | M37: 3540 | N37: =M37*H37 -> 3540 | O37: =IF(I37>0.1,I37*2.20462," ") -> 650.3629 | P37: =J37/2.54 -> 0 | Q37: =K37/2.54 -> 0 | R37: =L37/2.54 -> 0 | S37: =M37/18 -> 196.66667 | T37: =S37*H37 -> 196.66667

Sheet -TRK4
A2: TRK4 | B2: TUCSON | O2: TOTAL | R2: =SUM(M5:M204) -> 1470629.5
A4: date | B4: Description | C4: Tag - ID with LC | D4: LC | E4: AQ CODE | F4: RETAIL | G4: Quantity | H4: Weight KG | I4: length in CM | J4: Width in CM | K4: Depth in | L4: Per piece Pesos | M4: Total in Pesos | N4: pounds | O4: Height in Inches | P4: Width in inches | Q4: Depth in Inches | R4: Per Piece US$ | S4: Total in US$ Dollars
B5: HORSES PANEL | C5: AM82501LLE | D5: LLE | E5: HFE | F5: 5320 | G5: 1 | H5: 44 | I5: 150 | J5: 60 | K5: 10 | L5: 8550 | M5: =Table623[[#This Row],[Per piece Pesos]]*Table623[[#This Row],[Quantity]] -> 8550 | N5: 97.00328 | O5: 59.055118 | P5: 23.622047 | Q5: 3.9370079 | R5: 475 | S5: =Table623[[#This Row],[Per Piece US$]]*Table623[[#This Row],[Quantity]] -> 475
B6: HORSES PANEL | C6: AM82502FEX | D6: FEX | E6: EXA | F6: 6024 | G6: 1 | H6: 49 | I6: 173 | J6: 60 | K6: 10 | L6: 9684 | M6: =Table623[[#This Row],[Per piece Pesos]]*Table623[[#This Row],[Quantity]] -> 9684 | N6: 108.02638 | O6: 68.110236 | P6: 23.622047 | Q6: 3.9370079 | R6: 538 | S6: =Table623[[#This Row],[Per Piece US$]]*Table623[[#This Row],[Quantity]] -> 538
B7: ELK PANEL | C7: AM82503FOD | D7: FOD | E7: EMH | F7: 5760 | G7: 1 | H7: 48 | I7: 166 | J7: 60 | K7: 10 | L7: 9250 | M7: =Table623[[#This Row],[Per piece Pesos]]*Table623[[#This Row],[Quantity]] -> 9250 | N7: 105.82176 | O7: 65.354331 | P7: 23.622047 | Q7: 3.9370079 | R7: 514 | S7: =Table623[[#This Row],[Per Piece US$]]*Table623[[#This Row],[Quantity]] -> 514
B8: MOUNTANIEER PANEL | C8: AM82504FLL | D8: FLL | E8: EHF | F8: 6128 | G8: 1 | H8: 50 | I8: 177 | J8: 60 | K8: 10 | L8: 9840 | M8: =Table623[[#This Row],[Per piece Pesos]]*Table623[[#This Row],[Quantity]] -> 9840 | N8: 110.231 | O8: 69.685039 | P8: 23.622047 | Q8: 3.9370079 | R8: 547 | S8: =Table623[[#This Row],[Per Piece US$]]*Table623[[#This Row],[Quantity]] -> 547
B9: HORSES PANEL | C9: AM82505FLO | D9: FLO | E9: EHH | F9: 6096 | G9: 1 | H9: 50 | I9: 175 | J9: 60 | K9: 10 | L9: 9792 | M9: =Table623[[#This Row],[Per piece Pesos]]*Table623[[#This Row],[Quantity]] -> 9792 | N9: 110.231 | O9: 68.897638 | P9: 23.622047 | Q9: 3.9370079 | R9: 544 | S9: =Table623[[#This Row],[Per Piece US$]]*Table623[[#This Row],[Quantity]] -> 544
B10: HORSES PANEL | C10: AM82506FAH | D10: FAH | E10: ELD | F10: 6272 | G10: 1 | H10: 51 | I10: 180 | J10: 60 | K10: 10 | L10: 10073 | M10: =Table623[[#This Row],[Per piece Pesos]]*Table623[[#This Row],[Quantity]] -> 10073 | N10: 112.43562 | O10: 70.866142 | P10: 23.622047 | Q10: 3.9370079 | R10: 560 | S10: =Table623[[#This Row],[Per Piece US$]]*Table623[[#This Row],[Quantity]] -> 560
B11: HORSES PANEL | C11: AM82507LEA | D11: LEA | E11: HFD | F11: 5264 | G11: 1 | H11: 43 | I11: 144 | J11: 60 | K11: 10 | L11: 8461 | M11: =Table623[[#This Row],[Per piece Pesos]]*Table623[[#This Row],[Quantity]] -> 8461 | N11: 94.79866 | O11: 56.692913 | P11: 23.622047 | Q11: 3.9370079 | R11: 470 | S11: =Table623[[#This Row],[Per Piece US$]]*Table623[[#This Row],[Quantity]] -> 470
B12: HORSES PANEL | C12: AM82508FOH | D12: FOH | E12: EMF | F12: 5792 | G12: 1 | H12: 47 | I12: 162 | J12: 60 | K12: 10 | L12: 9300 | M12: =Table623[[#This Row],[Per piece Pesos]]*Table623[[#This Row],[Quantity]] -> 9300 | N12: 103.61714 | O12: 63.779528 | P12: 23.622047 | Q12: 3.9370079 | R12: 517 | S12: =Table623[[#This Row],[Per Piece US$]]*Table623[[#This Row],[Quantity]] -> 517
B13: ELK PANEL | C13: AM82509FAH | D13: FAH | E13: ELD | F13: 6272 | G13: 1 | H13: 51 | I13: 180 | J13: 60 | K13: 10 | L13: 10073 | M13: =Table623[[#This Row],[Per piece Pesos]]*Table623[[#This Row],[Quantity]] -> 10073 | N13: 112.43562 | O13: 70.866142 | P13: 23.622047 | Q13: 3.9370079 | R13: 560 | S13: =Table623[[#This Row],[Per Piece US$]]*Table623[[#This Row],[Quantity]] -> 560
B14: HORSES PANEL | C14: AM82510FAH | D14: FAH | E14: ELD | F14: 6272 | G14: 1 | H14: 51 | I14: 180 | J14: 60 | K14: 10 | L14: 10073 | M14: =Table623[[#This Row],[Per piece Pesos]]*Table623[[#This Row],[Quantity]] -> 10073 | N14: 112.43562 | O14: 70.866142 | P14: 23.622047 | Q14: 3.9370079 | R14: 560 | S14: =Table623[[#This Row],[Per Piece US$]]*Table623[[#This Row],[Quantity]] -> 560
B15: HORSES PANEL | C15: AM82511FHN | D15: FHN | E15: EXE | F15: 5992 | G15: 1 | H15: 49 | I15: 172 | J15: 60 | K15: 10 | L15: 9628 | M15: =Table623[[#This Row],[Per piece Pesos]]*Table623[[#This Row],[Quantity]] -> 9628 | N15: 108.02638 | O15: 67.716535 | P15: 23.622047 | Q15: 3.9370079 | R15: 535 | S15: =Table623[[#This Row],[Per Piece US$]]*Table623[[#This Row],[Quantity]] -> 535
B16: ELK PANEL | C16: AM82512FHM | D16: FHM | E16: EON | F16: 5928 | G16: 1 | H16: 49 | I16: 170 | J16: 60 | K16: 10 | L16: 9516 | M16: =Table623[[#This Row],[Per piece Pesos]]*Table623[[#This Row],[Quantity]] -> 9516 | N16: 108.02638 | O16: 66.929134 | P16: 23.622047 | Q16: 3.9370079 | R16: 529 | S16: =Table623[[#This Row],[Per Piece US$]]*Table623[[#This Row],[Quantity]] -> 529
B17: FLORITE SOL C/T | C17: RF82501MEE | D17: MEE | E17: MMM | F17: 1240 | G17: 10 | I17: 30 | J17: 15 | K17: 15 | L17: 2000 | M17: =Table623[[#This Row],[Per piece Pesos]]*Table623[[#This Row],[Quantity]] -> 20000 | O17: 11.811024 | P17: 5.9055118 | Q17: 5.9055118 | R17: 111 | S17: =Table623[[#This Row],[Per Piece US$]]*Table623[[#This Row],[Quantity]] -> 1110
B18: FLORITE SOL C/T | C18: RF82502ODD | D18: ODD | E18: MHX | F18: 1600 | G18: 10 | I18: 40 | J18: 15 | K18: 15 | L18: 2570 | M18: =Table623[[#This Row],[Per piece Pesos]]*Table623[[#This Row],[Quantity]] -> 25700 | O18: 15.748031 | P18: 5.9055118 | Q18: 5.9055118 | R18: 143 | S18: =Table623[[#This Row],[Per Piece US$]]*Table623[[#This Row],[Quantity]] -> 1430
B19: FLORITE CUBE | C19: RF82503ODH | D19: ODH | E19: MHL | F19: 1632 | G19: 2 | I19: 20 | J19: 20 | K19: 20 | L19: 2630 | M19: =Table623[[#This Row],[Per piece Pesos]]*Table623[[#This Row],[Quantity]] -> 5260 | O19: 7.8740157 | P19: 7.8740157 | Q19: 7.8740157 | R19: 146 | S19: =Table623[[#This Row],[Per Piece US$]]*Table623[[#This Row],[Quantity]] -> 292
B20: ORANGE ONIX SOL | C20: RF82504XLD | D20: XLD | E20: OEF | F20: 2880 | G20: 1 | I20: 130 | J20: 30 | K20: 30 | L20: 4625 | M20: =Table623[[#This Row],[Per piece Pesos]]*Table623[[#This Row],[Quantity]] -> 4625 | O20: 51.181102 | P20: 11.811024 | Q20: 11.811024 | R20: 257 | S20: =Table623[[#This Row],[Per Piece US$]]*Table623[[#This Row],[Quantity]] -> 257
B21: ORANGE ONIX SOL | C21: RF82505XAH | D21: XAH | E21: OFH | F21: 3072 | G21: 1 | I21: 140 | J21: 30 | K21: 30 | L21: 4925 | M21: =Table623[[#This Row],[Per piece Pesos]]*Table623[[#This Row],[Quantity]] -> 4925 | O21: 55.11811 | P21: 11.811024 | Q21: 11.811024 | R21: 274 | S21: =Table623[[#This Row],[Per Piece US$]]*Table623[[#This Row],[Quantity]] -> 274
B22: ORANGE ONIX SOL | C22: RF82506HDL | D22: HDL | E22: OND | F22: 3248 | G22: 1 | I22: 150 | J22: 30 | K22: 30 | L22: 5225 | M22: =Table623[[#This Row],[Per piece Pesos]]*Table623[[#This Row],[Quantity]] -> 5225 | O22: 59.055118 | P22: 11.811024 | Q22: 11.811024 | R22: 290 | S22: =Table623[[#This Row],[Per Piece US$]]*Table623[[#This Row],[Quantity]] -> 290
B23: PINK SERP SOL | C23: RF82507XMH | D23: XMH | E23: OOH | F23: 2512 | G23: 1 | I23: 135 | J23: 25 | K23: 25 | L23: 4025 | M23: =Table623[[#This Row],[Per piece Pesos]]*Table623[[#This Row],[Quantity]] -> 4025 | O23: 53.149606 | P23: 9.8425197 | Q23: 9.8425197 | R23: 224 | S23: =Table623[[#This Row],[Per Piece US$]]*Table623[[#This Row],[Quantity]] -> 224
B24: PINK SERP SOL | C24: RF82508XDH | D24: XDH | E24: OMF | F24: 2432 | G24: 1 | I24: 130 | J24: 25 | K24: 25 | L24: 3900 | M24: =Table623[[#This Row],[Per piece Pesos]]*Table623[[#This Row],[Quantity]] -> 3900 | O24: 51.181102 | P24: 9.8425197 | Q24: 9.8425197 | R24: 217 | S24: =Table623[[#This Row],[Per Piece US$]]*Table623[[#This Row],[Quantity]] -> 217
B25: PINK SERP SOL | C25: RF82509OFH | D25: OFH | E25: MNL | F25: 2192 | G25: 1 | I25: 115 | J25: 25 | K25: 25 | L25: 3525 | M25: =Table623[[#This Row],[Per piece Pesos]]*Table623[[#This Row],[Quantity]] -> 3525 | O25: 45.275591 | P25: 9.8425197 | Q25: 9.8425197 | R25: 196 | S25: =Table623[[#This Row],[Per Piece US$]]*Table623[[#This Row],[Quantity]] -> 196
B26: PINK SERP REC MIRROR | C26: EM82592XNL | D26: XNL | E26: OAX | F26: 3168 | G26: 9 | H26: 30 | I26: 150 | J26: 80 | K26: 10 | L26: 5100 | M26: =Table623[[#This Row],[Per piece Pesos]]*Table623[[#This Row],[Quantity]] -> 45900 | N26: 66.1386 | O26: 59.055118 | P26: 31.496063 | Q26: 3.9370079 | R26: 283 | S26: =Table623[[#This Row],[Per Piece US$]]*Table623[[#This Row],[Quantity]] -> 2547
B27: AQUA SERP RECT MIRROR | C27: EM82593XNL | D27: XNL | E27: OAX | F27: 3168 | G27: 6 | H27: 30 | I27: 150 | J27: 80 | K27: 10 | L27: 5100 | M27: =Table623[[#This Row],[Per piece Pesos]]*Table623[[#This Row],[Quantity]] -> 30600 | N27: 66.1386 | O27: 59.055118 | P27: 31.496063 | Q27: 3.9370079 | R27: 283 | S27: =Table623[[#This Row],[Per Piece US$]]*Table623[[#This Row],[Quantity]] -> 1698
B28: CRIS GREY SQ MIRROR | C28: EM82594XOL | D28: XOL | E28: OXX | F28: 2608 | G28: 6 | H28: 23 | I28: 100 | J28: 100 | K28: 10 | L28: 4200 | M28: =Table623[[#This Row],[Per piece Pesos]]*Table623[[#This Row],[Quantity]] -> 25200 | N28: 50.70626 | O28: 39.370079 | P28: 39.370079 | Q28: 3.9370079 | R28: 233 | S28: =Table623[[#This Row],[Per Piece US$]]*Table623[[#This Row],[Quantity]] -> 1398
B29: CRIS GREY AMBAR REC MIRROR | C29: EM82595OLE | D29: OLE | E29: MAN | F29: 2120 | G29: 7 | H29: 19 | I29: 110 | J29: 60 | K29: 10 | L29: 3400 | M29: =Table623[[#This Row],[Per piece Pesos]]*Table623[[#This Row],[Quantity]] -> 23800 | N29: 41.88778 | O29: 43.307087 | P29: 23.622047 | Q29: 3.9370079 | R29: 189 | S29: =Table623[[#This Row],[Per Piece US$]]*Table623[[#This Row],[Quantity]] -> 1323
B30: CRIS AMBER RECT MIRROR | C30: EM82596OMA | D30: OMA | E30: MEL | F30: 1744 | G30: 5 | H30: 16 | I30: 100 | J30: 60 | K30: 10 | L30: 2800 | M30: =Table623[[#This Row],[Per piece Pesos]]*Table623[[#This Row],[Quantity]] -> 14000 | N30: 35.27392 | O30: 39.370079 | P30: 23.622047 | Q30: 3.9370079 | R30: 156 | S30: =Table623[[#This Row],[Per Piece US$]]*Table623[[#This Row],[Quantity]] -> 780
B31: CRIS REC MIRROR | C31: EM82597HND | D31: HND | E31: XED | F31: 3920 | G31: 1 | H31: 30 | I31: 155 | J31: 100 | K31: 10 | L31: 6300 | M31: =Table623[[#This Row],[Per piece Pesos]]*Table623[[#This Row],[Quantity]] -> 6300 | N31: 66.1386 | O31: 61.023622 | P31: 39.370079 | Q31: 3.9370079 | R31: 350 | S31: =Table623[[#This Row],[Per Piece US$]]*Table623[[#This Row],[Quantity]] -> 350
B32: PINK SERP RD MIRROR | C32: EM82598HMX | D32: HMX | E32: ONE | F32: 3304 | G32: 3 | H32: 23 | I32: 100 | J32: 100 | K32: 10 | L32: 5300 | M32: =Table623[[#This Row],[Per piece Pesos]]*Table623[[#This Row],[Quantity]] -> 15900 | N32: 50.70626 | O32: 39.370079 | P32: 39.370079 | Q32: 3.9370079 | R32: 295 | S32: =Table623[[#This Row],[Per Piece US$]]*Table623[[#This Row],[Quantity]] -> 885
B33: AQUA SERP RD MIRROR | C33: EM82599XOL | D33: XOL | E33: OXX | F33: 2608 | G33: 3 | H33: 16 | I33: 80 | J33: 100 | K33: 10 | L33: 4200 | M33: =Table623[[#This Row],[Per piece Pesos]]*Table623[[#This Row],[Quantity]] -> 12600 | N33: 35.27392 | O33: 31.496063 | P33: 39.370079 | Q33: 3.9370079 | R33: 233 | S33: =Table623[[#This Row],[Per Piece US$]]*Table623[[#This Row],[Quantity]] -> 699
B34: CRISS DIAMOND TABLE | C34: EM825100LOX | D34: LOX | E34: HHE | F34: 4984 | G34: 1 | H34: 52 | I34: 96 | J34: 96 | K34: 50 | L34: 8000 | M34: =Table623[[#This Row],[Per piece Pesos]]*Table623[[#This Row],[Quantity]] -> 8000 | N34: 114.64024 | O34: 37.795276 | P34: 37.795276 | Q34: 19.685039 | R34: 445 | S34: =Table623[[#This Row],[Per Piece US$]]*Table623[[#This Row],[Quantity]] -> 445
B35: CRISS DIAMOND TABLE | C35: EM825101EHE | D35: EHE | E35: XAN | F35: 4360 | G35: 1 | H35: 38 | I35: 77 | J35: 77 | K35: 46 | L35: 7000 | M35: =Table623[[#This Row],[Per piece Pesos]]*Table623[[#This Row],[Quantity]] -> 7000 | N35: 83.77556 | O35: 30.314961 | P35: 30.314961 | Q35: 18.110236 | R35: 389 | S35: =Table623[[#This Row],[Per Piece US$]]*Table623[[#This Row],[Quantity]] -> 389
B36: CALCITE WALL PANEL | C36: EM825102XED | D36: XED | E36: OED | F36: 2800 | G36: 4 | H36: 36 | I36: 90 | J36: 59 | K36: 10 | L36: 4500 | M36: =Table623[[#This Row],[Per piece Pesos]]*Table623[[#This Row],[Quantity]] -> 18000 | N36: 79.36632 | O36: 35.433071 | P36: 23.228346 | Q36: 3.9370079 | R36: 250 | S36: =Table623[[#This Row],[Per Piece US$]]*Table623[[#This Row],[Quantity]] -> 1000
B37: GREEN CRIS CANOE | C37: EM825103MEA | D37: MEA | E37: MMX | F37: 1264 | G37: 2 | H37: 4.8 | I37: 70 | J37: 22 | K37: 11 | L37: 2032 | M37: =Table623[[#This Row],[Per piece Pesos]]*Table623[[#This Row],[Quantity]] -> 4064 | N37: 10.582176 | O37: 27.559055 | P37: 8.6614173 | Q37: 4.3307087 | R37: 113 | S37: =Table623[[#This Row],[Per Piece US$]]*Table623[[#This Row],[Quantity]] -> 226
... B53: CANOE | C53: JM8255072OXN | D53: OXN | E53: MFM | F53: 1912 | G53: 1 | H53: 7 | I53: 80 | J53: 23 | K53: 10 | L53: 3080 | M53: =Table623[[#This Row],[Per piece Pesos]]*Table623[[#This Row],[Quantity]] -> 3080 | N53: 15.43234 | O53: 31.496063 | P53: 9.0551181 | Q53: 3.9370079 | R53: 171 | S53: =Table623[[#This Row],[Per Piece US$]]*Table623[[#This Row],[Quantity]] -> 171
B54: CANOE | C54: JM8255205XDE | D54: XDE | E54: OMA | F54: 2440 | G54: 1 | I54: 100 | J54: 23 | K54: 10 | L54: 3920 | M54: =Table623[[#This Row],[Per piece Pesos]]*Table623[[#This Row],[Quantity]] -> 3920 | N54: 0 | O54: 39.370079 | P54: 9.0551181 | Q54: 3.9370079 | R54: 218 | S54: =Table623[[#This Row],[Per Piece US$]]*Table623[[#This Row],[Quantity]] -> 218
B55: WALL PANEL | C55: JM8254784MXDL | D55: MXDL | E55: NXX | F55: 10448 | G55: 3 | H55: 55 | I55: 170 | J55: 56 | K55: 10 | L55: 16800 | M55: =Table623[[#This Row],[Per piece Pesos]]*Table623[[#This Row],[Quantity]] -> 50400 | N55: 121.2541 | O55: 66.929134 | P55: 22.047244 | Q55: 3.9370079 | R55: 933 | S55: =Table623[[#This Row],[Per Piece US$]]*Table623[[#This Row],[Quantity]] -> 2799
B56: PEARL ONIX CANOE | C56: JM825101OFX | D56: OFX | E56: MNE | F56: 2184 | G56: 1 | H56: 9 | I56: 90 | J56: 23 | K56: 10 | L56: 3500 | M56: =Table623[[#This Row],[Per piece Pesos]]*Table623[[#This Row],[Quantity]] -> 3500 | N56: 0 | O56: 35.433071 | P56: 9.0551181 | Q56: 3.9370079 | R56: 195 | S56: =Table623[[#This Row],[Per Piece US$]]*Table623[[#This Row],[Quantity]] -> 195
B57: PEARL ONIX CANOE | C57: JM825102OXN | D57: OXN | E57: MFM | F57: 1912 | G57: 1 | H57: 7 | I57: 80 | J57: 23 | K57: 10 | L57: 3080 | M57: =Table623[[#This Row],[Per piece Pesos]]*Table623[[#This Row],[Quantity]] -> 3080 | N57: 0 | O57: 31.496063 | P57: 9.0551181 | Q57: 3.9370079 | R57: 171 | S57: =Table623[[#This Row],[Per Piece US$]]*Table623[[#This Row],[Quantity]] -> 171
B58: PEARL ONIX CANOE | C58: JM825103XDE | D58: XDE | E58: OMA | F58: 2440 | G58: 1 | H58: 10 | I58: 100 | J58: 23 | K58: 10 | L58: 3920 | M58: =Table623[[#This Row],[Per piece Pesos]]*Table623[[#This Row],[Quantity]] -> 3920 | N58: 0 | O58: 39.370079 | P58: 9.0551181 | Q58: 3.9370079 | R58: 218 | S58: =Table623[[#This Row],[Per Piece US$]]*Table623[[#This Row],[Quantity]] -> 218
B59: PEARL ONIX CANOE | C59: JM825104OXN | D59: OXN | E59: MFM | F59: 1912 | G59: 1 | H59: 7 | I59: 80 | J59: 23 | K59: 10 | L59: 3080 | M59: =Table623[[#This Row],[Per piece Pesos]]*Table623[[#This Row],[Quantity]] -> 3080 | N59: 0 | O59: 31.496063 | P59: 9.0551181 | Q59: 3.9370079 | R59: 171 | S59: =Table623[[#This Row],[Per Piece US$]]*Table623[[#This Row],[Quantity]] -> 171
B60: PEARL ONIX PANEL | C60: JM825105MXDL | D60: MXDL | E60: NXX | F60: 10448 | G60: 2 | H60: 55 | I60: 170 | J60: 58 | K60: 10 | L60: 16800 | M60: =Table623[[#This Row],[Per piece Pesos]]*Table623[[#This Row],[Quantity]] -> 33600 | N60: 0 | O60: 66.929134 | P60: 22.834646 | Q60: 3.9370079 | R60: 933 | S60: =Table623[[#This Row],[Per Piece US$]]*Table623[[#This Row],[Quantity]] -> 1866
B61: PEARL ONIX CANOE | C61: JM825106XFM | D61: XFM | E61: OLE | F61: 2968 | G61: 1 | H61: 11 | I61: 120 | J61: 23 | K61: 10 | L61: 4760 | M61: =Table623[[#This Row],[Per piece Pesos]]*Table623[[#This Row],[Quantity]] -> 4760 | N61: 0 | O61: 47.244094 | P61: 9.0551181 | Q61: 3.9370079 | R61: 265 | S61: =Table623[[#This Row],[Per Piece US$]]*Table623[[#This Row],[Quantity]] -> 265
B62: PEARL ONIX CANOE | C62: JM825107ODF | D62: ODF | E62: MHA | F62: 1656 | G62: 1 | H62: 7 | I62: 70 | J62: 24 | K62: 11 | L62: 2660 | M62: =Table623[[#This Row],[Per piece Pesos]]*Table623[[#This Row],[Quantity]] -> 2660 | N62: 0 | O62: 27.559055 | P62: 9.4488189 | Q62: 4.3307087 | R62: 148 | S62: =Table623[[#This Row],[Per Piece US$]]*Table623[[#This Row],[Quantity]] -> 148
B63: PEARL ONIX BOWL | C63: JM825108MDXE | D63: MDXE | E63: FXN | F63: 8280 | G63: 1 | H63: 12 | I63: 50 | J63: 30 | K63: 20 | L63: 13300 | M63: =Table623[[#This Row],[Per piece Pesos]]*Table623[[#This Row],[Quantity]] -> 13300 | N63: 0 | O63: 19.685039 | P63: 11.811024 | Q63: 0 | R63: 739 | S63: =Table623[[#This Row],[Per Piece US$]]*Table623[[#This Row],[Quantity]] -> 739
B64: PEARL ONIX BOWL | C64: JM825109LOD | D64: LOD | E64: HHX | F64: 4960 | G64: 1 | H64: 12 | I64: 55 | J64: 49 | K64: 35 | L64: 7980 | M64: =Table623[[#This Row],[Per piece Pesos]]*Table623[[#This Row],[Quantity]] -> 7980 | N64: 0 | O64: 21.653543 | P64: 19.291339 | Q64: 13.779528 | R64: 443 | S64: =Table623[[#This Row],[Per Piece US$]]*Table623[[#This Row],[Quantity]] -> 443
B65: PEARL ONIX PANEL | C65: JM825110OFFL | D65: OFFL | E65: MNAX | F65: 22208 | G65: 2 | H65: 65 | I65: 200 | J65: 40 | K65: 10 | L65: 35700 | M65: =Table623[[#This Row],[Per piece Pesos]]*Table623[[#This Row],[Quantity]] -> 71400 | N65: 0 | O65: 78.740157 | P65: 15.748031 | Q65: 3.9370079 | R65: 1983 | S65: =Table623[[#This Row],[Per Piece US$]]*Table623[[#This Row],[Quantity]] -> 3966
B66: PEARL ONIX PANEL | C66: JM825111OMFA | D66: OMFA | E66: MEEL | F66: 17424 | G66: 6 | H66: 85 | I66: 300 | J66: 50 | K66: 10 | L66: 28000 | M66: =Table623[[#This Row],[Per piece Pesos]]*Table623[[#This Row],[Quantity]] -> 168000 | N66: 0 | O66: 118.11024 | P66: 19.685039 | Q66: 3.9370079 | R66: 1556 | S66: =Table623[[#This Row],[Per Piece US$]]*Table623[[#This Row],[Quantity]] -> 9336
... B119: ZEBRA TABLE | C119: TE82530OMDN | D119: OMDN | E119: MEDL | F119: 16872 | G119: 1 | H119: 100 | I119: 79 | J119: 180 | K119: 100 | L119: 27115 | M119: =Table623[[#This Row],[Per piece Pesos]]*Table623[[#This Row],[Quantity]] -> 27115 | N119: 220.462 | O119: 31.102362 | P119: 70.866142 | Q119: 39.370079 | R119: 1506 | S119: =Table623[[#This Row],[Per Piece US$]]*Table623[[#This Row],[Quantity]] -> 1506
B120: GREEN TALAN TORSO SCULPURE | C120: TE82531MNO | D120: MNO | E120: MXF | F120: 1536 | G120: 4 | I120: 50 | L120: 2465 | M120: =Table623[[#This Row],[Per piece Pesos]]*Table623[[#This Row],[Quantity]] -> 9860 | N120: 0 | O120: 19.685039 | P120: 0 | Q120: 0 | R120: 137 | S120: =Table623[[#This Row],[Per Piece US$]]*Table623[[#This Row],[Quantity]] -> 548
B121: HONEY ONIX TORSO SCULPTURE | C121: TE82532MNO | D121: MNO | E121: MXF | F121: 1536 | G121: 1 | I121: 50 | L121: 2465 | M121: =Table623[[#This Row],[Per piece Pesos]]*Table623[[#This Row],[Quantity]] -> 2465 | N121: 0 | O121: 19.685039 | P121: 0 | Q121: 0 | R121: 137 | S121: =Table623[[#This Row],[Per Piece US$]]*Table623[[#This Row],[Quantity]] -> 137
B122: WHITE ONIX TORSO SCULPTURE | C122: TE82533MHL | D122: MHL | E122: MDH | F122: 1168 | G122: 1 | I122: 40 | L122: 1870 | M122: =Table623[[#This Row],[Per piece Pesos]]*Table623[[#This Row],[Quantity]] -> 1870 | N122: 0 | O122: 15.748031 | P122: 0 | Q122: 0 | R122: 104 | S122: =Table623[[#This Row],[Per Piece US$]]*Table623[[#This Row],[Quantity]] -> 104
B123: GREEN TALAN TORSO SCULPURE | C123: TE82534MHL | D123: MHL | E123: MDH | F123: 1168 | G123: 1 | I123: 40 | L123: 1870 | M123: =Table623[[#This Row],[Per piece Pesos]]*Table623[[#This Row],[Quantity]] -> 1870 | N123: 0 | O123: 15.748031 | P123: 0 | Q123: 0 | R123: 104 | S123: =Table623[[#This Row],[Per Piece US$]]*Table623[[#This Row],[Quantity]] -> 104
B124: HONEY ONIX TORSO SCULPTURE | C124: TE82535NF | D124: NF | E124: LN | F124: 776 | G124: 1 | I124: 30 | L124: 1232.5 | M124: =Table623[[#This Row],[Per piece Pesos]]*Table623[[#This Row],[Quantity]] -> 1232.5 | N124: 0 | O124: 11.811024 | P124: 0 | Q124: 0 | R124: 69 | S124: =Table623[[#This Row],[Per Piece US$]]*Table623[[#This Row],[Quantity]] -> 69
B125: GREEN TALAN W/BLACK BASE SCULPTURE | C125: TE82536LEE | D125: LEE | E125: HLA | F125: 5240 | G125: 1 | I125: 80 | L125: 8415 | M125: =Table623[[#This Row],[Per piece Pesos]]*Table623[[#This Row],[Quantity]] -> 8415 | N125: 0 | O125: 31.496063 | P125: 0 | Q125: 0 | R125: 468 | S125: =Table623[[#This Row],[Per Piece US$]]*Table623[[#This Row],[Quantity]] -> 468
B126: AQUA SERP. BUTERFLY PANEL 2 PCS SET | C126: TE82537MXML | D126: MXML | E126: NHD | F126: 10528 | G126: 1 | I126: 170 | J126: 60 | K126: 10 | L126: 16915 | M126: =Table623[[#This Row],[Per piece Pesos]]*Table623[[#This Row],[Quantity]] -> 16915 | N126: 0 | O126: 66.929134 | P126: 23.622047 | Q126: 3.9370079 | R126: 940 | S126: =Table623[[#This Row],[Per Piece US$]]*Table623[[#This Row],[Quantity]] -> 940
B127: FLORITE PANEL 2 PCS SET | C127: TE82538OLXO | D127: OLXO | E127: MAAD | F127: 21056 | G127: 1 | I127: 150 | J127: 50 | K127: 10 | L127: 33830 | M127: =Table623[[#This Row],[Per piece Pesos]]*Table623[[#This Row],[Quantity]] -> 33830 | N127: 0 | O127: 59.055118 | P127: 19.685039 | Q127: 3.9370079 | R127: 1880 | S127: =Table623[[#This Row],[Per Piece US$]]*Table623[[#This Row],[Quantity]] -> 1880
B128: TEHUA GREEN/ORANGE SOL C/T | C128: GE82515ED | D128: ED | E128: XL | F128: 400 | G128: 18 | H128: 7 | I128: 50 | J128: 15 | K128: 15 | L128: 645 | M128: =Table623[[#This Row],[Per piece Pesos]]*Table623[[#This Row],[Quantity]] -> 11610 | N128: 15.43234 | O128: 19.685039 | P128: 5.9055118 | Q128: 5.9055118 | R128: 36 | S128: =Table623[[#This Row],[Per Piece US$]]*Table623[[#This Row],[Quantity]] -> 648
B129: TEHUA GREEN/ORANGE SOL C/T | C129: GE82516HM | D129: HM | E129: ON | F129: 328 | G129: 12 | H129: 6 | I129: 40 | J129: 15 | K129: 15 | L129: 525 | M129: =Table623[[#This Row],[Per piece Pesos]]*Table623[[#This Row],[Quantity]] -> 6300 | N129: 13.22772 | O129: 15.748031 | P129: 5.9055118 | Q129: 5.9055118 | R129: 29 | S129: =Table623[[#This Row],[Per Piece US$]]*Table623[[#This Row],[Quantity]] -> 348
B130: TEHUA GRREN ORANGE SOL O/T | C130: GE82517HO | D130: HO | E130: XD | F130: 336 | G130: 4 | H130: 6 | I130: 45 | J130: 15 | K130: 15 | L130: 540 | M130: =Table623[[#This Row],[Per piece Pesos]]*Table623[[#This Row],[Quantity]] -> 2160 | N130: 13.22772 | O130: 17.716535 | P130: 5.9055118 | Q130: 5.9055118 | R130: 30 | S130: =Table623[[#This Row],[Per Piece US$]]*Table623[[#This Row],[Quantity]] -> 120
B131: TEHUA GREEN ORANGE SOL O/T | C131: GE82518XA | D131: XA | E131: OF | F131: 304 | G131: 23 | H131: 6 | I131: 40 | J131: 15 | K131: 15 | L131: 480 | M131: =Table623[[#This Row],[Per piece Pesos]]*Table623[[#This Row],[Quantity]] -> 11040 | N131: 13.22772 | O131: 15.748031 | P131: 5.9055118 | Q131: 5.9055118 | R131: 27 | S131: =Table623[[#This Row],[Per Piece US$]]*Table623[[#This Row],[Quantity]] -> 621
B132: TEHUA GREEN ORANGE SOL O/T | C132: GE82519XO | D132: XO | E132: OX | F132: 256 | G132: 5 | H132: 5 | I132: 35 | J132: 15 | K132: 15 | L132: 420 | M132: =Table623[[#This Row],[Per piece Pesos]]*Table623[[#This Row],[Quantity]] -> 2100 | N132: 11.0231 | O132: 13.779528 | P132: 5.9055118 | Q132: 5.9055118 | R132: 23 | S132: =Table623[[#This Row],[Per Piece US$]]*Table623[[#This Row],[Quantity]] -> 115
B133: TEHUA GREEN ORANGE SOL O/T | C133: GE82520OA | D133: OA | E133: OD | F133: 224 | G133: 5 | H133: 5 | I133: 30 | J133: 15 | K133: 15 | L133: 360 | M133: =Table623[[#This Row],[Per piece Pesos]]*Table623[[#This Row],[Quantity]] -> 1800 | N133: 11.0231 | O133: 11.811024 | P133: 5.9055118 | Q133: 5.9055118 | R133: 20 | S133: =Table623[[#This Row],[Per Piece US$]]*Table623[[#This Row],[Quantity]] -> 100
B134: TEHUA GREEN ORANGE SOL | C134: GE82521MDL | D134: MDL | E134: FL | F134: 848 | G134: 3 | H134: 17 | I134: 80 | J134: 20 | K134: 20 | L134: 1360 | M134: =Table623[[#This Row],[Per piece Pesos]]*Table623[[#This Row],[Quantity]] -> 4080 | N134: 37.47854 | O134: 31.496063 | P134: 7.8740157 | Q134: 7.8740157 | R134: 76 | S134: =Table623[[#This Row],[Per Piece US$]]*Table623[[#This Row],[Quantity]] -> 228
B135: TEHUA GREEN ORANGE SOL | C135: GE82522NH | D135: NH | E135: LF | F135: 752 | G135: 1 | H135: 15 | I135: 70 | J135: 20 | K135: 20 | L135: 1200 | M135: =Table623[[#This Row],[Per piece Pesos]]*Table623[[#This Row],[Quantity]] -> 1200 | N135: 33.0693 | O135: 27.559055 | P135: 7.8740157 | Q135: 7.8740157 | R135: 67 | S135: =Table623[[#This Row],[Per Piece US$]]*Table623[[#This Row],[Quantity]] -> 67
B136: TEHUA GREEN ORANGE SOL | C136: GE82523LN | D136: LN | E136: HN | F136: 552 | G136: 1 | H136: 11 | I136: 50 | J136: 20 | K136: 20 | L136: 880 | M136: =Table623[[#This Row],[Per piece Pesos]]*Table623[[#This Row],[Quantity]] -> 880 | N136: 24.25082 | O136: 19.685039 | P136: 7.8740157 | Q136: 7.8740157 | R136: 49 | S136: =Table623[[#This Row],[Per Piece US$]]*Table623[[#This Row],[Quantity]] -> 49
B137: AMBER SOL | C137: GE82524OXA | D137: OXA | E137: MFD | F137: 1904 | G137: 2 | H137: 34 | I137: 120 | J137: 30 | K137: 30 | L137: 3060 | M137: =Table623[[#This Row],[Per piece Pesos]]*Table623[[#This Row],[Quantity]] -> 6120 | N137: 74.95708 | O137: 47.244094 | P137: 11.811024 | Q137: 11.811024 | R137: 170 | S137: =Table623[[#This Row],[Per Piece US$]]*Table623[[#This Row],[Quantity]] -> 340
B138: AMBER SOL | C138: GE82525MEH | D138: MEH | E138: MMD | F138: 1232 | G138: 1 | H138: 24 | I138: 75 | J138: 30 | K138: 30 | L138: 1980 | M138: =Table623[[#This Row],[Per piece Pesos]]*Table623[[#This Row],[Quantity]] -> 1980 | N138: 52.91088 | O138: 29.527559 | P138: 11.811024 | Q138: 11.811024 | R138: 110 | S138: =Table623[[#This Row],[Per Piece US$]]*Table623[[#This Row],[Quantity]] -> 110
B139: AMBER SOL | C139: GE82526MLE | D139: MLE | E139: MMA | F139: 1320 | G139: 1 | H139: 26 | I139: 100 | J139: 25 | K139: 25 | L139: 2125 | M139: =Table623[[#This Row],[Per piece Pesos]]*Table623[[#This Row],[Quantity]] -> 2125 | N139: 57.32012 | O139: 39.370079 | P139: 9.8425197 | Q139: 9.8425197 | R139: 118 | S139: =Table623[[#This Row],[Per Piece US$]]*Table623[[#This Row],[Quantity]] -> 118
... B151: PYRAMID RED SOL | C151: GE82538XO | D151: XO | E151: OX | F151: 256 | G151: 3 | H151: 6 | I151: 30 | J151: 15 | K151: 15 | L151: 405 | M151: =Table623[[#This Row],[Per piece Pesos]]*Table623[[#This Row],[Quantity]] -> 1215 | N151: 13.22772 | O151: 11.811024 | P151: 5.9055118 | Q151: 5.9055118 | R151: 23 | S151: =Table623[[#This Row],[Per Piece US$]]*Table623[[#This Row],[Quantity]] -> 69
B152: tehuacan sol | C152: ET82501XN | D152: XN | E152: OA | F152: 312 | G152: 8 | I152: 30 | J152: 15 | K152: 15 | L152: 500 | M152: =Table623[[#This Row],[Per piece Pesos]]*Table623[[#This Row],[Quantity]] -> 4000 | N152: 0 | O152: 11.811024 | P152: 5.9055118 | Q152: 5.9055118 | R152: 28 | S152: =Table623[[#This Row],[Per Piece US$]]*Table623[[#This Row],[Quantity]] -> 224
B153: tehuacan sol | C153: ET82502HE | D153: HE | E153: XO | F153: 360 | G153: 15 | I153: 35 | J153: 15 | K153: 15 | L153: 575 | M153: =Table623[[#This Row],[Per piece Pesos]]*Table623[[#This Row],[Quantity]] -> 8625 | N153: 0 | O153: 13.779528 | P153: 5.9055118 | Q153: 5.9055118 | R153: 32 | S153: =Table623[[#This Row],[Per Piece US$]]*Table623[[#This Row],[Quantity]] -> 480
B154: honey onix sol | C154: ET82503ED | D154: ED | E154: XL | F154: 400 | G154: 18 | I154: 40 | J154: 15 | K154: 15 | L154: 650 | M154: =Table623[[#This Row],[Per piece Pesos]]*Table623[[#This Row],[Quantity]] -> 11700 | N154: 0 | O154: 15.748031 | P154: 5.9055118 | Q154: 5.9055118 | R154: 36 | S154: =Table623[[#This Row],[Per Piece US$]]*Table623[[#This Row],[Quantity]] -> 648
B155: tehuacan sol | C155: ET82504ED | D155: ED | E155: XL | F155: 400 | G155: 12 | I155: 40 | J155: 15 | K155: 15 | L155: 650 | M155: =Table623[[#This Row],[Per piece Pesos]]*Table623[[#This Row],[Quantity]] -> 7800 | N155: 0 | O155: 15.748031 | P155: 5.9055118 | Q155: 5.9055118 | R155: 36 | S155: =Table623[[#This Row],[Per Piece US$]]*Table623[[#This Row],[Quantity]] -> 432
B156: cloud onix sol | C156: ET82505EL | D156: EL | E156: HD | F156: 448 | G156: 3 | I156: 45 | J156: 15 | K156: 15 | L156: 725 | M156: =Table623[[#This Row],[Per piece Pesos]]*Table623[[#This Row],[Quantity]] -> 2175 | N156: 0 | O156: 17.716535 | P156: 5.9055118 | Q156: 5.9055118 | R156: 40 | S156: =Table623[[#This Row],[Per Piece US$]]*Table623[[#This Row],[Quantity]] -> 120
B157: cloud onix sol | C157: ET82506ED | D157: ED | E157: XL | F157: 400 | G157: 7 | I157: 40 | J157: 15 | K157: 15 | L157: 650 | M157: =Table623[[#This Row],[Per piece Pesos]]*Table623[[#This Row],[Quantity]] -> 4550 | N157: 0 | O157: 15.748031 | P157: 5.9055118 | Q157: 5.9055118 | R157: 36 | S157: =Table623[[#This Row],[Per Piece US$]]*Table623[[#This Row],[Quantity]] -> 252
B158: serpentine onix sol | C158: ET82507ED | D158: ED | E158: XL | F158: 400 | G158: 1 | I158: 40 | J158: 15 | K158: 15 | L158: 650 | M158: =Table623[[#This Row],[Per piece Pesos]]*Table623[[#This Row],[Quantity]] -> 650 | N158: 0 | O158: 15.748031 | P158: 5.9055118 | Q158: 5.9055118 | R158: 36 | S158: =Table623[[#This Row],[Per Piece US$]]*Table623[[#This Row],[Quantity]] -> 36
B159: honey onix sol | C159: ET82508EN | D159: EN | E159: HO | F159: 472 | G159: 1 | I159: 50 | J159: 15 | K159: 15 | L159: 750 | M159: =Table623[[#This Row],[Per piece Pesos]]*Table623[[#This Row],[Quantity]] -> 750 | N159: 0 | O159: 19.685039 | P159: 5.9055118 | Q159: 5.9055118 | R159: 42 | S159: =Table623[[#This Row],[Per Piece US$]]*Table623[[#This Row],[Quantity]] -> 42
B160: honey onix sol | C160: ET82509XN | D160: XN | E160: OA | F160: 312 | G160: 3 | I160: 30 | J160: 15 | K160: 15 | L160: 500 | M160: =Table623[[#This Row],[Per piece Pesos]]*Table623[[#This Row],[Quantity]] -> 1500 | N160: 0 | O160: 11.811024 | P160: 5.9055118 | Q160: 5.9055118 | R160: 28 | S160: =Table623[[#This Row],[Per Piece US$]]*Table623[[#This Row],[Quantity]] -> 84
B161: white san luis sol | C161: ET82510XN | D161: XN | E161: OA | F161: 312 | G161: 2 | I161: 30 | J161: 15 | K161: 15 | L161: 500 | M161: =Table623[[#This Row],[Per piece Pesos]]*Table623[[#This Row],[Quantity]] -> 1000 | N161: 0 | O161: 11.811024 | P161: 5.9055118 | Q161: 5.9055118 | R161: 28 | S161: =Table623[[#This Row],[Per Piece US$]]*Table623[[#This Row],[Quantity]] -> 56
B162: serpentine onix sol | C162: ET82511EN | D162: EN | E162: HO | F162: 472 | G162: 1 | I162: 50 | J162: 15 | K162: 15 | L162: 750 | M162: =Table623[[#This Row],[Per piece Pesos]]*Table623[[#This Row],[Quantity]] -> 750 | N162: 0 | O162: 19.685039 | P162: 5.9055118 | Q162: 5.9055118 | R162: 42 | S162: =Table623[[#This Row],[Per Piece US$]]*Table623[[#This Row],[Quantity]] -> 42
B163: blue onix sol | C163: ET82512EL | D163: EL | E163: HD | F163: 448 | G163: 1 | I163: 45 | J163: 15 | K163: 15 | L163: 725 | M163: =Table623[[#This Row],[Per piece Pesos]]*Table623[[#This Row],[Quantity]] -> 725 | N163: 0 | O163: 17.716535 | P163: 5.9055118 | Q163: 5.9055118 | R163: 40 | S163: =Table623[[#This Row],[Per Piece US$]]*Table623[[#This Row],[Quantity]] -> 40
... B203: black white onix sol c/top | C203: ET82552AE | D203: AE | E203: LM | F203: 680 | G203: 1 | I203: 50 | J203: 20 | K203: 20 | L203: 1100 | M203: =Table623[[#This Row],[Per piece Pesos]]*Table623[[#This Row],[Quantity]] -> 1100 | N203: 0 | O203: 19.685039 | P203: 7.8740157 | Q203: 7.8740157 | R203: 61 | S203: =Table623[[#This Row],[Per Piece US$]]*Table623[[#This Row],[Quantity]] -> 61
B204: SELENITE CILINDERS | C204: BT82513AE | D204: AE | E204: LM | F204: 680 | G204: 11 | H204: 3 | I204: 40 | J204: 12 | L204: 1100 | M204: =Table623[[#This Row],[Per piece Pesos]]*Table623[[#This Row],[Quantity]] -> 12100 | N204: 6.61386 | O204: 15.748031 | P204: 4.7244094 | Q204: 0 | R204: 61 | S204: =Table623[[#This Row],[Per Piece US$]]*Table623[[#This Row],[Quantity]] -> 671

Sheet EM
A1: EM | K1: =SUM(K93:K118) -> 325420 | T1: Book # | U1: 825
A2: EMMANUEL DE LOS SANTOS | K2: =SUM(Inventory_List_Table3[TOTAL PESOS]) -> 779315.5 | T2: Rate | U2: 18 | Y2: =AVERAGE(Y21:Y118) -> 2795.1332
A3: # | B3: Date | C3: Description Color - Object Type | D3: TAG-ID | E3: Q | F3: KG | G3: H CM | H3: W CM | I3: D CM | J3: Per piece MXN$ | K3: TOTAL PESOS | L3: POUNDS | M3: H Inches | N3: W Inches | O3: D Incbes | P3: AQ | Q3: AQ ROUND | R3: LND | S3: LND ROUND | T3: RETAIL | U3: TOTAL USD | V3: AQC | W3: LC | X3: SQCM | Y3: SQM PRICE
A4: 01 | C4: GREY RUSTIC ROCK FTN | D4: EM325055OHL | E4: 1 | F4: 228 | G4: 129 | H4: 42 | I4: 21 | J4: 2850 | K4: =Inventory_List_Table3[[#This Row],[Q]]*Inventory_List_Table3[[#This Row],[Per piece MXN$]] -> 2850 | L4: =Inventory_List_Table3[[#This Row],[KG]]*2.20462 -> 502.65336 | M4: =Inventory_List_Table3[[#This Row],[H CM]]/2.54 -> 50.787402 | N4: =Inventory_List_Table3[[#This Row],[W CM]]/2.54 -> 16.535433 | O4: =Inventory_List_Table3[[#This Row],[D CM ]]/2.54 -> 8.2677165 | P4: =Inventory_List_Table3[[#This Row],[Per piece MXN$]]/$U$2 -> 158.33333 | Q4: =IF(MOD(P4,1)>0.4,ROUNDUP(P4,0),ROUNDDOWN(P4,0)) -> 158 | R4: =Inventory_List_Table3[[#This Row],[AQ ROUND]]*1.4 -> 221.2 | S4: =IF(MOD(R4,1)>0.4,ROUNDUP(R4,0),ROUNDDOWN(R4,0)) -> 221 | T4: =Inventory_List_Table3[[#This Row],[LND ROUND]]*12 -> 2652 | U4: x` | V4: MEA | W4: OOM | X4: =Inventory_List_Table3[[#This Row],[H CM]]*Inventory_List_Table3[[#This Row],[W CM]]*Inventory_List_Table3[[#This Row],[D CM ]] -> 113778 | Y4: =Inventory_List_Table3[[#This Row],[Per piece MXN$]]/Inventory_List_Table3[[#This Row],[KG]] -> 12.5
A5: 02 | C5: GREY RUSTIC ROCK FTN | D5: EM325056OFF | E5: 1 | F5: 257 | G5: 95 | H5: 45 | I5: 27 | J5: 3212.5 | K5: =Inventory_List_Table3[[#This Row],[Q]]*Inventory_List_Table3[[#This Row],[Per piece MXN$]] -> 3212.5 | L5: =Inventory_List_Table3[[#This Row],[KG]]*2.20462 -> 566.58734 | M5: =Inventory_List_Table3[[#This Row],[H CM]]/2.54 -> 37.401575 | N5: =Inventory_List_Table3[[#This Row],[W CM]]/2.54 -> 17.716535 | O5: =Inventory_List_Table3[[#This Row],[D CM ]]/2.54 -> 10.629921 | P5: =Inventory_List_Table3[[#This Row],[Per piece MXN$]]/$U$2 -> 178.47222 | Q5: =IF(MOD(P5,1)>0.4,ROUNDUP(P5,0),ROUNDDOWN(P5,0)) -> 179 | R5: =Inventory_List_Table3[[#This Row],[AQ ROUND]]*1.4 -> 250.6 | S5: =IF(MOD(R5,1)>0.4,ROUNDUP(R5,0),ROUNDDOWN(R5,0)) -> 251 | T5: =Inventory_List_Table3[[#This Row],[LND ROUND]]*12 -> 3012 | U5: =Inventory_List_Table3[[#This Row],[AQ]]*Inventory_List_Table3[[#This Row],[Q]] -> 178.47222 | V5: MFN | W5: OEM | X5: =Inventory_List_Table3[[#This Row],[H CM]]*Inventory_List_Table3[[#This Row],[W CM]]*Inventory_List_Table3[[#This Row],[D CM ]] -> 115425 | Y5: =Inventory_List_Table3[[#This Row],[Per piece MXN$]]/Inventory_List_Table3[[#This Row],[KG]] -> 12.5
A6: 03 | C6: GREY RUSTIC ROCK FTN | D6: EM325057OHO | E6: 1 | F6: 224 | G6: 95 | H6: 45 | I6: 23 | J6: 2800 | K6: =Inventory_List_Table3[[#This Row],[Q]]*Inventory_List_Table3[[#This Row],[Per piece MXN$]] -> 2800 | L6: =Inventory_List_Table3[[#This Row],[KG]]*2.20462 -> 493.83488 | M6: =Inventory_List_Table3[[#This Row],[H CM]]/2.54 -> 37.401575 | N6: =Inventory_List_Table3[[#This Row],[W CM]]/2.54 -> 17.716535 | O6: =Inventory_List_Table3[[#This Row],[D CM ]]/2.54 -> 9.0551181 | P6: =Inventory_List_Table3[[#This Row],[Per piece MXN$]]/$U$2 -> 155.55556 | Q6: =IF(MOD(P6,1)>0.4,ROUNDUP(P6,0),ROUNDDOWN(P6,0)) -> 156 | R6: =Inventory_List_Table3[[#This Row],[AQ ROUND]]*1.4 -> 218.4 | S6: =IF(MOD(R6,1)>0.4,ROUNDUP(R6,0),ROUNDDOWN(R6,0)) -> 218 | T6: =Inventory_List_Table3[[#This Row],[LND ROUND]]*12 -> 2616 | U6: =Inventory_List_Table3[[#This Row],[AQ]]*Inventory_List_Table3[[#This Row],[Q]] -> 155.55556 | V6: MEL | W6: OMA | X6: =Inventory_List_Table3[[#This Row],[H CM]]*Inventory_List_Table3[[#This Row],[W CM]]*Inventory_List_Table3[[#This Row],[D CM ]] -> 98325 | Y6: =Inventory_List_Table3[[#This Row],[Per piece MXN$]]/Inventory_List_Table3[[#This Row],[KG]] -> 12.5
A7: 04 | C7: GREY RUSTIC ROCK FTN | D7: EM325058MXL | E7: 1 | F7: 126 | G7: 100 | H7: 40 | I7: 23 | J7: 1575 | K7: =Inventory_List_Table3[[#This Row],[Q]]*Inventory_List_Table3[[#This Row],[Per piece MXN$]] -> 1575 | L7: =Inventory_List_Table3[[#This Row],[KG]]*2.20462 -> 277.78212 | M7: =Inventory_List_Table3[[#This Row],[H CM]]/2.54 -> 39.370079 | N7: =Inventory_List_Table3[[#This Row],[W CM]]/2.54 -> 15.748031 | O7: =Inventory_List_Table3[[#This Row],[D CM ]]/2.54 -> 9.0551181 | P7: =Inventory_List_Table3[[#This Row],[Per piece MXN$]]/$U$2 -> 87.5 | Q7: =IF(MOD(P7,1)>0.4,ROUNDUP(P7,0),ROUNDDOWN(P7,0)) -> 88 | R7: =Inventory_List_Table3[[#This Row],[AQ ROUND]]*1.4 -> 123.2 | S7: =IF(MOD(R7,1)>0.4,ROUNDUP(R7,0),ROUNDDOWN(R7,0)) -> 123 | T7: =Inventory_List_Table3[[#This Row],[LND ROUND]]*12 -> 1476 | U7: =Inventory_List_Table3[[#This Row],[AQ]]*Inventory_List_Table3[[#This Row],[Q]] -> 87.5 | V7: AA | W7: MOX | X7: =Inventory_List_Table3[[#This Row],[H CM]]*Inventory_List_Table3[[#This Row],[W CM]]*Inventory_List_Table3[[#This Row],[D CM ]] -> 92000 | Y7: =Inventory_List_Table3[[#This Row],[Per piece MXN$]]/Inventory_List_Table3[[#This Row],[KG]] -> 12.5
A8: 05 | C8: GREY RUSTIC ROCK FTN | D8: EM325060OXH | E8: 1 | F8: 216 | G8: 100 | H8: 45 | I8: 29 | J8: 2700 | K8: =Inventory_List_Table3[[#This Row],[Q]]*Inventory_List_Table3[[#This Row],[Per piece MXN$]] -> 2700 | L8: =Inventory_List_Table3[[#This Row],[KG]]*2.20462 -> 476.19792 | M8: =Inventory_List_Table3[[#This Row],[H CM]]/2.54 -> 39.370079 | N8: =Inventory_List_Table3[[#This Row],[W CM]]/2.54 -> 17.716535 | O8: =Inventory_List_Table3[[#This Row],[D CM ]]/2.54 -> 11.417323 | P8: =Inventory_List_Table3[[#This Row],[Per piece MXN$]]/$U$2 -> 150 | Q8: =IF(MOD(P8,1)>0.4,ROUNDUP(P8,0),ROUNDDOWN(P8,0)) -> 150 | R8: =Inventory_List_Table3[[#This Row],[AQ ROUND]]*1.4 -> 210 | S8: =IF(MOD(R8,1)>0.4,ROUNDUP(R8,0),ROUNDDOWN(R8,0)) -> 210 | T8: =Inventory_List_Table3[[#This Row],[LND ROUND]]*12 -> 2520 | U8: =Inventory_List_Table3[[#This Row],[AQ]]*Inventory_List_Table3[[#This Row],[Q]] -> 150 | V8: MED | W8: OMD | X8: =Inventory_List_Table3[[#This Row],[H CM]]*Inventory_List_Table3[[#This Row],[W CM]]*Inventory_List_Table3[[#This Row],[D CM ]] -> 130500 | Y8: =Inventory_List_Table3[[#This Row],[Per piece MXN$]]/Inventory_List_Table3[[#This Row],[KG]] -> 12.5
A9: 06 | C9: GREY RUSTIC ROCK FTN | D9: EM325061NN | E9: 1 | F9: 92 | G9: 68 | H9: 33 | I9: 23 | J9: 1150 | K9: =Inventory_List_Table3[[#This Row],[Q]]*Inventory_List_Table3[[#This Row],[Per piece MXN$]] -> 1150 | L9: =Inventory_List_Table3[[#This Row],[KG]]*2.20462 -> 202.82504 | M9: =Inventory_List_Table3[[#This Row],[H CM]]/2.54 -> 26.771654 | N9: =Inventory_List_Table3[[#This Row],[W CM]]/2.54 -> 12.992126 | O9: =Inventory_List_Table3[[#This Row],[D CM ]]/2.54 -> 9.0551181 | P9: =Inventory_List_Table3[[#This Row],[Per piece MXN$]]/$U$2 -> 63.888889 | Q9: =IF(MOD(P9,1)>0.4,ROUNDUP(P9,0),ROUNDDOWN(P9,0)) -> 64 | R9: =Inventory_List_Table3[[#This Row],[AQ ROUND]]*1.4 -> 89.6 | S9: =IF(MOD(R9,1)>0.4,ROUNDUP(R9,0),ROUNDDOWN(R9,0)) -> 90 | T9: =Inventory_List_Table3[[#This Row],[LND ROUND]]*12 -> 1080 | U9: =Inventory_List_Table3[[#This Row],[AQ]]*Inventory_List_Table3[[#This Row],[Q]] -> 63.888889 | V9: LH | W9: ND | X9: =Inventory_List_Table3[[#This Row],[H CM]]*Inventory_List_Table3[[#This Row],[W CM]]*Inventory_List_Table3[[#This Row],[D CM ]] -> 51612 | Y9: =Inventory_List_Table3[[#This Row],[Per piece MXN$]]/Inventory_List_Table3[[#This Row],[KG]] -> 12.5
A10: 07 | C10: SERPENTINE RUSTIC ROCK FTN | D10: EM325062OAD | E10: 1 | F10: 260 | G10: 93 | H10: 37 | I10: 40 | J10: 3250 | K10: =Inventory_List_Table3[[#This Row],[Q]]*Inventory_List_Table3[[#This Row],[Per piece MXN$]] -> 3250 | L10: =Inventory_List_Table3[[#This Row],[KG]]*2.20462 -> 573.2012 | M10: =Inventory_List_Table3[[#This Row],[H CM]]/2.54 -> 36.614173 | N10: =Inventory_List_Table3[[#This Row],[W CM]]/2.54 -> 14.566929 | O10: =Inventory_List_Table3[[#This Row],[D CM ]]/2.54 -> 15.748031 | P10: =Inventory_List_Table3[[#This Row],[Per piece MXN$]]/$U$2 -> 180.55556 | Q10: =IF(MOD(P10,1)>0.4,ROUNDUP(P10,0),ROUNDDOWN(P10,0)) -> 181 | R10: =Inventory_List_Table3[[#This Row],[AQ ROUND]]*1.4 -> 253.4 | S10: =IF(MOD(R10,1)>0.4,ROUNDUP(R10,0),ROUNDDOWN(R10,0)) -> 253 | T10: =Inventory_List_Table3[[#This Row],[LND ROUND]]*12 -> 3036 | U10: =Inventory_List_Table3[[#This Row],[AQ]]*Inventory_List_Table3[[#This Row],[Q]] -> 180.55556 | V10: MAM | W10: OEX | X10: =Inventory_List_Table3[[#This Row],[H CM]]*Inventory_List_Table3[[#This Row],[W CM]]*Inventory_List_Table3[[#This Row],[D CM ]] -> 137640 | Y10: =Inventory_List_Table3[[#This Row],[Per piece MXN$]]/Inventory_List_Table3[[#This Row],[KG]] -> 12.5
A11: 08 | C11: SERPENTINE RUSTIC ROCK FTN | D11: EM325063OXH | E11: 1 | F11: 216 | G11: 91 | H11: 42 | I11: 32 | J11: 2700 | K11: =Inventory_List_Table3[[#This Row],[Q]]*Inventory_List_Table3[[#This Row],[Per piece MXN$]] -> 2700 | L11: =Inventory_List_Table3[[#This Row],[KG]]*2.20462 -> 476.19792 | M11: =Inventory_List_Table3[[#This Row],[H CM]]/2.54 -> 35.826772 | N11: =Inventory_List_Table3[[#This Row],[W CM]]/2.54 -> 16.535433 | O11: =Inventory_List_Table3[[#This Row],[D CM ]]/2.54 -> 12.598425 | P11: =Inventory_List_Table3[[#This Row],[Per piece MXN$]]/$U$2 -> 150 | Q11: =IF(MOD(P11,1)>0.4,ROUNDUP(P11,0),ROUNDDOWN(P11,0)) -> 150 | R11: =Inventory_List_Table3[[#This Row],[AQ ROUND]]*1.4 -> 210 | S11: =IF(MOD(R11,1)>0.4,ROUNDUP(R11,0),ROUNDDOWN(R11,0)) -> 210 | T11: =Inventory_List_Table3[[#This Row],[LND ROUND]]*12 -> 2520 | U11: =Inventory_List_Table3[[#This Row],[AQ]]*Inventory_List_Table3[[#This Row],[Q]] -> 150 | V11: MED | W11: OMD | X11: =Inventory_List_Table3[[#This Row],[H CM]]*Inventory_List_Table3[[#This Row],[W CM]]*Inventory_List_Table3[[#This Row],[D CM ]] -> 122304 | Y11: =Inventory_List_Table3[[#This Row],[Per piece MXN$]]/Inventory_List_Table3[[#This Row],[KG]] -> 12.5
A12: 09 | C12: SERPENTINE RUSTIC ROCK FTN | D12: EM325064MLO | E12: 1 | F12: 151 | G12: 88 | H12: 49 | I12: 25 | J12: 1887.5 | K12: =Inventory_List_Table3[[#This Row],[Q]]*Inventory_List_Table3[[#This Row],[Per piece MXN$]] -> 1887.5 | L12: =Inventory_List_Table3[[#This Row],[KG]]*2.20462 -> 332.89762 | M12: =Inventory_List_Table3[[#This Row],[H CM]]/2.54 -> 34.645669 | N12: =Inventory_List_Table3[[#This Row],[W CM]]/2.54 -> 19.291339 | O12: =Inventory_List_Table3[[#This Row],[D CM ]]/2.54 -> 9.8425197 | P12: =Inventory_List_Table3[[#This Row],[Per piece MXN$]]/$U$2 -> 104.86111 | Q12: =IF(MOD(P12,1)>0.4,ROUNDUP(P12,0),ROUNDDOWN(P12,0)) -> 105 | R12: =Inventory_List_Table3[[#This Row],[AQ ROUND]]*1.4 -> 147 | S12: =IF(MOD(R12,1)>0.4,ROUNDUP(R12,0),ROUNDDOWN(R12,0)) -> 147 | T12: =Inventory_List_Table3[[#This Row],[LND ROUND]]*12 -> 1764 | U12: =Inventory_List_Table3[[#This Row],[AQ]]*Inventory_List_Table3[[#This Row],[Q]] -> 104.86111 | V12: MDE | W12: MHF | X12: =Inventory_List_Table3[[#This Row],[H CM]]*Inventory_List_Table3[[#This Row],[W CM]]*Inventory_List_Table3[[#This Row],[D CM ]] -> 107800 | Y12: =Inventory_List_Table3[[#This Row],[Per piece MXN$]]/Inventory_List_Table3[[#This Row],[KG]] -> 12.5
A13: 10 | C13: SERPENTINE RUSTIC ROCK FTN | D13: EM325065OHA | E13: 1 | F13: 230 | G13: 85 | H13: 40 | I13: 34 | J13: 2875 | K13: =Inventory_List_Table3[[#This Row],[Q]]*Inventory_List_Table3[[#This Row],[Per piece MXN$]] -> 2875 | L13: =Inventory_List_Table3[[#This Row],[KG]]*2.20462 -> 507.0626 | M13: =Inventory_List_Table3[[#This Row],[H CM]]/2.54 -> 33.464567 | N13: =Inventory_List_Table3[[#This Row],[W CM]]/2.54 -> 15.748031 | O13: =Inventory_List_Table3[[#This Row],[D CM ]]/2.54 -> 13.385827 | P13: =Inventory_List_Table3[[#This Row],[Per piece MXN$]]/$U$2 -> 159.72222 | Q13: =IF(MOD(P13,1)>0.4,ROUNDUP(P13,0),ROUNDDOWN(P13,0)) -> 160 | R13: =Inventory_List_Table3[[#This Row],[AQ ROUND]]*1.4 -> 224 | S13: =IF(MOD(R13,1)>0.4,ROUNDUP(R13,0),ROUNDDOWN(R13,0)) -> 224 | T13: =Inventory_List_Table3[[#This Row],[LND ROUND]]*12 -> 2688 | U13: =Inventory_List_Table3[[#This Row],[AQ]]*Inventory_List_Table3[[#This Row],[Q]] -> 159.72222 | V13: MLD | W13: OOH | X13: =Inventory_List_Table3[[#This Row],[H CM]]*Inventory_List_Table3[[#This Row],[W CM]]*Inventory_List_Table3[[#This Row],[D CM ]] -> 115600 | Y13: =Inventory_List_Table3[[#This Row],[Per piece MXN$]]/Inventory_List_Table3[[#This Row],[KG]] -> 12.5
A14: 11 | C14: PINK SERP RUSTIC ROCK FTN | D14: EM325066HHN | E14: 1 | F14: 417 | G14: 68 | H14: 99 | I14: 42 | J14: 5212.5 | K14: =Inventory_List_Table3[[#This Row],[Q]]*Inventory_List_Table3[[#This Row],[Per piece MXN$]] -> 5212.5 | L14: =Inventory_List_Table3[[#This Row],[KG]]*2.20462 -> 919.32654 | M14: =Inventory_List_Table3[[#This Row],[H CM]]/2.54 -> 26.771654 | N14: =Inventory_List_Table3[[#This Row],[W CM]]/2.54 -> 38.976378 | O14: =Inventory_List_Table3[[#This Row],[D CM ]]/2.54 -> 16.535433 | P14: =Inventory_List_Table3[[#This Row],[Per piece MXN$]]/$U$2 -> 289.58333 | Q14: =IF(MOD(P14,1)>0.4,ROUNDUP(P14,0),ROUNDDOWN(P14,0)) -> 290 | R14: =Inventory_List_Table3[[#This Row],[AQ ROUND]]*1.4 -> 406 | S14: =IF(MOD(R14,1)>0.4,ROUNDUP(R14,0),ROUNDDOWN(R14,0)) -> 406 | T14: =Inventory_List_Table3[[#This Row],[LND ROUND]]*12 -> 4872 | U14: =Inventory_List_Table3[[#This Row],[AQ]]*Inventory_List_Table3[[#This Row],[Q]] -> 289.58333 | V14: OND | W14: HDL | X14: =Inventory_List_Table3[[#This Row],[H CM]]*Inventory_List_Table3[[#This Row],[W CM]]*Inventory_List_Table3[[#This Row],[D CM ]] -> 282744 | Y14: =Inventory_List_Table3[[#This Row],[Per piece MXN$]]/Inventory_List_Table3[[#This Row],[KG]] -> 12.5
A15: 12 | C15: PINK SERP RUSTIC ROCK FTN | D15: EM325067AA | E15: 1 | F15: 82 | G15: 80 | H15: 31 | I15: 18 | J15: 1025 | K15: =Inventory_List_Table3[[#This Row],[Q]]*Inventory_List_Table3[[#This Row],[Per piece MXN$]] -> 1025 | L15: =Inventory_List_Table3[[#This Row],[KG]]*2.20462 -> 180.77884 | M15: =Inventory_List_Table3[[#This Row],[H CM]]/2.54 -> 31.496063 | N15: =Inventory_List_Table3[[#This Row],[W CM]]/2.54 -> 12.204724 | O15: =Inventory_List_Table3[[#This Row],[D CM ]]/2.54 -> 7.0866142 | P15: =Inventory_List_Table3[[#This Row],[Per piece MXN$]]/$U$2 -> 56.944444 | Q15: =IF(MOD(P15,1)>0.4,ROUNDUP(P15,0),ROUNDDOWN(P15,0)) -> 57 | R15: =Inventory_List_Table3[[#This Row],[AQ ROUND]]*1.4 -> 79.8 | S15: =IF(MOD(R15,1)>0.4,ROUNDUP(R15,0),ROUNDDOWN(R15,0)) -> 80 | T15: =Inventory_List_Table3[[#This Row],[LND ROUND]]*12 -> 960 | U15: =Inventory_List_Table3[[#This Row],[AQ]]*Inventory_List_Table3[[#This Row],[Q]] -> 56.944444 | V15: EF | W15: AD | X15: =Inventory_List_Table3[[#This Row],[H CM]]*Inventory_List_Table3[[#This Row],[W CM]]*Inventory_List_Table3[[#This Row],[D CM ]] -> 44640 | Y15: =Inventory_List_Table3[[#This Row],[Per piece MXN$]]/Inventory_List_Table3[[#This Row],[KG]] -> 12.5
A16: 13 | C16: PINK SERP RUSTIC ROCK FTN | D16: EM325068OFF | E16: 1 | F16: 257 | G16: 121 | H16: 60 | I16: 27 | J16: 3212.5 | K16: =Inventory_List_Table3[[#This Row],[Q]]*Inventory_List_Table3[[#This Row],[Per piece MXN$]] -> 3212.5 | L16: =Inventory_List_Table3[[#This Row],[KG]]*2.20462 -> 566.58734 | M16: =Inventory_List_Table3[[#This Row],[H CM]]/2.54 -> 47.637795 | N16: =Inventory_List_Table3[[#This Row],[W CM]]/2.54 -> 23.622047 | O16: =Inventory_List_Table3[[#This Row],[D CM ]]/2.54 -> 10.629921 | P16: =Inventory_List_Table3[[#This Row],[Per piece MXN$]]/$U$2 -> 178.47222 | Q16: =IF(MOD(P16,1)>0.4,ROUNDUP(P16,0),ROUNDDOWN(P16,0)) -> 179 | R16: =Inventory_List_Table3[[#This Row],[AQ ROUND]]*1.4 -> 250.6 | S16: =IF(MOD(R16,1)>0.4,ROUNDUP(R16,0),ROUNDDOWN(R16,0)) -> 251 | T16: =Inventory_List_Table3[[#This Row],[LND ROUND]]*12 -> 3012 | U16: =Inventory_List_Table3[[#This Row],[AQ]]*Inventory_List_Table3[[#This Row],[Q]] -> 178.47222 | V16: MFN | W16: OEM | X16: =Inventory_List_Table3[[#This Row],[H CM]]*Inventory_List_Table3[[#This Row],[W CM]]*Inventory_List_Table3[[#This Row],[D CM ]] -> 196020 | Y16: =Inventory_List_Table3[[#This Row],[Per piece MXN$]]/Inventory_List_Table3[[#This Row],[KG]] -> 12.5
... A20: 17 | C20: GREY RUSTIC ROCK FTN | D20: EM325074AA | E20: 1 | F20: 82 | G20: 70 | H20: 34 | I20: 18 | J20: 1025 | K20: =Inventory_List_Table3[[#This Row],[Q]]*Inventory_List_Table3[[#This Row],[Per piece MXN$]] -> 1025 | L20: =Inventory_List_Table3[[#This Row],[KG]]*2.20462 -> 180.77884 | M20: =Inventory_List_Table3[[#This Row],[H CM]]/2.54 -> 27.559055 | N20: =Inventory_List_Table3[[#This Row],[W CM]]/2.54 -> 13.385827 | O20: =Inventory_List_Table3[[#This Row],[D CM ]]/2.54 -> 7.0866142 | P20: =Inventory_List_Table3[[#This Row],[Per piece MXN$]]/$U$2 -> 56.944444 | Q20: =IF(MOD(P20,1)>0.4,ROUNDUP(P20,0),ROUNDDOWN(P20,0)) -> 57 | R20: =Inventory_List_Table3[[#This Row],[AQ ROUND]]*1.4 -> 79.8 | S20: =IF(MOD(R20,1)>0.4,ROUNDUP(R20,0),ROUNDDOWN(R20,0)) -> 80 | T20: =Inventory_List_Table3[[#This Row],[LND ROUND]]*12 -> 960 | U20: =Inventory_List_Table3[[#This Row],[AQ]]*Inventory_List_Table3[[#This Row],[Q]] -> 56.944444 | V20: EF | W20: AD | X20: =Inventory_List_Table3[[#This Row],[H CM]]*Inventory_List_Table3[[#This Row],[W CM]]*Inventory_List_Table3[[#This Row],[D CM ]] -> 42840 | Y20: =Inventory_List_Table3[[#This Row],[Per piece MXN$]]/Inventory_List_Table3[[#This Row],[KG]] -> 12.5
A21: 20 | C21: GRAY REC MIRROR | D21: EM82520XNL | E21: 1 | F21: 30 | G21: 150 | H21: 80 | I21: 10 | J21: 5100 | K21: =Inventory_List_Table3[[#This Row],[Q]]*Inventory_List_Table3[[#This Row],[Per piece MXN$]] -> 5100 | L21: =Inventory_List_Table3[[#This Row],[KG]]*2.20462 -> 66.1386 | M21: =Inventory_List_Table3[[#This Row],[H CM]]/2.54 -> 59.055118 | N21: =Inventory_List_Table3[[#This Row],[W CM]]/2.54 -> 31.496063 | O21: =Inventory_List_Table3[[#This Row],[D CM ]]/2.54 -> 3.9370079 | P21: =Inventory_List_Table3[[#This Row],[Per piece MXN$]]/$U$2 -> 283.33333 | Q21: =IF(MOD(P21,1)>0.4,ROUNDUP(P21,0),ROUNDDOWN(P21,0)) -> 283 | R21: =Inventory_List_Table3[[#This Row],[AQ ROUND]]*1.4 -> 396.2 | S21: =IF(MOD(R21,1)>0.4,ROUNDUP(R21,0),ROUNDDOWN(R21,0)) -> 396 | T21: =Inventory_List_Table3[[#This Row],[LND ROUND]]*12 -> 4752 | U21: =Inventory_List_Table3[[#This Row],[AQ]]*Inventory_List_Table3[[#This Row],[Q]] -> 283.33333 | V21: OAX | W21: XNL | X21: =Inventory_List_Table3[[#This Row],[H CM]]*Inventory_List_Table3[[#This Row],[W CM]]+Inventory_List_Table3[[#This Row],[H CM]]*Inventory_List_Table3[[#This Row],[D CM ]]*2+Inventory_List_Table3[[#This Row],[W CM]]*Inventory_List_Table3[[#This Row],[D CM ]]*2 -> 16600 | Y21: =Inventory_List_Table3[[#This Row],[Per piece MXN$]]/X21*10000 -> 3072.2892
A22: 21 | C22: GRAY REC MIRROR | D22: EM82521XNL | E22: 1 | F22: 30 | G22: 150 | H22: 80 | I22: 10 | J22: 5100 | K22: =Inventory_List_Table3[[#This Row],[Q]]*Inventory_List_Table3[[#This Row],[Per piece MXN$]] -> 5100 | L22: =Inventory_List_Table3[[#This Row],[KG]]*2.20462 -> 66.1386 | M22: =Inventory_List_Table3[[#This Row],[H CM]]/2.54 -> 59.055118 | N22: =Inventory_List_Table3[[#This Row],[W CM]]/2.54 -> 31.496063 | O22: =Inventory_List_Table3[[#This Row],[D CM ]]/2.54 -> 3.9370079 | P22: =Inventory_List_Table3[[#This Row],[Per piece MXN$]]/$U$2 -> 283.33333 | Q22: =IF(MOD(P22,1)>0.4,ROUNDUP(P22,0),ROUNDDOWN(P22,0)) -> 283 | R22: =Inventory_List_Table3[[#This Row],[AQ ROUND]]*1.4 -> 396.2 | S22: =IF(MOD(R22,1)>0.4,ROUNDUP(R22,0),ROUNDDOWN(R22,0)) -> 396 | T22: =Inventory_List_Table3[[#This Row],[LND ROUND]]*12 -> 4752 | U22: =Inventory_List_Table3[[#This Row],[AQ]]*Inventory_List_Table3[[#This Row],[Q]] -> 283.33333 | V22: OAX | W22: XNL | X22: =Inventory_List_Table3[[#This Row],[H CM]]*Inventory_List_Table3[[#This Row],[W CM]]+Inventory_List_Table3[[#This Row],[H CM]]*Inventory_List_Table3[[#This Row],[D CM ]]*2+Inventory_List_Table3[[#This Row],[W CM]]*Inventory_List_Table3[[#This Row],[D CM ]]*2 -> 16600 | Y22: =Inventory_List_Table3[[#This Row],[Per piece MXN$]]/X22*10000 -> 3072.2892
A23: 22 | C23: AMBER REC MIRROR | D23: EM82522XNL | E23: 1 | F23: 30 | G23: 150 | H23: 80 | I23: 10 | J23: 5100 | K23: =Inventory_List_Table3[[#This Row],[Q]]*Inventory_List_Table3[[#This Row],[Per piece MXN$]] -> 5100 | L23: =Inventory_List_Table3[[#This Row],[KG]]*2.20462 -> 66.1386 | M23: =Inventory_List_Table3[[#This Row],[H CM]]/2.54 -> 59.055118 | N23: =Inventory_List_Table3[[#This Row],[W CM]]/2.54 -> 31.496063 | O23: =Inventory_List_Table3[[#This Row],[D CM ]]/2.54 -> 3.9370079 | P23: =Inventory_List_Table3[[#This Row],[Per piece MXN$]]/$U$2 -> 283.33333 | Q23: =IF(MOD(P23,1)>0.4,ROUNDUP(P23,0),ROUNDDOWN(P23,0)) -> 283 | R23: =Inventory_List_Table3[[#This Row],[AQ ROUND]]*1.4 -> 396.2 | S23: =IF(MOD(R23,1)>0.4,ROUNDUP(R23,0),ROUNDDOWN(R23,0)) -> 396 | T23: =Inventory_List_Table3[[#This Row],[LND ROUND]]*12 -> 4752 | U23: =Inventory_List_Table3[[#This Row],[AQ]]*Inventory_List_Table3[[#This Row],[Q]] -> 283.33333 | V23: OAX | W23: XNL | X23: =Inventory_List_Table3[[#This Row],[H CM]]*Inventory_List_Table3[[#This Row],[W CM]]+Inventory_List_Table3[[#This Row],[H CM]]*Inventory_List_Table3[[#This Row],[D CM ]]*2+Inventory_List_Table3[[#This Row],[W CM]]*Inventory_List_Table3[[#This Row],[D CM ]]*2 -> 16600 | Y23: =Inventory_List_Table3[[#This Row],[Per piece MXN$]]/X23*10000 -> 3072.2892
A24: 23 | C24: AMBER REC MIRROR | D24: EM82523XNL | E24: 1 | F24: 30 | G24: 150 | H24: 80 | I24: 10 | J24: 5100 | K24: =Inventory_List_Table3[[#This Row],[Q]]*Inventory_List_Table3[[#This Row],[Per piece MXN$]] -> 5100 | L24: =Inventory_List_Table3[[#This Row],[KG]]*2.20462 -> 66.1386 | M24: =Inventory_List_Table3[[#This Row],[H CM]]/2.54 -> 59.055118 | N24: =Inventory_List_Table3[[#This Row],[W CM]]/2.54 -> 31.496063 | O24: =Inventory_List_Table3[[#This Row],[D CM ]]/2.54 -> 3.9370079 | P24: =Inventory_List_Table3[[#This Row],[Per piece MXN$]]/$U$2 -> 283.33333 | Q24: =IF(MOD(P24,1)>0.4,ROUNDUP(P24,0),ROUNDDOWN(P24,0)) -> 283 | R24: =Inventory_List_Table3[[#This Row],[AQ ROUND]]*1.4 -> 396.2 | S24: =IF(MOD(R24,1)>0.4,ROUNDUP(R24,0),ROUNDDOWN(R24,0)) -> 396 | T24: =Inventory_List_Table3[[#This Row],[LND ROUND]]*12 -> 4752 | U24: =Inventory_List_Table3[[#This Row],[AQ]]*Inventory_List_Table3[[#This Row],[Q]] -> 283.33333 | V24: OAX | W24: XNL | X24: =Inventory_List_Table3[[#This Row],[H CM]]*Inventory_List_Table3[[#This Row],[W CM]]+Inventory_List_Table3[[#This Row],[H CM]]*Inventory_List_Table3[[#This Row],[D CM ]]*2+Inventory_List_Table3[[#This Row],[W CM]]*Inventory_List_Table3[[#This Row],[D CM ]]*2 -> 16600 | Y24: =Inventory_List_Table3[[#This Row],[Per piece MXN$]]/X24*10000 -> 3072.2892
A25: 24 | C25: CRYSTALLINE REC MIRROR | D25: EM82524XNL | E25: 1 | F25: 30 | G25: 150 | H25: 80 | I25: 10 | J25: 5100 | K25: =Inventory_List_Table3[[#This Row],[Q]]*Inventory_List_Table3[[#This Row],[Per piece MXN$]] -> 5100 | L25: =Inventory_List_Table3[[#This Row],[KG]]*2.20462 -> 66.1386 | M25: =Inventory_List_Table3[[#This Row],[H CM]]/2.54 -> 59.055118 | N25: =Inventory_List_Table3[[#This Row],[W CM]]/2.54 -> 31.496063 | O25: =Inventory_List_Table3[[#This Row],[D CM ]]/2.54 -> 3.9370079 | P25: =Inventory_List_Table3[[#This Row],[Per piece MXN$]]/$U$2 -> 283.33333 | Q25: =IF(MOD(P25,1)>0.4,ROUNDUP(P25,0),ROUNDDOWN(P25,0)) -> 283 | R25: =Inventory_List_Table3[[#This Row],[AQ ROUND]]*1.4 -> 396.2 | S25: =IF(MOD(R25,1)>0.4,ROUNDUP(R25,0),ROUNDDOWN(R25,0)) -> 396 | T25: =Inventory_List_Table3[[#This Row],[LND ROUND]]*12 -> 4752 | U25: =Inventory_List_Table3[[#This Row],[AQ]]*Inventory_List_Table3[[#This Row],[Q]] -> 283.33333 | V25: OAX | W25: XNL | X25: =Inventory_List_Table3[[#This Row],[H CM]]*Inventory_List_Table3[[#This Row],[W CM]]+Inventory_List_Table3[[#This Row],[H CM]]*Inventory_List_Table3[[#This Row],[D CM ]]*2+Inventory_List_Table3[[#This Row],[W CM]]*Inventory_List_Table3[[#This Row],[D CM ]]*2 -> 16600 | Y25: =Inventory_List_Table3[[#This Row],[Per piece MXN$]]/X25*10000 -> 3072.2892
A26: 25 | C26: CRYS REC MIRROR | D26: EM82525XNL | E26: 1 | F26: 30 | G26: 150 | H26: 80 | I26: 10 | J26: 5100 | K26: =Inventory_List_Table3[[#This Row],[Q]]*Inventory_List_Table3[[#This Row],[Per piece MXN$]] -> 5100 | L26: =Inventory_List_Table3[[#This Row],[KG]]*2.20462 -> 66.1386 | M26: =Inventory_List_Table3[[#This Row],[H CM]]/2.54 -> 59.055118 | N26: =Inventory_List_Table3[[#This Row],[W CM]]/2.54 -> 31.496063 | O26: =Inventory_List_Table3[[#This Row],[D CM ]]/2.54 -> 3.9370079 | P26: =Inventory_List_Table3[[#This Row],[Per piece MXN$]]/$U$2 -> 283.33333 | Q26: =IF(MOD(P26,1)>0.4,ROUNDUP(P26,0),ROUNDDOWN(P26,0)) -> 283 | R26: =Inventory_List_Table3[[#This Row],[AQ ROUND]]*1.4 -> 396.2 | S26: =IF(MOD(R26,1)>0.4,ROUNDUP(R26,0),ROUNDDOWN(R26,0)) -> 396 | T26: =Inventory_List_Table3[[#This Row],[LND ROUND]]*12 -> 4752 | U26: =Inventory_List_Table3[[#This Row],[AQ]]*Inventory_List_Table3[[#This Row],[Q]] -> 283.33333 | V26: OAX | W26: XNL | X26: =Inventory_List_Table3[[#This Row],[H CM]]*Inventory_List_Table3[[#This Row],[W CM]]+Inventory_List_Table3[[#This Row],[H CM]]*Inventory_List_Table3[[#This Row],[D CM ]]*2+Inventory_List_Table3[[#This Row],[W CM]]*Inventory_List_Table3[[#This Row],[D CM ]]*2 -> 16600 | Y26: =Inventory_List_Table3[[#This Row],[Per piece MXN$]]/X26*10000 -> 3072.2892
A27: 26 | C27: CRYS REC MIRROR | D27: EM82526XNL | E27: 1 | F27: 30 | G27: 150 | H27: 80 | I27: 10 | J27: 5100 | K27: =Inventory_List_Table3[[#This Row],[Q]]*Inventory_List_Table3[[#This Row],[Per piece MXN$]] -> 5100 | L27: =Inventory_List_Table3[[#This Row],[KG]]*2.20462 -> 66.1386 | M27: =Inventory_List_Table3[[#This Row],[H CM]]/2.54 -> 59.055118 | N27: =Inventory_List_Table3[[#This Row],[W CM]]/2.54 -> 31.496063 | O27: =Inventory_List_Table3[[#This Row],[D CM ]]/2.54 -> 3.9370079 | P27: =Inventory_List_Table3[[#This Row],[Per piece MXN$]]/$U$2 -> 283.33333 | Q27: =IF(MOD(P27,1)>0.4,ROUNDUP(P27,0),ROUNDDOWN(P27,0)) -> 283 | R27: =Inventory_List_Table3[[#This Row],[AQ ROUND]]*1.4 -> 396.2 | S27: =IF(MOD(R27,1)>0.4,ROUNDUP(R27,0),ROUNDDOWN(R27,0)) -> 396 | T27: =Inventory_List_Table3[[#This Row],[LND ROUND]]*12 -> 4752 | U27: =Inventory_List_Table3[[#This Row],[AQ]]*Inventory_List_Table3[[#This Row],[Q]] -> 283.33333 | V27: OAX | W27: XNL | X27: =Inventory_List_Table3[[#This Row],[H CM]]*Inventory_List_Table3[[#This Row],[W CM]]+Inventory_List_Table3[[#This Row],[H CM]]*Inventory_List_Table3[[#This Row],[D CM ]]*2+Inventory_List_Table3[[#This Row],[W CM]]*Inventory_List_Table3[[#This Row],[D CM ]]*2 -> 16600 | Y27: =Inventory_List_Table3[[#This Row],[Per piece MXN$]]/X27*10000 -> 3072.2892
A28: 27 | C28: CRYS REC MIRROR | D28: EM82527XNL | E28: 1 | F28: 30 | G28: 150 | H28: 80 | I28: 10 | J28: 5100 | K28: =Inventory_List_Table3[[#This Row],[Q]]*Inventory_List_Table3[[#This Row],[Per piece MXN$]] -> 5100 | L28: =Inventory_List_Table3[[#This Row],[KG]]*2.20462 -> 66.1386 | M28: =Inventory_List_Table3[[#This Row],[H CM]]/2.54 -> 59.055118 | N28: =Inventory_List_Table3[[#This Row],[W CM]]/2.54 -> 31.496063 | O28: =Inventory_List_Table3[[#This Row],[D CM ]]/2.54 -> 3.9370079 | P28: =Inventory_List_Table3[[#This Row],[Per piece MXN$]]/$U$2 -> 283.33333 | Q28: =IF(MOD(P28,1)>0.4,ROUNDUP(P28,0),ROUNDDOWN(P28,0)) -> 283 | R28: =Inventory_List_Table3[[#This Row],[AQ ROUND]]*1.4 -> 396.2 | S28: =IF(MOD(R28,1)>0.4,ROUNDUP(R28,0),ROUNDDOWN(R28,0)) -> 396 | T28: =Inventory_List_Table3[[#This Row],[LND ROUND]]*12 -> 4752 | U28: =Inventory_List_Table3[[#This Row],[AQ]]*Inventory_List_Table3[[#This Row],[Q]] -> 283.33333 | V28: OAX | W28: XNL | X28: =Inventory_List_Table3[[#This Row],[H CM]]*Inventory_List_Table3[[#This Row],[W CM]]+Inventory_List_Table3[[#This Row],[H CM]]*Inventory_List_Table3[[#This Row],[D CM ]]*2+Inventory_List_Table3[[#This Row],[W CM]]*Inventory_List_Table3[[#This Row],[D CM ]]*2 -> 16600 | Y28: =Inventory_List_Table3[[#This Row],[Per piece MXN$]]/X28*10000 -> 3072.2892
A29: 28 | C29: CRYS REC MIRROR | D29: EM82528XNL | E29: 1 | F29: 30 | G29: 150 | H29: 80 | I29: 10 | J29: 5100 | K29: =Inventory_List_Table3[[#This Row],[Q]]*Inventory_List_Table3[[#This Row],[Per piece MXN$]] -> 5100 | L29: =Inventory_List_Table3[[#This Row],[KG]]*2.20462 -> 66.1386 | M29: =Inventory_List_Table3[[#This Row],[H CM]]/2.54 -> 59.055118 | N29: =Inventory_List_Table3[[#This Row],[W CM]]/2.54 -> 31.496063 | O29: =Inventory_List_Table3[[#This Row],[D CM ]]/2.54 -> 3.9370079 | P29: =Inventory_List_Table3[[#This Row],[Per piece MXN$]]/$U$2 -> 283.33333 | Q29: =IF(MOD(P29,1)>0.4,ROUNDUP(P29,0),ROUNDDOWN(P29,0)) -> 283 | R29: =Inventory_List_Table3[[#This Row],[AQ ROUND]]*1.4 -> 396.2 | S29: =IF(MOD(R29,1)>0.4,ROUNDUP(R29,0),ROUNDDOWN(R29,0)) -> 396 | T29: =Inventory_List_Table3[[#This Row],[LND ROUND]]*12 -> 4752 | U29: =Inventory_List_Table3[[#This Row],[AQ]]*Inventory_List_Table3[[#This Row],[Q]] -> 283.33333 | V29: OAX | W29: XNL | X29: =Inventory_List_Table3[[#This Row],[H CM]]*Inventory_List_Table3[[#This Row],[W CM]]+Inventory_List_Table3[[#This Row],[H CM]]*Inventory_List_Table3[[#This Row],[D CM ]]*2+Inventory_List_Table3[[#This Row],[W CM]]*Inventory_List_Table3[[#This Row],[D CM ]]*2 -> 16600 | Y29: =Inventory_List_Table3[[#This Row],[Per piece MXN$]]/X29*10000 -> 3072.2892
A30: 29 | C30: CRYS REC MIRROR | D30: EM82529XNL | E30: 1 | F30: 30 | G30: 150 | H30: 80 | I30: 10 | J30: 5100 | K30: =Inventory_List_Table3[[#This Row],[Q]]*Inventory_List_Table3[[#This Row],[Per piece MXN$]] -> 5100 | L30: =Inventory_List_Table3[[#This Row],[KG]]*2.20462 -> 66.1386 | M30: =Inventory_List_Table3[[#This Row],[H CM]]/2.54 -> 59.055118 | N30: =Inventory_List_Table3[[#This Row],[W CM]]/2.54 -> 31.496063 | O30: =Inventory_List_Table3[[#This Row],[D CM ]]/2.54 -> 3.9370079 | P30: =Inventory_List_Table3[[#This Row],[Per piece MXN$]]/$U$2 -> 283.33333 | Q30: =IF(MOD(P30,1)>0.4,ROUNDUP(P30,0),ROUNDDOWN(P30,0)) -> 283 | R30: =Inventory_List_Table3[[#This Row],[AQ ROUND]]*1.4 -> 396.2 | S30: =IF(MOD(R30,1)>0.4,ROUNDUP(R30,0),ROUNDDOWN(R30,0)) -> 396 | T30: =Inventory_List_Table3[[#This Row],[LND ROUND]]*12 -> 4752 | U30: =Inventory_List_Table3[[#This Row],[AQ]]*Inventory_List_Table3[[#This Row],[Q]] -> 283.33333 | V30: OAX | W30: XNL | X30: =Inventory_List_Table3[[#This Row],[H CM]]*Inventory_List_Table3[[#This Row],[W CM]]+Inventory_List_Table3[[#This Row],[H CM]]*Inventory_List_Table3[[#This Row],[D CM ]]*2+Inventory_List_Table3[[#This Row],[W CM]]*Inventory_List_Table3[[#This Row],[D CM ]]*2 -> 16600 | Y30: =Inventory_List_Table3[[#This Row],[Per piece MXN$]]/X30*10000 -> 3072.2892
A31: 30 | C31: CRYS REC MIRROR | D31: EM82530XNL | E31: 1 | F31: 30 | G31: 150 | H31: 80 | I31: 10 | J31: 5100 | K31: =Inventory_List_Table3[[#This Row],[Q]]*Inventory_List_Table3[[#This Row],[Per piece MXN$]] -> 5100 | L31: =Inventory_List_Table3[[#This Row],[KG]]*2.20462 -> 66.1386 | M31: =Inventory_List_Table3[[#This Row],[H CM]]/2.54 -> 59.055118 | N31: =Inventory_List_Table3[[#This Row],[W CM]]/2.54 -> 31.496063 | O31: =Inventory_List_Table3[[#This Row],[D CM ]]/2.54 -> 3.9370079 | P31: =Inventory_List_Table3[[#This Row],[Per piece MXN$]]/$U$2 -> 283.33333 | Q31: =IF(MOD(P31,1)>0.4,ROUNDUP(P31,0),ROUNDDOWN(P31,0)) -> 283 | R31: =Inventory_List_Table3[[#This Row],[AQ ROUND]]*1.4 -> 396.2 | S31: =IF(MOD(R31,1)>0.4,ROUNDUP(R31,0),ROUNDDOWN(R31,0)) -> 396 | T31: =Inventory_List_Table3[[#This Row],[LND ROUND]]*12 -> 4752 | U31: =Inventory_List_Table3[[#This Row],[AQ]]*Inventory_List_Table3[[#This Row],[Q]] -> 283.33333 | V31: OAX | W31: XNL | X31: =Inventory_List_Table3[[#This Row],[H CM]]*Inventory_List_Table3[[#This Row],[W CM]]+Inventory_List_Table3[[#This Row],[H CM]]*Inventory_List_Table3[[#This Row],[D CM ]]*2+Inventory_List_Table3[[#This Row],[W CM]]*Inventory_List_Table3[[#This Row],[D CM ]]*2 -> 16600 | Y31: =Inventory_List_Table3[[#This Row],[Per piece MXN$]]/X31*10000 -> 3072.2892
A32: 31 | C32: CRYS REC MIRROR | D32: EM82531XNL | E32: 1 | F32: 30 | G32: 150 | H32: 80 | I32: 10 | J32: 5100 | K32: =Inventory_List_Table3[[#This Row],[Q]]*Inventory_List_Table3[[#This Row],[Per piece MXN$]] -> 5100 | L32: =Inventory_List_Table3[[#This Row],[KG]]*2.20462 -> 66.1386 | M32: =Inventory_List_Table3[[#This Row],[H CM]]/2.54 -> 59.055118 | N32: =Inventory_List_Table3[[#This Row],[W CM]]/2.54 -> 31.496063 | O32: =Inventory_List_Table3[[#This Row],[D CM ]]/2.54 -> 3.9370079 | P32: =Inventory_List_Table3[[#This Row],[Per piece MXN$]]/$U$2 -> 283.33333 | Q32: =IF(MOD(P32,1)>0.4,ROUNDUP(P32,0),ROUNDDOWN(P32,0)) -> 283 | R32: =Inventory_List_Table3[[#This Row],[AQ ROUND]]*1.4 -> 396.2 | S32: =IF(MOD(R32,1)>0.4,ROUNDUP(R32,0),ROUNDDOWN(R32,0)) -> 396 | T32: =Inventory_List_Table3[[#This Row],[LND ROUND]]*12 -> 4752 | U32: =Inventory_List_Table3[[#This Row],[AQ]]*Inventory_List_Table3[[#This Row],[Q]] -> 283.33333 | V32: OAX | W32: XNL | X32: =Inventory_List_Table3[[#This Row],[H CM]]*Inventory_List_Table3[[#This Row],[W CM]]+Inventory_List_Table3[[#This Row],[H CM]]*Inventory_List_Table3[[#This Row],[D CM ]]*2+Inventory_List_Table3[[#This Row],[W CM]]*Inventory_List_Table3[[#This Row],[D CM ]]*2 -> 16600 | Y32: =Inventory_List_Table3[[#This Row],[Per piece MXN$]]/X32*10000 -> 3072.2892
... A43: 42 | C43: CRIS VEIN REC MIRROR | D43: EM82542OLE | E43: 1 | F43: 19 | G43: 110 | H43: 60 | I43: 10 | J43: 3400 | K43: =Inventory_List_Table3[[#This Row],[Q]]*Inventory_List_Table3[[#This Row],[Per piece MXN$]] -> 3400 | L43: =Inventory_List_Table3[[#This Row],[KG]]*2.20462 -> 41.88778 | M43: =Inventory_List_Table3[[#This Row],[H CM]]/2.54 -> 43.307087 | N43: =Inventory_List_Table3[[#This Row],[W CM]]/2.54 -> 23.622047 | O43: =Inventory_List_Table3[[#This Row],[D CM ]]/2.54 -> 3.9370079 | P43: =Inventory_List_Table3[[#This Row],[Per piece MXN$]]/$U$2 -> 188.88889 | Q43: =IF(MOD(P43,1)>0.4,ROUNDUP(P43,0),ROUNDDOWN(P43,0)) -> 189 | R43: =Inventory_List_Table3[[#This Row],[AQ ROUND]]*1.4 -> 264.6 | S43: =IF(MOD(R43,1)>0.4,ROUNDUP(R43,0),ROUNDDOWN(R43,0)) -> 265 | T43: =Inventory_List_Table3[[#This Row],[LND ROUND]]*12 -> 3180 | U43: =Inventory_List_Table3[[#This Row],[AQ]]*Inventory_List_Table3[[#This Row],[Q]] -> 188.88889 | V43: MAN | W43: OLE | X43: =Inventory_List_Table3[[#This Row],[H CM]]*Inventory_List_Table3[[#This Row],[W CM]]+Inventory_List_Table3[[#This Row],[H CM]]*Inventory_List_Table3[[#This Row],[D CM ]]*2+Inventory_List_Table3[[#This Row],[W CM]]*Inventory_List_Table3[[#This Row],[D CM ]]*2 -> 10000 | Y43: =Inventory_List_Table3[[#This Row],[Per piece MXN$]]/X43*10000 -> 3400
A44: 43 | C44: CRIS COL | D44: EM82543EN | E44: 25 | F44: 6.8 | G44: 45 | H44: 15 | I44: 15 | J44: 750 | K44: =Inventory_List_Table3[[#This Row],[Q]]*Inventory_List_Table3[[#This Row],[Per piece MXN$]] -> 18750 | L44: =Inventory_List_Table3[[#This Row],[KG]]*2.20462 -> 14.991416 | M44: =Inventory_List_Table3[[#This Row],[H CM]]/2.54 -> 17.716535 | N44: =Inventory_List_Table3[[#This Row],[W CM]]/2.54 -> 5.9055118 | O44: =Inventory_List_Table3[[#This Row],[D CM ]]/2.54 -> 5.9055118 | P44: =Inventory_List_Table3[[#This Row],[Per piece MXN$]]/$U$2 -> 41.666667 | Q44: =IF(MOD(P44,1)>0.4,ROUNDUP(P44,0),ROUNDDOWN(P44,0)) -> 42 | R44: =Inventory_List_Table3[[#This Row],[AQ ROUND]]*1.4 -> 58.8 | S44: =IF(MOD(R44,1)>0.4,ROUNDUP(R44,0),ROUNDDOWN(R44,0)) -> 59 | T44: =Inventory_List_Table3[[#This Row],[LND ROUND]]*12 -> 708 | U44: =Inventory_List_Table3[[#This Row],[AQ]]*Inventory_List_Table3[[#This Row],[Q]] -> 1041.6667 | V44: HO | W44: EN | X44: =Inventory_List_Table3[[#This Row],[H CM]]*Inventory_List_Table3[[#This Row],[W CM]]*4+Inventory_List_Table3[[#This Row],[D CM ]]*Inventory_List_Table3[[#This Row],[D CM ]] -> 2925 | Y44: =Inventory_List_Table3[[#This Row],[Per piece MXN$]]/X44*10000 -> 2564.1026
A45: 44 | C45: CRIS COL | D45: EM82544ED | E45: 9 | F45: 5.2 | G45: 40 | H45: 15 | I45: 15 | J45: 648 | K45: =Inventory_List_Table3[[#This Row],[Q]]*Inventory_List_Table3[[#This Row],[Per piece MXN$]] -> 5832 | L45: =Inventory_List_Table3[[#This Row],[KG]]*2.20462 -> 11.464024 | M45: =Inventory_List_Table3[[#This Row],[H CM]]/2.54 -> 15.748031 | N45: =Inventory_List_Table3[[#This Row],[W CM]]/2.54 -> 5.9055118 | O45: =Inventory_List_Table3[[#This Row],[D CM ]]/2.54 -> 5.9055118 | P45: =Inventory_List_Table3[[#This Row],[Per piece MXN$]]/$U$2 -> 36 | Q45: =IF(MOD(P45,1)>0.4,ROUNDUP(P45,0),ROUNDDOWN(P45,0)) -> 36 | R45: =Inventory_List_Table3[[#This Row],[AQ ROUND]]*1.4 -> 50.4 | S45: =IF(MOD(R45,1)>0.4,ROUNDUP(R45,0),ROUNDDOWN(R45,0)) -> 50 | T45: =Inventory_List_Table3[[#This Row],[LND ROUND]]*12 -> 600 | U45: =Inventory_List_Table3[[#This Row],[AQ]]*Inventory_List_Table3[[#This Row],[Q]] -> 324 | V45: XL | W45: ED | X45: =Inventory_List_Table3[[#This Row],[H CM]]*Inventory_List_Table3[[#This Row],[W CM]]*4+Inventory_List_Table3[[#This Row],[D CM ]]*Inventory_List_Table3[[#This Row],[D CM ]] -> 2625 | Y45: =Inventory_List_Table3[[#This Row],[Per piece MXN$]]/X45*10000 -> 2468.5714
A46: 45 | C46: CRIS COL | D46: EM82545HE | E46: 2 | F46: 5 | G46: 35 | H46: 15 | I46: 15 | J46: 567 | K46: =Inventory_List_Table3[[#This Row],[Q]]*Inventory_List_Table3[[#This Row],[Per piece MXN$]] -> 1134 | L46: =Inventory_List_Table3[[#This Row],[KG]]*2.20462 -> 11.0231 | M46: =Inventory_List_Table3[[#This Row],[H CM]]/2.54 -> 13.779528 | N46: =Inventory_List_Table3[[#This Row],[W CM]]/2.54 -> 5.9055118 | O46: =Inventory_List_Table3[[#This Row],[D CM ]]/2.54 -> 5.9055118 | P46: =Inventory_List_Table3[[#This Row],[Per piece MXN$]]/$U$2 -> 31.5 | Q46: =IF(MOD(P46,1)>0.4,ROUNDUP(P46,0),ROUNDDOWN(P46,0)) -> 32 | R46: =Inventory_List_Table3[[#This Row],[AQ ROUND]]*1.4 -> 44.8 | S46: =IF(MOD(R46,1)>0.4,ROUNDUP(R46,0),ROUNDDOWN(R46,0)) -> 45 | T46: =Inventory_List_Table3[[#This Row],[LND ROUND]]*12 -> 540 | U46: =Inventory_List_Table3[[#This Row],[AQ]]*Inventory_List_Table3[[#This Row],[Q]] -> 63 | V46: XO | W46: HE | X46: =Inventory_List_Table3[[#This Row],[H CM]]*Inventory_List_Table3[[#This Row],[W CM]]*4+Inventory_List_Table3[[#This Row],[D CM ]]*Inventory_List_Table3[[#This Row],[D CM ]] -> 2325 | Y46: =Inventory_List_Table3[[#This Row],[Per piece MXN$]]/X46*10000 -> 2438.7097
A47: 46 | C47: CRIS VEIN POL | D47: EM82546XE | E47: 16 | F47: 3.2 | G47: 35 | H47: 12 | I47: 12 | J47: 440 | K47: =Inventory_List_Table3[[#This Row],[Q]]*Inventory_List_Table3[[#This Row],[Per piece MXN$]] -> 7040 | L47: =Inventory_List_Table3[[#This Row],[KG]]*2.20462 -> 7.054784 | M47: =Inventory_List_Table3[[#This Row],[H CM]]/2.54 -> 13.779528 | N47: =Inventory_List_Table3[[#This Row],[W CM]]/2.54 -> 4.7244094 | O47: =Inventory_List_Table3[[#This Row],[D CM ]]/2.54 -> 4.7244094 | P47: =Inventory_List_Table3[[#This Row],[Per piece MXN$]]/$U$2 -> 24.444444 | Q47: =IF(MOD(P47,1)>0.4,ROUNDUP(P47,0),ROUNDDOWN(P47,0)) -> 25 | R47: =Inventory_List_Table3[[#This Row],[AQ ROUND]]*1.4 -> 35 | S47: =IF(MOD(R47,1)>0.4,ROUNDUP(R47,0),ROUNDDOWN(R47,0)) -> 35 | T47: =Inventory_List_Table3[[#This Row],[LND ROUND]]*12 -> 420 | U47: =Inventory_List_Table3[[#This Row],[AQ]]*Inventory_List_Table3[[#This Row],[Q]] -> 391.11111 | V47: OE | W47: XE | X47: =Inventory_List_Table3[[#This Row],[H CM]]*Inventory_List_Table3[[#This Row],[W CM]]*4+Inventory_List_Table3[[#This Row],[D CM ]]*Inventory_List_Table3[[#This Row],[D CM ]] -> 1824 | Y47: =Inventory_List_Table3[[#This Row],[Per piece MXN$]]/X47*10000 -> 2412.2807
A48: 47 | C48: CRIS VEIN POL | D48: EM82547ON | E48: 21 | F48: 2.8 | G48: 30 | H48: 12 | I48: 12 | J48: 380 | K48: =Inventory_List_Table3[[#This Row],[Q]]*Inventory_List_Table3[[#This Row],[Per piece MXN$]] -> 7980 | L48: =Inventory_List_Table3[[#This Row],[KG]]*2.20462 -> 6.172936 | M48: =Inventory_List_Table3[[#This Row],[H CM]]/2.54 -> 11.811024 | N48: =Inventory_List_Table3[[#This Row],[W CM]]/2.54 -> 4.7244094 | O48: =Inventory_List_Table3[[#This Row],[D CM ]]/2.54 -> 4.7244094 | P48: =Inventory_List_Table3[[#This Row],[Per piece MXN$]]/$U$2 -> 21.111111 | Q48: =IF(MOD(P48,1)>0.4,ROUNDUP(P48,0),ROUNDDOWN(P48,0)) -> 21 | R48: =Inventory_List_Table3[[#This Row],[AQ ROUND]]*1.4 -> 29.4 | S48: =IF(MOD(R48,1)>0.4,ROUNDUP(R48,0),ROUNDDOWN(R48,0)) -> 29 | T48: =Inventory_List_Table3[[#This Row],[LND ROUND]]*12 -> 348 | U48: =Inventory_List_Table3[[#This Row],[AQ]]*Inventory_List_Table3[[#This Row],[Q]] -> 443.33333 | V48: OM | W48: ON | X48: =Inventory_List_Table3[[#This Row],[H CM]]*Inventory_List_Table3[[#This Row],[W CM]]*4+Inventory_List_Table3[[#This Row],[D CM ]]*Inventory_List_Table3[[#This Row],[D CM ]] -> 1584 | Y48: =Inventory_List_Table3[[#This Row],[Per piece MXN$]]/X48*10000 -> 2398.9899
A49: 48 | C49: CRIS POL | D49: EM82548XN | E49: 19 | F49: 4 | G49: 40 | H49: 12 | I49: 12 | J49: 500 | K49: =Inventory_List_Table3[[#This Row],[Q]]*Inventory_List_Table3[[#This Row],[Per piece MXN$]] -> 9500 | L49: =Inventory_List_Table3[[#This Row],[KG]]*2.20462 -> 8.81848 | M49: =Inventory_List_Table3[[#This Row],[H CM]]/2.54 -> 15.748031 | N49: =Inventory_List_Table3[[#This Row],[W CM]]/2.54 -> 4.7244094 | O49: =Inventory_List_Table3[[#This Row],[D CM ]]/2.54 -> 4.7244094 | P49: =Inventory_List_Table3[[#This Row],[Per piece MXN$]]/$U$2 -> 27.777778 | Q49: =IF(MOD(P49,1)>0.4,ROUNDUP(P49,0),ROUNDDOWN(P49,0)) -> 28 | R49: =Inventory_List_Table3[[#This Row],[AQ ROUND]]*1.4 -> 39.2 | S49: =IF(MOD(R49,1)>0.4,ROUNDUP(R49,0),ROUNDDOWN(R49,0)) -> 39 | T49: =Inventory_List_Table3[[#This Row],[LND ROUND]]*12 -> 468 | U49: =Inventory_List_Table3[[#This Row],[AQ]]*Inventory_List_Table3[[#This Row],[Q]] -> 527.77778 | V49: OA | W49: XN | X49: =Inventory_List_Table3[[#This Row],[H CM]]*Inventory_List_Table3[[#This Row],[W CM]]*4+Inventory_List_Table3[[#This Row],[D CM ]]*Inventory_List_Table3[[#This Row],[D CM ]] -> 2064 | Y49: =Inventory_List_Table3[[#This Row],[Per piece MXN$]]/X49*10000 -> 2422.4806
A50: 49 | C50: CRIS VEIN POL | D50: EM82549XH | E50: 7 | F50: 3.4 | G50: 40 | H50: 10 | I50: 10 | J50: 430 | K50: =Inventory_List_Table3[[#This Row],[Q]]*Inventory_List_Table3[[#This Row],[Per piece MXN$]] -> 3010 | L50: =Inventory_List_Table3[[#This Row],[KG]]*2.20462 -> 7.495708 | M50: =Inventory_List_Table3[[#This Row],[H CM]]/2.54 -> 15.748031 | N50: =Inventory_List_Table3[[#This Row],[W CM]]/2.54 -> 3.9370079 | O50: =Inventory_List_Table3[[#This Row],[D CM ]]/2.54 -> 3.9370079 | P50: =Inventory_List_Table3[[#This Row],[Per piece MXN$]]/$U$2 -> 23.888889 | Q50: =IF(MOD(P50,1)>0.4,ROUNDUP(P50,0),ROUNDDOWN(P50,0)) -> 24 | R50: =Inventory_List_Table3[[#This Row],[AQ ROUND]]*1.4 -> 33.6 | S50: =IF(MOD(R50,1)>0.4,ROUNDUP(R50,0),ROUNDDOWN(R50,0)) -> 34 | T50: =Inventory_List_Table3[[#This Row],[LND ROUND]]*12 -> 408 | U50: =Inventory_List_Table3[[#This Row],[AQ]]*Inventory_List_Table3[[#This Row],[Q]] -> 167.22222 | V50: OH | W50: XH | X50: =Inventory_List_Table3[[#This Row],[H CM]]*Inventory_List_Table3[[#This Row],[W CM]]*4+Inventory_List_Table3[[#This Row],[D CM ]]*Inventory_List_Table3[[#This Row],[D CM ]] -> 1700 | Y50: =Inventory_List_Table3[[#This Row],[Per piece MXN$]]/X50*10000 -> 2529.4118
A51: 50 | C51: CRIS AMBER POL | D51: EM82550XH | E51: 11 | F51: 3.4 | G51: 40 | H51: 10 | I51: 10 | J51: 430 | K51: =Inventory_List_Table3[[#This Row],[Q]]*Inventory_List_Table3[[#This Row],[Per piece MXN$]] -> 4730 | L51: =Inventory_List_Table3[[#This Row],[KG]]*2.20462 -> 7.495708 | M51: =Inventory_List_Table3[[#This Row],[H CM]]/2.54 -> 15.748031 | N51: =Inventory_List_Table3[[#This Row],[W CM]]/2.54 -> 3.9370079 | O51: =Inventory_List_Table3[[#This Row],[D CM ]]/2.54 -> 3.9370079 | P51: =Inventory_List_Table3[[#This Row],[Per piece MXN$]]/$U$2 -> 23.888889 | Q51: =IF(MOD(P51,1)>0.4,ROUNDUP(P51,0),ROUNDDOWN(P51,0)) -> 24 | R51: =Inventory_List_Table3[[#This Row],[AQ ROUND]]*1.4 -> 33.6 | S51: =IF(MOD(R51,1)>0.4,ROUNDUP(R51,0),ROUNDDOWN(R51,0)) -> 34 | T51: =Inventory_List_Table3[[#This Row],[LND ROUND]]*12 -> 408 | U51: =Inventory_List_Table3[[#This Row],[AQ]]*Inventory_List_Table3[[#This Row],[Q]] -> 262.77778 | V51: OH | W51: XH | X51: =Inventory_List_Table3[[#This Row],[H CM]]*Inventory_List_Table3[[#This Row],[W CM]]*4+Inventory_List_Table3[[#This Row],[D CM ]]*Inventory_List_Table3[[#This Row],[D CM ]] -> 1700 | Y51: =Inventory_List_Table3[[#This Row],[Per piece MXN$]]/X51*10000 -> 2529.4118
A52: 51 | C52: CRIS AMBER /GREY POL | D52: EM82551XH | E52: 4 | F52: 3.4 | G52: 40 | H52: 10 | I52: 10 | J52: 430 | K52: =Inventory_List_Table3[[#This Row],[Q]]*Inventory_List_Table3[[#This Row],[Per piece MXN$]] -> 1720 | L52: =Inventory_List_Table3[[#This Row],[KG]]*2.20462 -> 7.495708 | M52: =Inventory_List_Table3[[#This Row],[H CM]]/2.54 -> 15.748031 | N52: =Inventory_List_Table3[[#This Row],[W CM]]/2.54 -> 3.9370079 | O52: =Inventory_List_Table3[[#This Row],[D CM ]]/2.54 -> 3.9370079 | P52: =Inventory_List_Table3[[#This Row],[Per piece MXN$]]/$U$2 -> 23.888889 | Q52: =IF(MOD(P52,1)>0.4,ROUNDUP(P52,0),ROUNDDOWN(P52,0)) -> 24 | R52: =Inventory_List_Table3[[#This Row],[AQ ROUND]]*1.4 -> 33.6 | S52: =IF(MOD(R52,1)>0.4,ROUNDUP(R52,0),ROUNDDOWN(R52,0)) -> 34 | T52: =Inventory_List_Table3[[#This Row],[LND ROUND]]*12 -> 408 | U52: =Inventory_List_Table3[[#This Row],[AQ]]*Inventory_List_Table3[[#This Row],[Q]] -> 95.555556 | V52: OH | W52: XH | X52: =Inventory_List_Table3[[#This Row],[H CM]]*Inventory_List_Table3[[#This Row],[W CM]]*4+Inventory_List_Table3[[#This Row],[D CM ]]*Inventory_List_Table3[[#This Row],[D CM ]] -> 1700 | Y52: =Inventory_List_Table3[[#This Row],[Per piece MXN$]]/X52*10000 -> 2529.4118
A53: 52 | C53: CRIS POL | D53: EM82552XH | E53: 11 | F53: 3.4 | G53: 40 | H53: 10 | I53: 10 | J53: 430 | K53: =Inventory_List_Table3[[#This Row],[Q]]*Inventory_List_Table3[[#This Row],[Per piece MXN$]] -> 4730 | L53: =Inventory_List_Table3[[#This Row],[KG]]*2.20462 -> 7.495708 | M53: =Inventory_List_Table3[[#This Row],[H CM]]/2.54 -> 15.748031 | N53: =Inventory_List_Table3[[#This Row],[W CM]]/2.54 -> 3.9370079 | O53: =Inventory_List_Table3[[#This Row],[D CM ]]/2.54 -> 3.9370079 | P53: =Inventory_List_Table3[[#This Row],[Per piece MXN$]]/$U$2 -> 23.888889 | Q53: =IF(MOD(P53,1)>0.4,ROUNDUP(P53,0),ROUNDDOWN(P53,0)) -> 24 | R53: =Inventory_List_Table3[[#This Row],[AQ ROUND]]*1.4 -> 33.6 | S53: =IF(MOD(R53,1)>0.4,ROUNDUP(R53,0),ROUNDDOWN(R53,0)) -> 34 | T53: =Inventory_List_Table3[[#This Row],[LND ROUND]]*12 -> 408 | U53: =Inventory_List_Table3[[#This Row],[AQ]]*Inventory_List_Table3[[#This Row],[Q]] -> 262.77778 | V53: OH | W53: XH | X53: =Inventory_List_Table3[[#This Row],[H CM]]*Inventory_List_Table3[[#This Row],[W CM]]*4+Inventory_List_Table3[[#This Row],[D CM ]]*Inventory_List_Table3[[#This Row],[D CM ]] -> 1700 | Y53: =Inventory_List_Table3[[#This Row],[Per piece MXN$]]/X53*10000 -> 2529.4118
A54: 53 | C54: CRIS VEINS POL | D54: EM82553ON | E54: 9 | F54: 3 | G54: 35 | H54: 10 | I54: 10 | J54: 380 | K54: =Inventory_List_Table3[[#This Row],[Q]]*Inventory_List_Table3[[#This Row],[Per piece MXN$]] -> 3420 | L54: =Inventory_List_Table3[[#This Row],[KG]]*2.20462 -> 6.61386 | M54: =Inventory_List_Table3[[#This Row],[H CM]]/2.54 -> 13.779528 | N54: =Inventory_List_Table3[[#This Row],[W CM]]/2.54 -> 3.9370079 | O54: =Inventory_List_Table3[[#This Row],[D CM ]]/2.54 -> 3.9370079 | P54: =Inventory_List_Table3[[#This Row],[Per piece MXN$]]/$U$2 -> 21.111111 | Q54: =IF(MOD(P54,1)>0.4,ROUNDUP(P54,0),ROUNDDOWN(P54,0)) -> 21 | R54: =Inventory_List_Table3[[#This Row],[AQ ROUND]]*1.4 -> 29.4 | S54: =IF(MOD(R54,1)>0.4,ROUNDUP(R54,0),ROUNDDOWN(R54,0)) -> 29 | T54: =Inventory_List_Table3[[#This Row],[LND ROUND]]*12 -> 348 | U54: =Inventory_List_Table3[[#This Row],[AQ]]*Inventory_List_Table3[[#This Row],[Q]] -> 190 | V54: OM | W54: ON | X54: =Inventory_List_Table3[[#This Row],[H CM]]*Inventory_List_Table3[[#This Row],[W CM]]*4+Inventory_List_Table3[[#This Row],[D CM ]]*Inventory_List_Table3[[#This Row],[D CM ]] -> 1500 | Y54: =Inventory_List_Table3[[#This Row],[Per piece MXN$]]/X54*10000 -> 2533.3333
A55: 54 | C55: CRIS POL | D55: EM82554ON | E55: 2 | F55: 3 | G55: 35 | H55: 10 | I55: 10 | J55: 380 | K55: =Inventory_List_Table3[[#This Row],[Q]]*Inventory_List_Table3[[#This Row],[Per piece MXN$]] -> 760 | L55: =Inventory_List_Table3[[#This Row],[KG]]*2.20462 -> 6.61386 | M55: =Inventory_List_Table3[[#This Row],[H CM]]/2.54 -> 13.779528 | N55: =Inventory_List_Table3[[#This Row],[W CM]]/2.54 -> 3.9370079 | O55: =Inventory_List_Table3[[#This Row],[D CM ]]/2.54 -> 3.9370079 | P55: =Inventory_List_Table3[[#This Row],[Per piece MXN$]]/$U$2 -> 21.111111 | Q55: =IF(MOD(P55,1)>0.4,ROUNDUP(P55,0),ROUNDDOWN(P55,0)) -> 21 | R55: =Inventory_List_Table3[[#This Row],[AQ ROUND]]*1.4 -> 29.4 | S55: =IF(MOD(R55,1)>0.4,ROUNDUP(R55,0),ROUNDDOWN(R55,0)) -> 29 | T55: =Inventory_List_Table3[[#This Row],[LND ROUND]]*12 -> 348 | U55: =Inventory_List_Table3[[#This Row],[AQ]]*Inventory_List_Table3[[#This Row],[Q]] -> 42.222222 | V55: OM | W55: ON | X55: =Inventory_List_Table3[[#This Row],[H CM]]*Inventory_List_Table3[[#This Row],[W CM]]*4+Inventory_List_Table3[[#This Row],[D CM ]]*Inventory_List_Table3[[#This Row],[D CM ]] -> 1500 | Y55: =Inventory_List_Table3[[#This Row],[Per piece MXN$]]/X55*10000 -> 2533.3333
... A60: 59 | C60: CRIS AMBER SOL | D60: EM82559XO | E60: 14 | F60: 5.2 | G60: 35 | H60: 15 | I60: 15 | J60: 420 | K60: =Inventory_List_Table3[[#This Row],[Q]]*Inventory_List_Table3[[#This Row],[Per piece MXN$]] -> 5880 | L60: =Inventory_List_Table3[[#This Row],[KG]]*2.20462 -> 11.464024 | M60: =Inventory_List_Table3[[#This Row],[H CM]]/2.54 -> 13.779528 | N60: =Inventory_List_Table3[[#This Row],[W CM]]/2.54 -> 5.9055118 | O60: =Inventory_List_Table3[[#This Row],[D CM ]]/2.54 -> 5.9055118 | P60: =Inventory_List_Table3[[#This Row],[Per piece MXN$]]/$U$2 -> 23.333333 | Q60: =IF(MOD(P60,1)>0.4,ROUNDUP(P60,0),ROUNDDOWN(P60,0)) -> 23 | R60: =Inventory_List_Table3[[#This Row],[AQ ROUND]]*1.4 -> 32.2 | S60: =IF(MOD(R60,1)>0.4,ROUNDUP(R60,0),ROUNDDOWN(R60,0)) -> 32 | T60: =Inventory_List_Table3[[#This Row],[LND ROUND]]*12 -> 384 | U60: =Inventory_List_Table3[[#This Row],[AQ]]*Inventory_List_Table3[[#This Row],[Q]] -> 326.66667 | V60: OX | W60: XO | X60: =Inventory_List_Table3[[#This Row],[H CM]]*Inventory_List_Table3[[#This Row],[W CM]]*4+Inventory_List_Table3[[#This Row],[D CM ]]*Inventory_List_Table3[[#This Row],[D CM ]] -> 2325 | Y60: =Inventory_List_Table3[[#This Row],[Per piece MXN$]]/X60*10000 -> 1806.4516
A61: 60 | C61: CRIS GREY REC MIRROR | D61: EM82560XNL | E61: 1 | F61: 30 | G61: 150 | H61: 80 | I61: 10 | J61: 5100 | K61: =Inventory_List_Table3[[#This Row],[Q]]*Inventory_List_Table3[[#This Row],[Per piece MXN$]] -> 5100 | L61: =Inventory_List_Table3[[#This Row],[KG]]*2.20462 -> 66.1386 | M61: =Inventory_List_Table3[[#This Row],[H CM]]/2.54 -> 59.055118 | N61: =Inventory_List_Table3[[#This Row],[W CM]]/2.54 -> 31.496063 | O61: =Inventory_List_Table3[[#This Row],[D CM ]]/2.54 -> 3.9370079 | P61: =Inventory_List_Table3[[#This Row],[Per piece MXN$]]/$U$2 -> 283.33333 | Q61: =IF(MOD(P61,1)>0.4,ROUNDUP(P61,0),ROUNDDOWN(P61,0)) -> 283 | R61: =Inventory_List_Table3[[#This Row],[AQ ROUND]]*1.4 -> 396.2 | S61: =IF(MOD(R61,1)>0.4,ROUNDUP(R61,0),ROUNDDOWN(R61,0)) -> 396 | T61: =Inventory_List_Table3[[#This Row],[LND ROUND]]*12 -> 4752 | U61: =Inventory_List_Table3[[#This Row],[AQ]]*Inventory_List_Table3[[#This Row],[Q]] -> 283.33333 | V61: OAX | W61: XNL | X61: =Inventory_List_Table3[[#This Row],[H CM]]*Inventory_List_Table3[[#This Row],[W CM]]+Inventory_List_Table3[[#This Row],[H CM]]*Inventory_List_Table3[[#This Row],[D CM ]]*2+Inventory_List_Table3[[#This Row],[W CM]]*Inventory_List_Table3[[#This Row],[D CM ]]*2 -> 16600 | Y61: =Inventory_List_Table3[[#This Row],[Per piece MXN$]]/X61*10000 -> 3072.2892
A62: 61 | C62: CRIS GREY REC MIRROR | D62: EM82561XNL | E62: 1 | F62: 30 | G62: 150 | H62: 80 | I62: 10 | J62: 5100 | K62: =Inventory_List_Table3[[#This Row],[Q]]*Inventory_List_Table3[[#This Row],[Per piece MXN$]] -> 5100 | L62: =Inventory_List_Table3[[#This Row],[KG]]*2.20462 -> 66.1386 | M62: =Inventory_List_Table3[[#This Row],[H CM]]/2.54 -> 59.055118 | N62: =Inventory_List_Table3[[#This Row],[W CM]]/2.54 -> 31.496063 | O62: =Inventory_List_Table3[[#This Row],[D CM ]]/2.54 -> 3.9370079 | P62: =Inventory_List_Table3[[#This Row],[Per piece MXN$]]/$U$2 -> 283.33333 | Q62: =IF(MOD(P62,1)>0.4,ROUNDUP(P62,0),ROUNDDOWN(P62,0)) -> 283 | R62: =Inventory_List_Table3[[#This Row],[AQ ROUND]]*1.4 -> 396.2 | S62: =IF(MOD(R62,1)>0.4,ROUNDUP(R62,0),ROUNDDOWN(R62,0)) -> 396 | T62: =Inventory_List_Table3[[#This Row],[LND ROUND]]*12 -> 4752 | U62: =Inventory_List_Table3[[#This Row],[AQ]]*Inventory_List_Table3[[#This Row],[Q]] -> 283.33333 | V62: OAX | W62: XNL | X62: =Inventory_List_Table3[[#This Row],[H CM]]*Inventory_List_Table3[[#This Row],[W CM]]+Inventory_List_Table3[[#This Row],[H CM]]*Inventory_List_Table3[[#This Row],[D CM ]]*2+Inventory_List_Table3[[#This Row],[W CM]]*Inventory_List_Table3[[#This Row],[D CM ]]*2 -> 16600 | Y62: =Inventory_List_Table3[[#This Row],[Per piece MXN$]]/X62*10000 -> 3072.2892
A63: 62 | C63: CRIS GREY SQ MIRROR | D63: EM82562XOL | E63: 1 | F63: 27 | G63: 100 | H63: 100 | I63: 10 | J63: 4200 | K63: =Inventory_List_Table3[[#This Row],[Q]]*Inventory_List_Table3[[#This Row],[Per piece MXN$]] -> 4200 | L63: =Inventory_List_Table3[[#This Row],[KG]]*2.20462 -> 59.52474 | M63: =Inventory_List_Table3[[#This Row],[H CM]]/2.54 -> 39.370079 | N63: =Inventory_List_Table3[[#This Row],[W CM]]/2.54 -> 39.370079 | O63: =Inventory_List_Table3[[#This Row],[D CM ]]/2.54 -> 3.9370079 | P63: =Inventory_List_Table3[[#This Row],[Per piece MXN$]]/$U$2 -> 233.33333 | Q63: =IF(MOD(P63,1)>0.4,ROUNDUP(P63,0),ROUNDDOWN(P63,0)) -> 233 | R63: =Inventory_List_Table3[[#This Row],[AQ ROUND]]*1.4 -> 326.2 | S63: =IF(MOD(R63,1)>0.4,ROUNDUP(R63,0),ROUNDDOWN(R63,0)) -> 326 | T63: =Inventory_List_Table3[[#This Row],[LND ROUND]]*12 -> 3912 | U63: =Inventory_List_Table3[[#This Row],[AQ]]*Inventory_List_Table3[[#This Row],[Q]] -> 233.33333 | V63: OXX | W63: XOL | X63: =Inventory_List_Table3[[#This Row],[H CM]]*Inventory_List_Table3[[#This Row],[W CM]]+Inventory_List_Table3[[#This Row],[H CM]]*Inventory_List_Table3[[#This Row],[D CM ]]*2+Inventory_List_Table3[[#This Row],[W CM]]*Inventory_List_Table3[[#This Row],[D CM ]]*2 -> 14000 | Y63: =Inventory_List_Table3[[#This Row],[Per piece MXN$]]/X63*10000 -> 3000
A64: 63 | C64: CRIS AMBER REC MIRROR | D64: EM82563OLE | E64: 1 | F64: 19 | G64: 110 | H64: 60 | I64: 10 | J64: 3400 | K64: =Inventory_List_Table3[[#This Row],[Q]]*Inventory_List_Table3[[#This Row],[Per piece MXN$]] -> 3400 | L64: =Inventory_List_Table3[[#This Row],[KG]]*2.20462 -> 41.88778 | M64: =Inventory_List_Table3[[#This Row],[H CM]]/2.54 -> 43.307087 | N64: =Inventory_List_Table3[[#This Row],[W CM]]/2.54 -> 23.622047 | O64: =Inventory_List_Table3[[#This Row],[D CM ]]/2.54 -> 3.9370079 | P64: =Inventory_List_Table3[[#This Row],[Per piece MXN$]]/$U$2 -> 188.88889 | Q64: =IF(MOD(P64,1)>0.4,ROUNDUP(P64,0),ROUNDDOWN(P64,0)) -> 189 | R64: =Inventory_List_Table3[[#This Row],[AQ ROUND]]*1.4 -> 264.6 | S64: =IF(MOD(R64,1)>0.4,ROUNDUP(R64,0),ROUNDDOWN(R64,0)) -> 265 | T64: =Inventory_List_Table3[[#This Row],[LND ROUND]]*12 -> 3180 | U64: =Inventory_List_Table3[[#This Row],[AQ]]*Inventory_List_Table3[[#This Row],[Q]] -> 188.88889 | V64: MAN | W64: OLE | X64: =Inventory_List_Table3[[#This Row],[H CM]]*Inventory_List_Table3[[#This Row],[W CM]]+Inventory_List_Table3[[#This Row],[H CM]]*Inventory_List_Table3[[#This Row],[D CM ]]*2+Inventory_List_Table3[[#This Row],[W CM]]*Inventory_List_Table3[[#This Row],[D CM ]]*2 -> 10000 | Y64: =Inventory_List_Table3[[#This Row],[Per piece MXN$]]/X64*10000 -> 3400
A65: 64 | C65: CRIS AMBER REC MIRROR | D65: EM82564OLE | E65: 1 | F65: 19 | G65: 110 | H65: 60 | I65: 10 | J65: 3400 | K65: =Inventory_List_Table3[[#This Row],[Q]]*Inventory_List_Table3[[#This Row],[Per piece MXN$]] -> 3400 | L65: =Inventory_List_Table3[[#This Row],[KG]]*2.20462 -> 41.88778 | M65: =Inventory_List_Table3[[#This Row],[H CM]]/2.54 -> 43.307087 | N65: =Inventory_List_Table3[[#This Row],[W CM]]/2.54 -> 23.622047 | O65: =Inventory_List_Table3[[#This Row],[D CM ]]/2.54 -> 3.9370079 | P65: =Inventory_List_Table3[[#This Row],[Per piece MXN$]]/$U$2 -> 188.88889 | Q65: =IF(MOD(P65,1)>0.4,ROUNDUP(P65,0),ROUNDDOWN(P65,0)) -> 189 | R65: =Inventory_List_Table3[[#This Row],[AQ ROUND]]*1.4 -> 264.6 | S65: =IF(MOD(R65,1)>0.4,ROUNDUP(R65,0),ROUNDDOWN(R65,0)) -> 265 | T65: =Inventory_List_Table3[[#This Row],[LND ROUND]]*12 -> 3180 | U65: =Inventory_List_Table3[[#This Row],[AQ]]*Inventory_List_Table3[[#This Row],[Q]] -> 188.88889 | V65: MAN | W65: OLE | X65: =Inventory_List_Table3[[#This Row],[H CM]]*Inventory_List_Table3[[#This Row],[W CM]]+Inventory_List_Table3[[#This Row],[H CM]]*Inventory_List_Table3[[#This Row],[D CM ]]*2+Inventory_List_Table3[[#This Row],[W CM]]*Inventory_List_Table3[[#This Row],[D CM ]]*2 -> 10000 | Y65: =Inventory_List_Table3[[#This Row],[Per piece MXN$]]/X65*10000 -> 3400
A66: 65 | C66: CRIS AMBER REC MIRROR | D66: EM82565OLE | E66: 1 | F66: 19 | G66: 110 | H66: 60 | I66: 10 | J66: 3400 | K66: =Inventory_List_Table3[[#This Row],[Q]]*Inventory_List_Table3[[#This Row],[Per piece MXN$]] -> 3400 | L66: =Inventory_List_Table3[[#This Row],[KG]]*2.20462 -> 41.88778 | M66: =Inventory_List_Table3[[#This Row],[H CM]]/2.54 -> 43.307087 | N66: =Inventory_List_Table3[[#This Row],[W CM]]/2.54 -> 23.622047 | O66: =Inventory_List_Table3[[#This Row],[D CM ]]/2.54 -> 3.9370079 | P66: =Inventory_List_Table3[[#This Row],[Per piece MXN$]]/$U$2 -> 188.88889 | Q66: =IF(MOD(P66,1)>0.4,ROUNDUP(P66,0),ROUNDDOWN(P66,0)) -> 189 | R66: =Inventory_List_Table3[[#This Row],[AQ ROUND]]*1.4 -> 264.6 | S66: =IF(MOD(R66,1)>0.4,ROUNDUP(R66,0),ROUNDDOWN(R66,0)) -> 265 | T66: =Inventory_List_Table3[[#This Row],[LND ROUND]]*12 -> 3180 | U66: =Inventory_List_Table3[[#This Row],[AQ]]*Inventory_List_Table3[[#This Row],[Q]] -> 188.88889 | V66: MAN | W66: OLE | X66: =Inventory_List_Table3[[#This Row],[H CM]]*Inventory_List_Table3[[#This Row],[W CM]]+Inventory_List_Table3[[#This Row],[H CM]]*Inventory_List_Table3[[#This Row],[D CM ]]*2+Inventory_List_Table3[[#This Row],[W CM]]*Inventory_List_Table3[[#This Row],[D CM ]]*2 -> 10000 | Y66: =Inventory_List_Table3[[#This Row],[Per piece MXN$]]/X66*10000 -> 3400
A67: 66 | C67: CRIS AMBER REC MIRROR | D67: EM82566OLE | E67: 1 | F67: 19 | G67: 110 | H67: 60 | I67: 10 | J67: 3400 | K67: =Inventory_List_Table3[[#This Row],[Q]]*Inventory_List_Table3[[#This Row],[Per piece MXN$]] -> 3400 | L67: =Inventory_List_Table3[[#This Row],[KG]]*2.20462 -> 41.88778 | M67: =Inventory_List_Table3[[#This Row],[H CM]]/2.54 -> 43.307087 | N67: =Inventory_List_Table3[[#This Row],[W CM]]/2.54 -> 23.622047 | O67: =Inventory_List_Table3[[#This Row],[D CM ]]/2.54 -> 3.9370079 | P67: =Inventory_List_Table3[[#This Row],[Per piece MXN$]]/$U$2 -> 188.88889 | Q67: =IF(MOD(P67,1)>0.4,ROUNDUP(P67,0),ROUNDDOWN(P67,0)) -> 189 | R67: =Inventory_List_Table3[[#This Row],[AQ ROUND]]*1.4 -> 264.6 | S67: =IF(MOD(R67,1)>0.4,ROUNDUP(R67,0),ROUNDDOWN(R67,0)) -> 265 | T67: =Inventory_List_Table3[[#This Row],[LND ROUND]]*12 -> 3180 | U67: =Inventory_List_Table3[[#This Row],[AQ]]*Inventory_List_Table3[[#This Row],[Q]] -> 188.88889 | V67: MAN | W67: OLE | X67: =Inventory_List_Table3[[#This Row],[H CM]]*Inventory_List_Table3[[#This Row],[W CM]]+Inventory_List_Table3[[#This Row],[H CM]]*Inventory_List_Table3[[#This Row],[D CM ]]*2+Inventory_List_Table3[[#This Row],[W CM]]*Inventory_List_Table3[[#This Row],[D CM ]]*2 -> 10000 | Y67: =Inventory_List_Table3[[#This Row],[Per piece MXN$]]/X67*10000 -> 3400
A68: 67 | C68: CRIS GREY REC MIRROR | D68: EM82567OLE | E68: 1 | F68: 19 | G68: 110 | H68: 60 | I68: 10 | J68: 3400 | K68: =Inventory_List_Table3[[#This Row],[Q]]*Inventory_List_Table3[[#This Row],[Per piece MXN$]] -> 3400 | L68: =Inventory_List_Table3[[#This Row],[KG]]*2.20462 -> 41.88778 | M68: =Inventory_List_Table3[[#This Row],[H CM]]/2.54 -> 43.307087 | N68: =Inventory_List_Table3[[#This Row],[W CM]]/2.54 -> 23.622047 | O68: =Inventory_List_Table3[[#This Row],[D CM ]]/2.54 -> 3.9370079 | P68: =Inventory_List_Table3[[#This Row],[Per piece MXN$]]/$U$2 -> 188.88889 | Q68: =IF(MOD(P68,1)>0.4,ROUNDUP(P68,0),ROUNDDOWN(P68,0)) -> 189 | R68: =Inventory_List_Table3[[#This Row],[AQ ROUND]]*1.4 -> 264.6 | S68: =IF(MOD(R68,1)>0.4,ROUNDUP(R68,0),ROUNDDOWN(R68,0)) -> 265 | T68: =Inventory_List_Table3[[#This Row],[LND ROUND]]*12 -> 3180 | U68: =Inventory_List_Table3[[#This Row],[AQ]]*Inventory_List_Table3[[#This Row],[Q]] -> 188.88889 | V68: MAN | W68: OLE | X68: =Inventory_List_Table3[[#This Row],[H CM]]*Inventory_List_Table3[[#This Row],[W CM]]+Inventory_List_Table3[[#This Row],[H CM]]*Inventory_List_Table3[[#This Row],[D CM ]]*2+Inventory_List_Table3[[#This Row],[W CM]]*Inventory_List_Table3[[#This Row],[D CM ]]*2 -> 10000 | Y68: =Inventory_List_Table3[[#This Row],[Per piece MXN$]]/X68*10000 -> 3400
A69: 68 | C69: CRIS GREY COL | D69: EM82568EN | E69: 13 | F69: 7 | G69: 45 | H69: 15 | I69: 15 | J69: 750 | K69: =Inventory_List_Table3[[#This Row],[Q]]*Inventory_List_Table3[[#This Row],[Per piece MXN$]] -> 9750 | L69: =Inventory_List_Table3[[#This Row],[KG]]*2.20462 -> 15.43234 | M69: =Inventory_List_Table3[[#This Row],[H CM]]/2.54 -> 17.716535 | N69: =Inventory_List_Table3[[#This Row],[W CM]]/2.54 -> 5.9055118 | O69: =Inventory_List_Table3[[#This Row],[D CM ]]/2.54 -> 5.9055118 | P69: =Inventory_List_Table3[[#This Row],[Per piece MXN$]]/$U$2 -> 41.666667 | Q69: =IF(MOD(P69,1)>0.4,ROUNDUP(P69,0),ROUNDDOWN(P69,0)) -> 42 | R69: =Inventory_List_Table3[[#This Row],[AQ ROUND]]*1.4 -> 58.8 | S69: =IF(MOD(R69,1)>0.4,ROUNDUP(R69,0),ROUNDDOWN(R69,0)) -> 59 | T69: =Inventory_List_Table3[[#This Row],[LND ROUND]]*12 -> 708 | U69: =Inventory_List_Table3[[#This Row],[AQ]]*Inventory_List_Table3[[#This Row],[Q]] -> 541.66667 | V69: HO | W69: EN | X69: =Inventory_List_Table3[[#This Row],[H CM]]*Inventory_List_Table3[[#This Row],[W CM]]*4+Inventory_List_Table3[[#This Row],[D CM ]]*Inventory_List_Table3[[#This Row],[D CM ]] -> 2925 | Y69: =Inventory_List_Table3[[#This Row],[Per piece MXN$]]/X69*10000 -> 2564.1026
A70: 69 | C70: CRIS GREY COL | D70: EM82569XN | E70: 4 | F70: 4 | G70: 40 | H70: 12 | I70: 12 | J70: 500 | K70: =Inventory_List_Table3[[#This Row],[Q]]*Inventory_List_Table3[[#This Row],[Per piece MXN$]] -> 2000 | L70: =Inventory_List_Table3[[#This Row],[KG]]*2.20462 -> 8.81848 | M70: =Inventory_List_Table3[[#This Row],[H CM]]/2.54 -> 15.748031 | N70: =Inventory_List_Table3[[#This Row],[W CM]]/2.54 -> 4.7244094 | O70: =Inventory_List_Table3[[#This Row],[D CM ]]/2.54 -> 4.7244094 | P70: =Inventory_List_Table3[[#This Row],[Per piece MXN$]]/$U$2 -> 27.777778 | Q70: =IF(MOD(P70,1)>0.4,ROUNDUP(P70,0),ROUNDDOWN(P70,0)) -> 28 | R70: =Inventory_List_Table3[[#This Row],[AQ ROUND]]*1.4 -> 39.2 | S70: =IF(MOD(R70,1)>0.4,ROUNDUP(R70,0),ROUNDDOWN(R70,0)) -> 39 | T70: =Inventory_List_Table3[[#This Row],[LND ROUND]]*12 -> 468 | U70: =Inventory_List_Table3[[#This Row],[AQ]]*Inventory_List_Table3[[#This Row],[Q]] -> 111.11111 | V70: OA | W70: XN | X70: =Inventory_List_Table3[[#This Row],[H CM]]*Inventory_List_Table3[[#This Row],[W CM]]*4+Inventory_List_Table3[[#This Row],[D CM ]]*Inventory_List_Table3[[#This Row],[D CM ]] -> 2064 | Y70: =Inventory_List_Table3[[#This Row],[Per piece MXN$]]/X70*10000 -> 2422.4806
A71: 70 | C71: CRIS GREY POL | D71: EM82570XE | E71: 1 | F71: 3 | G71: 35 | H71: 12 | I71: 12 | J71: 440 | K71: =Inventory_List_Table3[[#This Row],[Q]]*Inventory_List_Table3[[#This Row],[Per piece MXN$]] -> 440 | L71: =Inventory_List_Table3[[#This Row],[KG]]*2.20462 -> 6.61386 | M71: =Inventory_List_Table3[[#This Row],[H CM]]/2.54 -> 13.779528 | N71: =Inventory_List_Table3[[#This Row],[W CM]]/2.54 -> 4.7244094 | O71: =Inventory_List_Table3[[#This Row],[D CM ]]/2.54 -> 4.7244094 | P71: =Inventory_List_Table3[[#This Row],[Per piece MXN$]]/$U$2 -> 24.444444 | Q71: =IF(MOD(P71,1)>0.4,ROUNDUP(P71,0),ROUNDDOWN(P71,0)) -> 25 | R71: =Inventory_List_Table3[[#This Row],[AQ ROUND]]*1.4 -> 35 | S71: =IF(MOD(R71,1)>0.4,ROUNDUP(R71,0),ROUNDDOWN(R71,0)) -> 35 | T71: =Inventory_List_Table3[[#This Row],[LND ROUND]]*12 -> 420 | U71: =Inventory_List_Table3[[#This Row],[AQ]]*Inventory_List_Table3[[#This Row],[Q]] -> 24.444444 | V71: OE | W71: XE | X71: =Inventory_List_Table3[[#This Row],[H CM]]*Inventory_List_Table3[[#This Row],[W CM]]*4+Inventory_List_Table3[[#This Row],[D CM ]]*Inventory_List_Table3[[#This Row],[D CM ]] -> 1824 | Y71: =Inventory_List_Table3[[#This Row],[Per piece MXN$]]/X71*10000 -> 2412.2807
A72: 71 | C72: CRIS GREY POL | D72: EM82571ON | E72: 4 | F72: 3 | G72: 30 | H72: 12 | I72: 12 | J72: 380 | K72: =Inventory_List_Table3[[#This Row],[Q]]*Inventory_List_Table3[[#This Row],[Per piece MXN$]] -> 1520 | L72: =Inventory_List_Table3[[#This Row],[KG]]*2.20462 -> 6.61386 | M72: =Inventory_List_Table3[[#This Row],[H CM]]/2.54 -> 11.811024 | N72: =Inventory_List_Table3[[#This Row],[W CM]]/2.54 -> 4.7244094 | O72: =Inventory_List_Table3[[#This Row],[D CM ]]/2.54 -> 4.7244094 | P72: =Inventory_List_Table3[[#This Row],[Per piece MXN$]]/$U$2 -> 21.111111 | Q72: =IF(MOD(P72,1)>0.4,ROUNDUP(P72,0),ROUNDDOWN(P72,0)) -> 21 | R72: =Inventory_List_Table3[[#This Row],[AQ ROUND]]*1.4 -> 29.4 | S72: =IF(MOD(R72,1)>0.4,ROUNDUP(R72,0),ROUNDDOWN(R72,0)) -> 29 | T72: =Inventory_List_Table3[[#This Row],[LND ROUND]]*12 -> 348 | U72: =Inventory_List_Table3[[#This Row],[AQ]]*Inventory_List_Table3[[#This Row],[Q]] -> 84.444444 | V72: OM | W72: ON | X72: =Inventory_List_Table3[[#This Row],[H CM]]*Inventory_List_Table3[[#This Row],[W CM]]*4+Inventory_List_Table3[[#This Row],[D CM ]]*Inventory_List_Table3[[#This Row],[D CM ]] -> 1584 | Y72: =Inventory_List_Table3[[#This Row],[Per piece MXN$]]/X72*10000 -> 2398.9899
A73: 72 | C73: CRIS GREY REC MIRROR | D73: EM82572XNL | E73: 1 | F73: 30 | G73: 150 | H73: 80 | I73: 10 | J73: 5100 | K73: =Inventory_List_Table3[[#This Row],[Q]]*Inventory_List_Table3[[#This Row],[Per piece MXN$]] -> 5100 | L73: =Inventory_List_Table3[[#This Row],[KG]]*2.20462 -> 66.1386 | M73: =Inventory_List_Table3[[#This Row],[H CM]]/2.54 -> 59.055118 | N73: =Inventory_List_Table3[[#This Row],[W CM]]/2.54 -> 31.496063 | O73: =Inventory_List_Table3[[#This Row],[D CM ]]/2.54 -> 3.9370079 | P73: =Inventory_List_Table3[[#This Row],[Per piece MXN$]]/$U$2 -> 283.33333 | Q73: =IF(MOD(P73,1)>0.4,ROUNDUP(P73,0),ROUNDDOWN(P73,0)) -> 283 | R73: =Inventory_List_Table3[[#This Row],[AQ ROUND]]*1.4 -> 396.2 | S73: =IF(MOD(R73,1)>0.4,ROUNDUP(R73,0),ROUNDDOWN(R73,0)) -> 396 | T73: =Inventory_List_Table3[[#This Row],[LND ROUND]]*12 -> 4752 | U73: =Inventory_List_Table3[[#This Row],[AQ]]*Inventory_List_Table3[[#This Row],[Q]] -> 283.33333 | V73: OAX | W73: XNL | X73: =Inventory_List_Table3[[#This Row],[H CM]]*Inventory_List_Table3[[#This Row],[W CM]]+Inventory_List_Table3[[#This Row],[H CM]]*Inventory_List_Table3[[#This Row],[D CM ]]*2+Inventory_List_Table3[[#This Row],[W CM]]*Inventory_List_Table3[[#This Row],[D CM ]]*2 -> 16600 | Y73: =Inventory_List_Table3[[#This Row],[Per piece MXN$]]/X73*10000 -> 3072.2892
A74: 73 | C74: CRIS GREY RD MIRROR | D74: EM82573XOL | E74: 6 | F74: 13 | G74: 80 | H74: 80 | I74: 10 | J74: 4200 | K74: =Inventory_List_Table3[[#This Row],[Q]]*Inventory_List_Table3[[#This Row],[Per piece MXN$]] -> 25200 | L74: =Inventory_List_Table3[[#This Row],[KG]]*2.20462 -> 28.66006 | M74: =Inventory_List_Table3[[#This Row],[H CM]]/2.54 -> 31.496063 | N74: =Inventory_List_Table3[[#This Row],[W CM]]/2.54 -> 31.496063 | O74: =Inventory_List_Table3[[#This Row],[D CM ]]/2.54 -> 3.9370079 | P74: =Inventory_List_Table3[[#This Row],[Per piece MXN$]]/$U$2 -> 233.33333 | Q74: =IF(MOD(P74,1)>0.4,ROUNDUP(P74,0),ROUNDDOWN(P74,0)) -> 233 | R74: =Inventory_List_Table3[[#This Row],[AQ ROUND]]*1.4 -> 326.2 | S74: =IF(MOD(R74,1)>0.4,ROUNDUP(R74,0),ROUNDDOWN(R74,0)) -> 326 | T74: =Inventory_List_Table3[[#This Row],[LND ROUND]]*12 -> 3912 | U74: =Inventory_List_Table3[[#This Row],[AQ]]*Inventory_List_Table3[[#This Row],[Q]] -> 1400 | V74: OXX | W74: XOL | X74: =Inventory_List_Table3[[#This Row],[H CM]]*Inventory_List_Table3[[#This Row],[W CM]]+Inventory_List_Table3[[#This Row],[H CM]]*Inventory_List_Table3[[#This Row],[D CM ]]*2+Inventory_List_Table3[[#This Row],[W CM]]*Inventory_List_Table3[[#This Row],[D CM ]]*2 -> 9600 | Y74: =Inventory_List_Table3[[#This Row],[Per piece MXN$]]/X74*10000 -> 4375
A75: 74 | C75: CRIS GREY REC MIRROR | D75: EM82574OLE | E75: 5 | F75: 19 | G75: 110 | H75: 60 | I75: 10 | J75: 3400 | K75: =Inventory_List_Table3[[#This Row],[Q]]*Inventory_List_Table3[[#This Row],[Per piece MXN$]] -> 17000 | L75: =Inventory_List_Table3[[#This Row],[KG]]*2.20462 -> 41.88778 | M75: =Inventory_List_Table3[[#This Row],[H CM]]/2.54 -> 43.307087 | N75: =Inventory_List_Table3[[#This Row],[W CM]]/2.54 -> 23.622047 | O75: =Inventory_List_Table3[[#This Row],[D CM ]]/2.54 -> 3.9370079 | P75: =Inventory_List_Table3[[#This Row],[Per piece MXN$]]/$U$2 -> 188.88889 | Q75: =IF(MOD(P75,1)>0.4,ROUNDUP(P75,0),ROUNDDOWN(P75,0)) -> 189 | R75: =Inventory_List_Table3[[#This Row],[AQ ROUND]]*1.4 -> 264.6 | S75: =IF(MOD(R75,1)>0.4,ROUNDUP(R75,0),ROUNDDOWN(R75,0)) -> 265 | T75: =Inventory_List_Table3[[#This Row],[LND ROUND]]*12 -> 3180 | U75: =Inventory_List_Table3[[#This Row],[AQ]]*Inventory_List_Table3[[#This Row],[Q]] -> 944.44444 | V75: MAN | W75: OLE | X75: =Inventory_List_Table3[[#This Row],[H CM]]*Inventory_List_Table3[[#This Row],[W CM]]+Inventory_List_Table3[[#This Row],[H CM]]*Inventory_List_Table3[[#This Row],[D CM ]]*2+Inventory_List_Table3[[#This Row],[W CM]]*Inventory_List_Table3[[#This Row],[D CM ]]*2 -> 10000 | Y75: =Inventory_List_Table3[[#This Row],[Per piece MXN$]]/X75*10000 -> 3400
A76: 75 | C76: TEHUA/GREY DIAMOND TABLE | D76: EM82575LOX | E76: 1 | F76: 52 | G76: 86 | H76: 86 | I76: 50 | J76: 8000 | K76: =Inventory_List_Table3[[#This Row],[Q]]*Inventory_List_Table3[[#This Row],[Per piece MXN$]] -> 8000 | L76: =Inventory_List_Table3[[#This Row],[KG]]*2.20462 -> 114.64024 | M76: =Inventory_List_Table3[[#This Row],[H CM]]/2.54 -> 33.858268 | N76: =Inventory_List_Table3[[#This Row],[W CM]]/2.54 -> 33.858268 | O76: =Inventory_List_Table3[[#This Row],[D CM ]]/2.54 -> 19.685039 | P76: =Inventory_List_Table3[[#This Row],[Per piece MXN$]]/$U$2 -> 444.44444 | Q76: =IF(MOD(P76,1)>0.4,ROUNDUP(P76,0),ROUNDDOWN(P76,0)) -> 445 | R76: =Inventory_List_Table3[[#This Row],[AQ ROUND]]*1.4 -> 623 | S76: =IF(MOD(R76,1)>0.4,ROUNDUP(R76,0),ROUNDDOWN(R76,0)) -> 623 | T76: =Inventory_List_Table3[[#This Row],[LND ROUND]]*12 -> 7476 | U76: =Inventory_List_Table3[[#This Row],[AQ]]*Inventory_List_Table3[[#This Row],[Q]] -> 444.44444 | V76: HHE | W76: LOX | X76: =Inventory_List_Table3[[#This Row],[H CM]]*Inventory_List_Table3[[#This Row],[W CM]]*4+Inventory_List_Table3[[#This Row],[D CM ]]*Inventory_List_Table3[[#This Row],[D CM ]] -> 32084 | Y76: =Inventory_List_Table3[[#This Row],[Per piece MXN$]]/X76*10000 -> 2493.4547
A77: 76 | B77: 45954 | C77: AQUA SERP REC MIRROR | D77: EM82576XNL | E77: 2 | F77: 30 | G77: 150 | H77: 80 | I77: 10 | J77: 5100 | K77: =Inventory_List_Table3[[#This Row],[Q]]*Inventory_List_Table3[[#This Row],[Per piece MXN$]] -> 10200 | L77: =Inventory_List_Table3[[#This Row],[KG]]*2.20462 -> 66.1386 | M77: =Inventory_List_Table3[[#This Row],[H CM]]/2.54 -> 59.055118 | N77: =Inventory_List_Table3[[#This Row],[W CM]]/2.54 -> 31.496063 | O77: =Inventory_List_Table3[[#This Row],[D CM ]]/2.54 -> 3.9370079 | P77: =Inventory_List_Table3[[#This Row],[Per piece MXN$]]/$U$2 -> 283.33333 | Q77: =IF(MOD(P77,1)>0.4,ROUNDUP(P77,0),ROUNDDOWN(P77,0)) -> 283 | R77: =Inventory_List_Table3[[#This Row],[AQ ROUND]]*1.4 -> 396.2 | S77: =IF(MOD(R77,1)>0.4,ROUNDUP(R77,0),ROUNDDOWN(R77,0)) -> 396 | T77: =Inventory_List_Table3[[#This Row],[LND ROUND]]*12 -> 4752 | U77: =Inventory_List_Table3[[#This Row],[AQ]]*Inventory_List_Table3[[#This Row],[Q]] -> 566.66667 | V77: OAX | W77: XNL | X77: =Inventory_List_Table3[[#This Row],[H CM]]*Inventory_List_Table3[[#This Row],[W CM]]*4+Inventory_List_Table3[[#This Row],[D CM ]]*Inventory_List_Table3[[#This Row],[D CM ]] -> 48100 | Y77: =Inventory_List_Table3[[#This Row],[Per piece MXN$]]/X77*10000 -> 1060.2911
A78: 77 | B78: 45954 | C78: TEHUA GREY REC MIRROR | D78: EM82577XNL | E78: 4 | F78: 30 | G78: 150 | H78: 80 | I78: 10 | J78: 5100 | K78: =Inventory_List_Table3[[#This Row],[Q]]*Inventory_List_Table3[[#This Row],[Per piece MXN$]] -> 20400 | L78: =Inventory_List_Table3[[#This Row],[KG]]*2.20462 -> 66.1386 | M78: =Inventory_List_Table3[[#This Row],[H CM]]/2.54 -> 59.055118 | N78: =Inventory_List_Table3[[#This Row],[W CM]]/2.54 -> 31.496063 | O78: =Inventory_List_Table3[[#This Row],[D CM ]]/2.54 -> 3.9370079 | P78: =Inventory_List_Table3[[#This Row],[Per piece MXN$]]/$U$2 -> 283.33333 | Q78: =IF(MOD(P78,1)>0.4,ROUNDUP(P78,0),ROUNDDOWN(P78,0)) -> 283 | R78: =Inventory_List_Table3[[#This Row],[AQ ROUND]]*1.4 -> 396.2 | S78: =IF(MOD(R78,1)>0.4,ROUNDUP(R78,0),ROUNDDOWN(R78,0)) -> 396 | T78: =Inventory_List_Table3[[#This Row],[LND ROUND]]*12 -> 4752 | U78: =Inventory_List_Table3[[#This Row],[AQ]]*Inventory_List_Table3[[#This Row],[Q]] -> 1133.3333 | V78: OAX | W78: XNL | X78: =Inventory_List_Table3[[#This Row],[H CM]]*Inventory_List_Table3[[#This Row],[W CM]]*4+Inventory_List_Table3[[#This Row],[D CM ]]*Inventory_List_Table3[[#This Row],[D CM ]] -> 48100 | Y78: =Inventory_List_Table3[[#This Row],[Per piece MXN$]]/X78*10000 -> 1060.2911
A79: 78 | B79: 45954 | C79: CRISTALINO REC MIRROR | D79: EM82578ENM | E79: 1 | F79: 40 | G79: 183 | H79: 102 | I79: 10 | J79: 7600 | K79: =Inventory_List_Table3[[#This Row],[Q]]*Inventory_List_Table3[[#This Row],[Per piece MXN$]] -> 7600 | L79: =Inventory_List_Table3[[#This Row],[KG]]*2.20462 -> 88.1848 | M79: =Inventory_List_Table3[[#This Row],[H CM]]/2.54 -> 72.047244 | N79: =Inventory_List_Table3[[#This Row],[W CM]]/2.54 -> 40.15748 | O79: =Inventory_List_Table3[[#This Row],[D CM ]]/2.54 -> 3.9370079 | P79: =Inventory_List_Table3[[#This Row],[Per piece MXN$]]/$U$2 -> 422.22222 | Q79: =IF(MOD(P79,1)>0.4,ROUNDUP(P79,0),ROUNDDOWN(P79,0)) -> 422 | R79: =Inventory_List_Table3[[#This Row],[AQ ROUND]]*1.4 -> 590.8 | S79: =IF(MOD(R79,1)>0.4,ROUNDUP(R79,0),ROUNDDOWN(R79,0)) -> 591 | T79: =Inventory_List_Table3[[#This Row],[LND ROUND]]*12 -> 7092 | U79: =Inventory_List_Table3[[#This Row],[AQ]]*Inventory_List_Table3[[#This Row],[Q]] -> 422.22222 | V79: HOO | W79: ENM | X79: =Inventory_List_Table3[[#This Row],[H CM]]*Inventory_List_Table3[[#This Row],[W CM]]*4+Inventory_List_Table3[[#This Row],[D CM ]]*Inventory_List_Table3[[#This Row],[D CM ]] -> 74764 | Y79: =Inventory_List_Table3[[#This Row],[Per piece MXN$]]/X79*10000 -> 1016.532
A80: 79 | B80: 45954 | C80: CRIS GREY SQ MIRROR | D80: EM82579XOL | E80: 3 | F80: 27 | G80: 100 | H80: 100 | I80: 10 | J80: 4200 | K80: =Inventory_List_Table3[[#This Row],[Q]]*Inventory_List_Table3[[#This Row],[Per piece MXN$]] -> 12600 | L80: =Inventory_List_Table3[[#This Row],[KG]]*2.20462 -> 59.52474 | M80: =Inventory_List_Table3[[#This Row],[H CM]]/2.54 -> 39.370079 | N80: =Inventory_List_Table3[[#This Row],[W CM]]/2.54 -> 39.370079 | O80: =Inventory_List_Table3[[#This Row],[D CM ]]/2.54 -> 3.9370079 | P80: =Inventory_List_Table3[[#This Row],[Per piece MXN$]]/$U$2 -> 233.33333 | Q80: =IF(MOD(P80,1)>0.4,ROUNDUP(P80,0),ROUNDDOWN(P80,0)) -> 233 | R80: =Inventory_List_Table3[[#This Row],[AQ ROUND]]*1.4 -> 326.2 | S80: =IF(MOD(R80,1)>0.4,ROUNDUP(R80,0),ROUNDDOWN(R80,0)) -> 326 | T80: =Inventory_List_Table3[[#This Row],[LND ROUND]]*12 -> 3912 | U80: =Inventory_List_Table3[[#This Row],[AQ]]*Inventory_List_Table3[[#This Row],[Q]] -> 700 | V80: OXX | W80: XOL | X80: =Inventory_List_Table3[[#This Row],[H CM]]*Inventory_List_Table3[[#This Row],[W CM]]*4+Inventory_List_Table3[[#This Row],[D CM ]]*Inventory_List_Table3[[#This Row],[D CM ]] -> 40100 | Y80: =Inventory_List_Table3[[#This Row],[Per piece MXN$]]/X80*10000 -> 1047.3815
A81: 80 | B81: 45954 | C81: TEHUA GREY REC MIRROR | D81: EM82580OLE | E81: 2 | F81: 19 | G81: 110 | H81: 60 | I81: 10 | J81: 3400 | K81: =Inventory_List_Table3[[#This Row],[Q]]*Inventory_List_Table3[[#This Row],[Per piece MXN$]] -> 6800 | L81: =Inventory_List_Table3[[#This Row],[KG]]*2.20462 -> 41.88778 | M81: =Inventory_List_Table3[[#This Row],[H CM]]/2.54 -> 43.307087 | N81: =Inventory_List_Table3[[#This Row],[W CM]]/2.54 -> 23.622047 | O81: =Inventory_List_Table3[[#This Row],[D CM ]]/2.54 -> 3.9370079 | P81: =Inventory_List_Table3[[#This Row],[Per piece MXN$]]/$U$2 -> 188.88889 | Q81: =IF(MOD(P81,1)>0.4,ROUNDUP(P81,0),ROUNDDOWN(P81,0)) -> 189 | R81: =Inventory_List_Table3[[#This Row],[AQ ROUND]]*1.4 -> 264.6 | S81: =IF(MOD(R81,1)>0.4,ROUNDUP(R81,0),ROUNDDOWN(R81,0)) -> 265 | T81: =Inventory_List_Table3[[#This Row],[LND ROUND]]*12 -> 3180 | U81: =Inventory_List_Table3[[#This Row],[AQ]]*Inventory_List_Table3[[#This Row],[Q]] -> 377.77778 | V81: MAN | W81: OLE | X81: =Inventory_List_Table3[[#This Row],[H CM]]*Inventory_List_Table3[[#This Row],[W CM]]*4+Inventory_List_Table3[[#This Row],[D CM ]]*Inventory_List_Table3[[#This Row],[D CM ]] -> 26500 | Y81: =Inventory_List_Table3[[#This Row],[Per piece MXN$]]/X81*10000 -> 1283.0189
A82: 81 | B82: 45954 | C82: CRISTALINO CANOE | D82: EM82581OFO | E82: 1 | G82: 120 | H82: 22 | I82: 11 | J82: 3484 | K82: =Inventory_List_Table3[[#This Row],[Q]]*Inventory_List_Table3[[#This Row],[Per piece MXN$]] -> 3484 | L82: =Inventory_List_Table3[[#This Row],[KG]]*2.20462 -> 0 | M82: =Inventory_List_Table3[[#This Row],[H CM]]/2.54 -> 47.244094 | N82: =Inventory_List_Table3[[#This Row],[W CM]]/2.54 -> 8.6614173 | O82: =Inventory_List_Table3[[#This Row],[D CM ]]/2.54 -> 4.3307087 | P82: =Inventory_List_Table3[[#This Row],[Per piece MXN$]]/$U$2 -> 193.55556 | Q82: =IF(MOD(P82,1)>0.4,ROUNDUP(P82,0),ROUNDDOWN(P82,0)) -> 194 | R82: =Inventory_List_Table3[[#This Row],[AQ ROUND]]*1.4 -> 271.6 | S82: =IF(MOD(R82,1)>0.4,ROUNDUP(R82,0),ROUNDDOWN(R82,0)) -> 272 | T82: =Inventory_List_Table3[[#This Row],[LND ROUND]]*12 -> 3264 | U82: =Inventory_List_Table3[[#This Row],[AQ]]*Inventory_List_Table3[[#This Row],[Q]] -> 193.55556 | V82: MNH | W82: OFO | X82: =Inventory_List_Table3[[#This Row],[H CM]]*Inventory_List_Table3[[#This Row],[W CM]]*4+Inventory_List_Table3[[#This Row],[D CM ]]*Inventory_List_Table3[[#This Row],[D CM ]] -> 10681 | Y82: =Inventory_List_Table3[[#This Row],[Per piece MXN$]]/X82*10000 -> 3261.8669
A83: 82 | B83: 45954 | C83: CRISTALINO CANOE | D83: EM82582OLD | E83: 1 | G83: 115 | H83: 22 | I83: 11 | J83: 3339 | K83: =Inventory_List_Table3[[#This Row],[Q]]*Inventory_List_Table3[[#This Row],[Per piece MXN$]] -> 3339 | L83: =Inventory_List_Table3[[#This Row],[KG]]*2.20462 -> 0 | M83: =Inventory_List_Table3[[#This Row],[H CM]]/2.54 -> 45.275591 | N83: =Inventory_List_Table3[[#This Row],[W CM]]/2.54 -> 8.6614173 | O83: =Inventory_List_Table3[[#This Row],[D CM ]]/2.54 -> 4.3307087 | P83: =Inventory_List_Table3[[#This Row],[Per piece MXN$]]/$U$2 -> 185.5 | Q83: =IF(MOD(P83,1)>0.4,ROUNDUP(P83,0),ROUNDDOWN(P83,0)) -> 186 | R83: =Inventory_List_Table3[[#This Row],[AQ ROUND]]*1.4 -> 260.4 | S83: =IF(MOD(R83,1)>0.4,ROUNDUP(R83,0),ROUNDDOWN(R83,0)) -> 260 | T83: =Inventory_List_Table3[[#This Row],[LND ROUND]]*12 -> 3120 | U83: =Inventory_List_Table3[[#This Row],[AQ]]*Inventory_List_Table3[[#This Row],[Q]] -> 185.5 | V83: MAL | W83: OLD | X83: =Inventory_List_Table3[[#This Row],[H CM]]*Inventory_List_Table3[[#This Row],[W CM]]*4+Inventory_List_Table3[[#This Row],[D CM ]]*Inventory_List_Table3[[#This Row],[D CM ]] -> 10241 | Y83: =Inventory_List_Table3[[#This Row],[Per piece MXN$]]/X83*10000 -> 3260.4238
